Workbook

Sheet PRENOTAZIONI
A1: PRENOTAZIONI 2026
A2: IN | B2: OUT | C2: Notti | D2: CASA | E2: Ospite | F2: N. Ospiti | G2: Canale | H2: Prezzo | I2: ADR | J2: Comm. OTA | K2: Pagamento | L2: City Tax | M2: % Matteo | N2: Costo Pulizia | O2: Chi Pulisce | P2: Kit+Lav. | Q2: Rimborso | R2: NOTE | S2: #Sotto la Q | T2: LEGENDA | U2: #Casa Letiz | V2: #Casa nel B | W2: #Via San Ro | X2: #Via Cavour | Y2: #Miramare | Z2: #Agantonio | AA2: #Casa Bella | AB2: #Casa Verde | AC2: #Casa Nicol | AD2: #White Cott | AE2: #Villa Nell
A3: 46026 | B3: 46028 | C3: =IF(A3<>"",B3-A3,"") -> 2 | D3: Sotto la Quercia | E3: Matteo Locaputo | F3: 2 ad | G3: booking.com | H3: 223.64 | I3: =IF(AND(H3<>"",C3<>"",C3<>0),H3/C3,"") -> 111.82 | J3: =IF(AND(ISNUMBER(SEARCH("booking",G3)),OR(D3="Via San Rocco",D3="Via Cavour")),H3*0.165,IF(ISNUMBER(SEARCH("airbnb",G3)),H3*0.155,IF(ISNUMBER(SEARCH("booking",G3)),H3*0.15,""))) -> 33.546 | K3: VISA | L3: 4 | M3: =IF(H3<>"",H3*0.25,"") -> 55.91 | N3: 0 | O3: Matteo | P3: 10.38 | S3: =IF(AND($D3="Sotto la Quercia",$G3<>""),ROW(),"") -> 3 | T3: Booking.com | U3: =IF(AND($D3="Casa Letizia",$G3<>""),ROW(),"") | V3: =IF(AND($D3="Casa nel Borgo",$G3<>""),ROW(),"") | W3: =IF(AND($D3="Via San Rocco",$G3<>""),ROW(),"") | X3: =IF(AND($D3="Via Cavour",$G3<>""),ROW(),"") | Y3: =IF(AND($D3="Miramare",$G3<>""),ROW(),"") | Z3: =IF(AND($D3="Agantonio",$G3<>""),ROW(),"") | AA3: =IF(AND($D3="Casa Bella Gialla",$G3<>""),ROW(),"") | AB3: =IF(AND($D3="Casa Verde Oliva",$G3<>""),ROW(),"") | AC3: =IF(AND($D3="Casa Nicola",$G3<>""),ROW(),"") | AD3: =IF(AND($D3="White Cottage",$G3<>""),ROW(),"") | AE3: =IF(AND($D3="Villa Nella",$G3<>""),ROW(),"") | AF3: =IF(AND($D3="Villa Elena",$G3<>""),ROW(),"") | AG3: =IF(AND($D3="Sotto la Quercia",$G3=""),ROW(),"") | AH3: =IF(AND($D3="Villa Elena",$G3=""),ROW(),"") | AI3: =IF(AND($D3="Casa Letizia",$G3=""),ROW(),"") | AJ3: =IF(AND($D3="Casa nel Borgo",$G3=""),ROW(),"") | AK3: =IF(AND($D3="Via San Rocco",$G3=""),ROW(),"") | AL3: =IF(AND($D3="Via Cavour",$G3=""),ROW(),"") | AM3: =IF(AND($D3="Miramare",$G3=""),ROW(),"") | AN3: =IF(AND($D3="Agantonio",$G3=""),ROW(),"") | AO3: =IF(AND($D3="Casa Bella Gialla",$G3=""),ROW(),"") | AP3: =IF(AND($D3="Casa Verde Oliva",$G3=""),ROW(),"") | AQ3: =IF(AND($D3="Casa Nicola",$G3=""),ROW(),"") | AR3: =IF(AND($D3="White Cottage",$G3=""),ROW(),"") | AS3: =IF(AND($D3="Villa Nella",$G3=""),ROW(),"") | AT3: =IF(AND($D3="Nel Cuore di Lanciano",$G3<>""),ROW(),"") | AU3: =IF(AND($D3="Nel Cuore di Lanciano",$G3=""),ROW(),"")
A4: 46029 | B4: 46052 | C4: =IF(A4<>"",B4-A4,"") -> 23 | D4: Casa nel Borgo | E4: Filomena Adduocchio | F4: 1 ad | H4: 300 | I4: =IF(AND(H4<>"",C4<>"",C4<>0),H4/C4,"") -> 13.043478 | J4: 0 | K4: contanti | M4: =IF(H4<>"",H4*0.25,"") -> 75 | N4: 15 | O4: DIANA | P4: 10.38 | S4: =IF(AND($D4="Sotto la Quercia",$G4<>""),ROW(),"") | T4: Airbnb | U4: =IF(AND($D4="Casa Letizia",$G4<>""),ROW(),"") | V4: =IF(AND($D4="Casa nel Borgo",$G4<>""),ROW(),"") | W4: =IF(AND($D4="Via San Rocco",$G4<>""),ROW(),"") | X4: =IF(AND($D4="Via Cavour",$G4<>""),ROW(),"") | Y4: =IF(AND($D4="Miramare",$G4<>""),ROW(),"") | Z4: =IF(AND($D4="Agantonio",$G4<>""),ROW(),"") | AA4: =IF(AND($D4="Casa Bella Gialla",$G4<>""),ROW(),"") | AB4: =IF(AND($D4="Casa Verde Oliva",$G4<>""),ROW(),"") | AC4: =IF(AND($D4="Casa Nicola",$G4<>""),ROW(),"") | AD4: =IF(AND($D4="White Cottage",$G4<>""),ROW(),"") | AE4: =IF(AND($D4="Villa Nella",$G4<>""),ROW(),"") | AF4: =IF(AND($D4="Villa Elena",$G4<>""),ROW(),"") | AG4: =IF(AND($D4="Sotto la Quercia",$G4=""),ROW(),"") | AH4: =IF(AND($D4="Villa Elena",$G4=""),ROW(),"") | AI4: =IF(AND($D4="Casa Letizia",$G4=""),ROW(),"") | AJ4: =IF(AND($D4="Casa nel Borgo",$G4=""),ROW(),"") -> 4 | AK4: =IF(AND($D4="Via San Rocco",$G4=""),ROW(),"") | AL4: =IF(AND($D4="Via Cavour",$G4=""),ROW(),"") | AM4: =IF(AND($D4="Miramare",$G4=""),ROW(),"") | AN4: =IF(AND($D4="Agantonio",$G4=""),ROW(),"") | AO4: =IF(AND($D4="Casa Bella Gialla",$G4=""),ROW(),"") | AP4: =IF(AND($D4="Casa Verde Oliva",$G4=""),ROW(),"") | AQ4: =IF(AND($D4="Casa Nicola",$G4=""),ROW(),"") | AR4: =IF(AND($D4="White Cottage",$G4=""),ROW(),"") | AS4: =IF(AND($D4="Villa Nella",$G4=""),ROW(),"") | AT4: =IF(AND($D4="Nel Cuore di Lanciano",$G4<>""),ROW(),"") | AU4: =IF(AND($D4="Nel Cuore di Lanciano",$G4=""),ROW(),"")
A5: 46038 | B5: 46040 | C5: =IF(A5<>"",B5-A5,"") -> 2 | D5: Villa Elena | E5: Giovanni Simone | F5: 4 ad | G5: diretta | H5: 200 | I5: =IF(AND(H5<>"",C5<>"",C5<>0),H5/C5,"") -> 100 | J5: 0 | K5: MASTER | L5: 8 | M5: =IF(H5<>"",H5*0.25,"") -> 50 | N5: 15 | O5: DIANA | P5: 22.24 | S5: =IF(AND($D5="Sotto la Quercia",$G5<>""),ROW(),"") | T5: Diretta | U5: =IF(AND($D5="Casa Letizia",$G5<>""),ROW(),"") | V5: =IF(AND($D5="Casa nel Borgo",$G5<>""),ROW(),"") | W5: =IF(AND($D5="Via San Rocco",$G5<>""),ROW(),"") | X5: =IF(AND($D5="Via Cavour",$G5<>""),ROW(),"") | Y5: =IF(AND($D5="Miramare",$G5<>""),ROW(),"") | Z5: =IF(AND($D5="Agantonio",$G5<>""),ROW(),"") | AA5: =IF(AND($D5="Casa Bella Gialla",$G5<>""),ROW(),"") | AB5: =IF(AND($D5="Casa Verde Oliva",$G5<>""),ROW(),"") | AC5: =IF(AND($D5="Casa Nicola",$G5<>""),ROW(),"") | AD5: =IF(AND($D5="White Cottage",$G5<>""),ROW(),"") | AE5: =IF(AND($D5="Villa Nella",$G5<>""),ROW(),"") | AF5: =IF(AND($D5="Villa Elena",$G5<>""),ROW(),"") -> 5 | AG5: =IF(AND($D5="Sotto la Quercia",$G5=""),ROW(),"") | AH5: =IF(AND($D5="Villa Elena",$G5=""),ROW(),"") | AI5: =IF(AND($D5="Casa Letizia",$G5=""),ROW(),"") | AJ5: =IF(AND($D5="Casa nel Borgo",$G5=""),ROW(),"") | AK5: =IF(AND($D5="Via San Rocco",$G5=""),ROW(),"") | AL5: =IF(AND($D5="Via Cavour",$G5=""),ROW(),"") | AM5: =IF(AND($D5="Miramare",$G5=""),ROW(),"") | AN5: =IF(AND($D5="Agantonio",$G5=""),ROW(),"") | AO5: =IF(AND($D5="Casa Bella Gialla",$G5=""),ROW(),"") | AP5: =IF(AND($D5="Casa Verde Oliva",$G5=""),ROW(),"") | AQ5: =IF(AND($D5="Casa Nicola",$G5=""),ROW(),"") | AR5: =IF(AND($D5="White Cottage",$G5=""),ROW(),"") | AS5: =IF(AND($D5="Villa Nella",$G5=""),ROW(),"") | AT5: =IF(AND($D5="Nel Cuore di Lanciano",$G5<>""),ROW(),"") | AU5: =IF(AND($D5="Nel Cuore di Lanciano",$G5=""),ROW(),"")
A6: 46053 | B6: 46055 | C6: =IF(A6<>"",B6-A6,"") -> 2 | D6: Via San Rocco | E6: Maria Proietti | F6: 2 ad | G6: booking.com | H6: 192.3 | I6: =IF(AND(H6<>"",C6<>"",C6<>0),H6/C6,"") -> 96.15 | J6: =IF(AND(ISNUMBER(SEARCH("booking",G6)),OR(D6="Via San Rocco",D6="Via Cavour")),H6*0.165,IF(ISNUMBER(SEARCH("airbnb",G6)),H6*0.155,IF(ISNUMBER(SEARCH("booking",G6)),H6*0.15,""))) -> 31.7295 | L6: 4 | M6: =IF(H6<>"",H6*0.1,"") -> 19.23 | S6: =IF(AND($D6="Sotto la Quercia",$G6<>""),ROW(),"") | T6: Via San Rocco/Cavour | U6: =IF(AND($D6="Casa Letizia",$G6<>""),ROW(),"") | V6: =IF(AND($D6="Casa nel Borgo",$G6<>""),ROW(),"") | W6: =IF(AND($D6="Via San Rocco",$G6<>""),ROW(),"") -> 6 | X6: =IF(AND($D6="Via Cavour",$G6<>""),ROW(),"") | Y6: =IF(AND($D6="Miramare",$G6<>""),ROW(),"") | Z6: =IF(AND($D6="Agantonio",$G6<>""),ROW(),"") | AA6: =IF(AND($D6="Casa Bella Gialla",$G6<>""),ROW(),"") | AB6: =IF(AND($D6="Casa Verde Oliva",$G6<>""),ROW(),"") | AC6: =IF(AND($D6="Casa Nicola",$G6<>""),ROW(),"") | AD6: =IF(AND($D6="White Cottage",$G6<>""),ROW(),"") | AE6: =IF(AND($D6="Villa Nella",$G6<>""),ROW(),"") | AF6: =IF(AND($D6="Villa Elena",$G6<>""),ROW(),"") | AG6: =IF(AND($D6="Sotto la Quercia",$G6=""),ROW(),"") | AH6: =IF(AND($D6="Villa Elena",$G6=""),ROW(),"") | AI6: =IF(AND($D6="Casa Letizia",$G6=""),ROW(),"") | AJ6: =IF(AND($D6="Casa nel Borgo",$G6=""),ROW(),"") | AK6: =IF(AND($D6="Via San Rocco",$G6=""),ROW(),"") | AL6: =IF(AND($D6="Via Cavour",$G6=""),ROW(),"") | AM6: =IF(AND($D6="Miramare",$G6=""),ROW(),"") | AN6: =IF(AND($D6="Agantonio",$G6=""),ROW(),"") | AO6: =IF(AND($D6="Casa Bella Gialla",$G6=""),ROW(),"") | AP6: =IF(AND($D6="Casa Verde Oliva",$G6=""),ROW(),"") | AQ6: =IF(AND($D6="Casa Nicola",$G6=""),ROW(),"") | AR6: =IF(AND($D6="White Cottage",$G6=""),ROW(),"") | AS6: =IF(AND($D6="Villa Nella",$G6=""),ROW(),"") | AT6: =IF(AND($D6="Nel Cuore di Lanciano",$G6<>""),ROW(),"") | AU6: =IF(AND($D6="Nel Cuore di Lanciano",$G6=""),ROW(),"")
A7: 46055 | B7: 46064 | C7: =IF(A7<>"",B7-A7,"") -> 9 | D7: Casa nel Borgo | E7: Filomena Adduocchio | F7: 1 ad | H7: 300 | I7: =IF(AND(H7<>"",C7<>"",C7<>0),H7/C7,"") -> 33.333333 | J7: 0 | K7: contanti | M7: =IF(H7<>"",H7*0.25,"") -> 75 | N7: 15 | O7: DIANA | P7: 10.38 | S7: =IF(AND($D7="Sotto la Quercia",$G7<>""),ROW(),"") | T7: NON RIMBORSABILE | U7: =IF(AND($D7="Casa Letizia",$G7<>""),ROW(),"") | V7: =IF(AND($D7="Casa nel Borgo",$G7<>""),ROW(),"") | W7: =IF(AND($D7="Via San Rocco",$G7<>""),ROW(),"") | X7: =IF(AND($D7="Via Cavour",$G7<>""),ROW(),"") | Y7: =IF(AND($D7="Miramare",$G7<>""),ROW(),"") | Z7: =IF(AND($D7="Agantonio",$G7<>""),ROW(),"") | AA7: =IF(AND($D7="Casa Bella Gialla",$G7<>""),ROW(),"") | AB7: =IF(AND($D7="Casa Verde Oliva",$G7<>""),ROW(),"") | AC7: =IF(AND($D7="Casa Nicola",$G7<>""),ROW(),"") | AD7: =IF(AND($D7="White Cottage",$G7<>""),ROW(),"") | AE7: =IF(AND($D7="Villa Nella",$G7<>""),ROW(),"") | AF7: =IF(AND($D7="Villa Elena",$G7<>""),ROW(),"") | AG7: =IF(AND($D7="Sotto la Quercia",$G7=""),ROW(),"") | AH7: =IF(AND($D7="Villa Elena",$G7=""),ROW(),"") | AI7: =IF(AND($D7="Casa Letizia",$G7=""),ROW(),"") | AJ7: =IF(AND($D7="Casa nel Borgo",$G7=""),ROW(),"") -> 7 | AK7: =IF(AND($D7="Via San Rocco",$G7=""),ROW(),"") | AL7: =IF(AND($D7="Via Cavour",$G7=""),ROW(),"") | AM7: =IF(AND($D7="Miramare",$G7=""),ROW(),"") | AN7: =IF(AND($D7="Agantonio",$G7=""),ROW(),"") | AO7: =IF(AND($D7="Casa Bella Gialla",$G7=""),ROW(),"") | AP7: =IF(AND($D7="Casa Verde Oliva",$G7=""),ROW(),"") | AQ7: =IF(AND($D7="Casa Nicola",$G7=""),ROW(),"") | AR7: =IF(AND($D7="White Cottage",$G7=""),ROW(),"") | AS7: =IF(AND($D7="Villa Nella",$G7=""),ROW(),"") | AT7: =IF(AND($D7="Nel Cuore di Lanciano",$G7<>""),ROW(),"") | AU7: =IF(AND($D7="Nel Cuore di Lanciano",$G7=""),ROW(),"")
A8: 46056 | B8: 46058 | C8: =IF(A8<>"",B8-A8,"") -> 2 | D8: Villa Elena | E8: Monia Cardo | F8: 1 ad | H8: 162 | I8: =IF(AND(H8<>"",C8<>"",C8<>0),H8/C8,"") -> 81 | J8: 0 | K8: contanti | M8: =IF(H8<>"",H8*0.25,"") -> 40.5 | N8: 20 | O8: DIANA | P8: 10.38 | S8: =IF(AND($D8="Sotto la Quercia",$G8<>""),ROW(),"") | T8: =IF($D8="Villa Elena",COUNTIF($D$3:$D8,"Villa Elena"),"") -> 2 | U8: =IF(AND($D8="Casa Letizia",$G8<>""),ROW(),"") | V8: =IF(AND($D8="Casa nel Borgo",$G8<>""),ROW(),"") | W8: =IF(AND($D8="Via San Rocco",$G8<>""),ROW(),"") | X8: =IF(AND($D8="Via Cavour",$G8<>""),ROW(),"") | Y8: =IF(AND($D8="Miramare",$G8<>""),ROW(),"") | Z8: =IF(AND($D8="Agantonio",$G8<>""),ROW(),"") | AA8: =IF(AND($D8="Casa Bella Gialla",$G8<>""),ROW(),"") | AB8: =IF(AND($D8="Casa Verde Oliva",$G8<>""),ROW(),"") | AC8: =IF(AND($D8="Casa Nicola",$G8<>""),ROW(),"") | AD8: =IF(AND($D8="White Cottage",$G8<>""),ROW(),"") | AE8: =IF(AND($D8="Villa Nella",$G8<>""),ROW(),"") | AF8: =IF(AND($D8="Villa Elena",$G8<>""),ROW(),"") | AG8: =IF(AND($D8="Sotto la Quercia",$G8=""),ROW(),"") | AH8: =IF(AND($D8="Villa Elena",$G8=""),ROW(),"") -> 8 | AI8: =IF(AND($D8="Casa Letizia",$G8=""),ROW(),"") | AJ8: =IF(AND($D8="Casa nel Borgo",$G8=""),ROW(),"") | AK8: =IF(AND($D8="Via San Rocco",$G8=""),ROW(),"") | AL8: =IF(AND($D8="Via Cavour",$G8=""),ROW(),"") | AM8: =IF(AND($D8="Miramare",$G8=""),ROW(),"") | AN8: =IF(AND($D8="Agantonio",$G8=""),ROW(),"") | AO8: =IF(AND($D8="Casa Bella Gialla",$G8=""),ROW(),"") | AP8: =IF(AND($D8="Casa Verde Oliva",$G8=""),ROW(),"") | AQ8: =IF(AND($D8="Casa Nicola",$G8=""),ROW(),"") | AR8: =IF(AND($D8="White Cottage",$G8=""),ROW(),"") | AS8: =IF(AND($D8="Villa Nella",$G8=""),ROW(),"") | AT8: =IF(AND($D8="Nel Cuore di Lanciano",$G8<>""),ROW(),"") | AU8: =IF(AND($D8="Nel Cuore di Lanciano",$G8=""),ROW(),"")
A9: 46066 | B9: 46072 | C9: =IF(A9<>"",B9-A9,"") -> 6 | D9: Casa nel Borgo | E9: Cornelia Bruckner | F9: 2 ad | G9: booking.com | H9: 475.13 | I9: =IF(AND(H9<>"",C9<>"",C9<>0),H9/C9,"") -> 79.188333 | J9: =IF(AND(ISNUMBER(SEARCH("booking",G9)),OR(D9="Via San Rocco",D9="Via Cavour")),H9*0.165,IF(ISNUMBER(SEARCH("airbnb",G9)),H9*0.155,IF(ISNUMBER(SEARCH("booking",G9)),H9*0.15,""))) -> 71.2695 | K9: VISA | L9: 4 | M9: =IF(H9<>"",H9*0.25,"") -> 118.7825 | N9: 30 | O9: DUSHA | P9: 10.38 | R9: NON RIMBORSABILE | S9: =IF(AND($D9="Sotto la Quercia",$G9<>""),ROW(),"") | T9: =IF($D9="Villa Elena",COUNTIF($D$3:$D9,"Villa Elena"),"") | U9: =IF(AND($D9="Casa Letizia",$G9<>""),ROW(),"") | V9: =IF(AND($D9="Casa nel Borgo",$G9<>""),ROW(),"") -> 9 | W9: =IF(AND($D9="Via San Rocco",$G9<>""),ROW(),"") | X9: =IF(AND($D9="Via Cavour",$G9<>""),ROW(),"") | Y9: =IF(AND($D9="Miramare",$G9<>""),ROW(),"") | Z9: =IF(AND($D9="Agantonio",$G9<>""),ROW(),"") | AA9: =IF(AND($D9="Casa Bella Gialla",$G9<>""),ROW(),"") | AB9: =IF(AND($D9="Casa Verde Oliva",$G9<>""),ROW(),"") | AC9: =IF(AND($D9="Casa Nicola",$G9<>""),ROW(),"") | AD9: =IF(AND($D9="White Cottage",$G9<>""),ROW(),"") | AE9: =IF(AND($D9="Villa Nella",$G9<>""),ROW(),"") | AF9: =IF(AND($D9="Villa Elena",$G9<>""),ROW(),"") | AG9: =IF(AND($D9="Sotto la Quercia",$G9=""),ROW(),"") | AH9: =IF(AND($D9="Villa Elena",$G9=""),ROW(),"") | AI9: =IF(AND($D9="Casa Letizia",$G9=""),ROW(),"") | AJ9: =IF(AND($D9="Casa nel Borgo",$G9=""),ROW(),"") | AK9: =IF(AND($D9="Via San Rocco",$G9=""),ROW(),"") | AL9: =IF(AND($D9="Via Cavour",$G9=""),ROW(),"") | AM9: =IF(AND($D9="Miramare",$G9=""),ROW(),"") | AN9: =IF(AND($D9="Agantonio",$G9=""),ROW(),"") | AO9: =IF(AND($D9="Casa Bella Gialla",$G9=""),ROW(),"") | AP9: =IF(AND($D9="Casa Verde Oliva",$G9=""),ROW(),"") | AQ9: =IF(AND($D9="Casa Nicola",$G9=""),ROW(),"") | AR9: =IF(AND($D9="White Cottage",$G9=""),ROW(),"") | AS9: =IF(AND($D9="Villa Nella",$G9=""),ROW(),"") | AT9: =IF(AND($D9="Nel Cuore di Lanciano",$G9<>""),ROW(),"") | AU9: =IF(AND($D9="Nel Cuore di Lanciano",$G9=""),ROW(),"")
A10: 46072 | B10: 46089 | C10: =IF(A10<>"",B10-A10,"") -> 17 | D10: Casa nel Borgo | E10: Filomena Adduocchio | F10: 1 ad | H10: 300 | I10: =IF(AND(H10<>"",C10<>"",C10<>0),H10/C10,"") -> 17.647059 | J10: 0 | K10: contanti | M10: =IF(H10<>"",H10*0.25,"") -> 75 | N10: 20 | O10: DUSHA | P10: 10.38 | S10: =IF(AND($D10="Sotto la Quercia",$G10<>""),ROW(),"") | T10: =IF($D10="Villa Elena",COUNTIF($D$3:$D10,"Villa Elena"),"") | U10: =IF(AND($D10="Casa Letizia",$G10<>""),ROW(),"") | V10: =IF(AND($D10="Casa nel Borgo",$G10<>""),ROW(),"") | W10: =IF(AND($D10="Via San Rocco",$G10<>""),ROW(),"") | X10: =IF(AND($D10="Via Cavour",$G10<>""),ROW(),"") | Y10: =IF(AND($D10="Miramare",$G10<>""),ROW(),"") | Z10: =IF(AND($D10="Agantonio",$G10<>""),ROW(),"") | AA10: =IF(AND($D10="Casa Bella Gialla",$G10<>""),ROW(),"") | AB10: =IF(AND($D10="Casa Verde Oliva",$G10<>""),ROW(),"") | AC10: =IF(AND($D10="Casa Nicola",$G10<>""),ROW(),"") | AD10: =IF(AND($D10="White Cottage",$G10<>""),ROW(),"") | AE10: =IF(AND($D10="Villa Nella",$G10<>""),ROW(),"") | AF10: =IF(AND($D10="Villa Elena",$G10<>""),ROW(),"") | AG10: =IF(AND($D10="Sotto la Quercia",$G10=""),ROW(),"") | AH10: =IF(AND($D10="Villa Elena",$G10=""),ROW(),"") | AI10: =IF(AND($D10="Casa Letizia",$G10=""),ROW(),"") | AJ10: =IF(AND($D10="Casa nel Borgo",$G10=""),ROW(),"") -> 10 | AK10: =IF(AND($D10="Via San Rocco",$G10=""),ROW(),"") | AL10: =IF(AND($D10="Via Cavour",$G10=""),ROW(),"") | AM10: =IF(AND($D10="Miramare",$G10=""),ROW(),"") | AN10: =IF(AND($D10="Agantonio",$G10=""),ROW(),"") | AO10: =IF(AND($D10="Casa Bella Gialla",$G10=""),ROW(),"") | AP10: =IF(AND($D10="Casa Verde Oliva",$G10=""),ROW(),"") | AQ10: =IF(AND($D10="Casa Nicola",$G10=""),ROW(),"") | AR10: =IF(AND($D10="White Cottage",$G10=""),ROW(),"") | AS10: =IF(AND($D10="Villa Nella",$G10=""),ROW(),"") | AT10: =IF(AND($D10="Nel Cuore di Lanciano",$G10<>""),ROW(),"") | AU10: =IF(AND($D10="Nel Cuore di Lanciano",$G10=""),ROW(),"")
A11: 46091 | B11: 46093 | C11: =IF(A11<>"",B11-A11,"") -> 2 | D11: Villa Elena | E11: Monia Cardo | F11: 1 ad | H11: 162 | I11: =IF(AND(H11<>"",C11<>"",C11<>0),H11/C11,"") -> 81 | J11: 0 | K11: contanti | M11: =IF(H11<>"",H11*0.25,"") -> 40.5 | N11: 0 | O11: MATTEO | P11: 10.38 | S11: =IF(AND($D11="Sotto la Quercia",$G11<>""),ROW(),"") | T11: =IF($D11="Villa Elena",COUNTIF($D$3:$D11,"Villa Elena"),"") -> 3 | U11: =IF(AND($D11="Casa Letizia",$G11<>""),ROW(),"") | V11: =IF(AND($D11="Casa nel Borgo",$G11<>""),ROW(),"") | W11: =IF(AND($D11="Via San Rocco",$G11<>""),ROW(),"") | X11: =IF(AND($D11="Via Cavour",$G11<>""),ROW(),"") | Y11: =IF(AND($D11="Miramare",$G11<>""),ROW(),"") | Z11: =IF(AND($D11="Agantonio",$G11<>""),ROW(),"") | AA11: =IF(AND($D11="Casa Bella Gialla",$G11<>""),ROW(),"") | AB11: =IF(AND($D11="Casa Verde Oliva",$G11<>""),ROW(),"") | AC11: =IF(AND($D11="Casa Nicola",$G11<>""),ROW(),"") | AD11: =IF(AND($D11="White Cottage",$G11<>""),ROW(),"") | AE11: =IF(AND($D11="Villa Nella",$G11<>""),ROW(),"") | AF11: =IF(AND($D11="Villa Elena",$G11<>""),ROW(),"") | AG11: =IF(AND($D11="Sotto la Quercia",$G11=""),ROW(),"") | AH11: =IF(AND($D11="Villa Elena",$G11=""),ROW(),"") -> 11 | AI11: =IF(AND($D11="Casa Letizia",$G11=""),ROW(),"") | AJ11: =IF(AND($D11="Casa nel Borgo",$G11=""),ROW(),"") | AK11: =IF(AND($D11="Via San Rocco",$G11=""),ROW(),"") | AL11: =IF(AND($D11="Via Cavour",$G11=""),ROW(),"") | AM11: =IF(AND($D11="Miramare",$G11=""),ROW(),"") | AN11: =IF(AND($D11="Agantonio",$G11=""),ROW(),"") | AO11: =IF(AND($D11="Casa Bella Gialla",$G11=""),ROW(),"") | AP11: =IF(AND($D11="Casa Verde Oliva",$G11=""),ROW(),"") | AQ11: =IF(AND($D11="Casa Nicola",$G11=""),ROW(),"") | AR11: =IF(AND($D11="White Cottage",$G11=""),ROW(),"") | AS11: =IF(AND($D11="Villa Nella",$G11=""),ROW(),"") | AT11: =IF(AND($D11="Nel Cuore di Lanciano",$G11<>""),ROW(),"") | AU11: =IF(AND($D11="Nel Cuore di Lanciano",$G11=""),ROW(),"")
A12: 46097 | B12: 46110 | C12: =IF(A12<>"",B12-A12,"") -> 13 | D12: Casa nel Borgo | E12: Filomena Adduocchio | F12: 2 ad | H12: 300 | I12: =IF(AND(H12<>"",C12<>"",C12<>0),H12/C12,"") -> 23.076923 | J12: 0 | K12: contanti | M12: =IF(H12<>"",H12*0.25,"") -> 75 | N12: 15 | O12: DIANA | P12: 10.38 | S12: =IF(AND($D12="Sotto la Quercia",$G12<>""),ROW(),"") | T12: =IF($D12="Villa Elena",COUNTIF($D$3:$D12,"Villa Elena"),"") | U12: =IF(AND($D12="Casa Letizia",$G12<>""),ROW(),"") | V12: =IF(AND($D12="Casa nel Borgo",$G12<>""),ROW(),"") | W12: =IF(AND($D12="Via San Rocco",$G12<>""),ROW(),"") | X12: =IF(AND($D12="Via Cavour",$G12<>""),ROW(),"") | Y12: =IF(AND($D12="Miramare",$G12<>""),ROW(),"") | Z12: =IF(AND($D12="Agantonio",$G12<>""),ROW(),"") | AA12: =IF(AND($D12="Casa Bella Gialla",$G12<>""),ROW(),"") | AB12: =IF(AND($D12="Casa Verde Oliva",$G12<>""),ROW(),"") | AC12: =IF(AND($D12="Casa Nicola",$G12<>""),ROW(),"") | AD12: =IF(AND($D12="White Cottage",$G12<>""),ROW(),"") | AE12: =IF(AND($D12="Villa Nella",$G12<>""),ROW(),"") | AF12: =IF(AND($D12="Villa Elena",$G12<>""),ROW(),"") | AG12: =IF(AND($D12="Sotto la Quercia",$G12=""),ROW(),"") | AH12: =IF(AND($D12="Villa Elena",$G12=""),ROW(),"") | AI12: =IF(AND($D12="Casa Letizia",$G12=""),ROW(),"") | AJ12: =IF(AND($D12="Casa nel Borgo",$G12=""),ROW(),"") -> 12 | AK12: =IF(AND($D12="Via San Rocco",$G12=""),ROW(),"") | AL12: =IF(AND($D12="Via Cavour",$G12=""),ROW(),"") | AM12: =IF(AND($D12="Miramare",$G12=""),ROW(),"") | AN12: =IF(AND($D12="Agantonio",$G12=""),ROW(),"") | AO12: =IF(AND($D12="Casa Bella Gialla",$G12=""),ROW(),"") | AP12: =IF(AND($D12="Casa Verde Oliva",$G12=""),ROW(),"") | AQ12: =IF(AND($D12="Casa Nicola",$G12=""),ROW(),"") | AR12: =IF(AND($D12="White Cottage",$G12=""),ROW(),"") | AS12: =IF(AND($D12="Villa Nella",$G12=""),ROW(),"") | AT12: =IF(AND($D12="Nel Cuore di Lanciano",$G12<>""),ROW(),"") | AU12: =IF(AND($D12="Nel Cuore di Lanciano",$G12=""),ROW(),"")
A13: 46105 | B13: 46109 | C13: =IF(A13<>"",B13-A13,"") -> 4 | D13: Via Cavour | E13: Flavia di Campli | F13: 1 ad | G13: booking.com | H13: 322.64 | I13: =IF(AND(H13<>"",C13<>"",C13<>0),H13/C13,"") -> 80.66 | J13: =IF(AND(ISNUMBER(SEARCH("booking",G13)),OR(D13="Via San Rocco",D13="Via Cavour")),H13*0.165,IF(ISNUMBER(SEARCH("airbnb",G13)),H13*0.155,IF(ISNUMBER(SEARCH("booking",G13)),H13*0.15,""))) -> 53.2356 | L13: 2 | M13: =IF(H13<>"",H13*0.1,"") -> 32.264 | S13: =IF(AND($D13="Sotto la Quercia",$G13<>""),ROW(),"") | T13: =IF($D13="Villa Elena",COUNTIF($D$3:$D13,"Villa Elena"),"") | U13: =IF(AND($D13="Casa Letizia",$G13<>""),ROW(),"") | V13: =IF(AND($D13="Casa nel Borgo",$G13<>""),ROW(),"") | W13: =IF(AND($D13="Via San Rocco",$G13<>""),ROW(),"") | X13: =IF(AND($D13="Via Cavour",$G13<>""),ROW(),"") -> 13 | Y13: =IF(AND($D13="Miramare",$G13<>""),ROW(),"") | Z13: =IF(AND($D13="Agantonio",$G13<>""),ROW(),"") | AA13: =IF(AND($D13="Casa Bella Gialla",$G13<>""),ROW(),"") | AB13: =IF(AND($D13="Casa Verde Oliva",$G13<>""),ROW(),"") | AC13: =IF(AND($D13="Casa Nicola",$G13<>""),ROW(),"") | AD13: =IF(AND($D13="White Cottage",$G13<>""),ROW(),"") | AE13: =IF(AND($D13="Villa Nella",$G13<>""),ROW(),"") | AF13: =IF(AND($D13="Villa Elena",$G13<>""),ROW(),"") | AG13: =IF(AND($D13="Sotto la Quercia",$G13=""),ROW(),"") | AH13: =IF(AND($D13="Villa Elena",$G13=""),ROW(),"") | AI13: =IF(AND($D13="Casa Letizia",$G13=""),ROW(),"") | AJ13: =IF(AND($D13="Casa nel Borgo",$G13=""),ROW(),"") | AK13: =IF(AND($D13="Via San Rocco",$G13=""),ROW(),"") | AL13: =IF(AND($D13="Via Cavour",$G13=""),ROW(),"") | AM13: =IF(AND($D13="Miramare",$G13=""),ROW(),"") | AN13: =IF(AND($D13="Agantonio",$G13=""),ROW(),"") | AO13: =IF(AND($D13="Casa Bella Gialla",$G13=""),ROW(),"") | AP13: =IF(AND($D13="Casa Verde Oliva",$G13=""),ROW(),"") | AQ13: =IF(AND($D13="Casa Nicola",$G13=""),ROW(),"") | AR13: =IF(AND($D13="White Cottage",$G13=""),ROW(),"") | AS13: =IF(AND($D13="Villa Nella",$G13=""),ROW(),"") | AT13: =IF(AND($D13="Nel Cuore di Lanciano",$G13<>""),ROW(),"") | AU13: =IF(AND($D13="Nel Cuore di Lanciano",$G13=""),ROW(),"")
A14: 46107 | B14: 46110 | C14: =IF(A14<>"",B14-A14,"") -> 3 | D14: Via San Rocco | E14: Simeno Riccomob | F14: 1 ad | G14: diretta | H14: 225 | I14: =IF(AND(H14<>"",C14<>"",C14<>0),H14/C14,"") -> 75 | J14: =IF(AND(ISNUMBER(SEARCH("booking",G14)),OR(D14="Via San Rocco",D14="Via Cavour")),H14*0.165,IF(ISNUMBER(SEARCH("airbnb",G14)),H14*0.155,IF(ISNUMBER(SEARCH("booking",G14)),H14*0.15,""))) | L14: 2 | M14: =IF(H14<>"",H14*0.1,"") -> 22.5 | S14: =IF(AND($D14="Sotto la Quercia",$G14<>""),ROW(),"") | T14: =IF($D14="Villa Elena",COUNTIF($D$3:$D14,"Villa Elena"),"") | U14: =IF(AND($D14="Casa Letizia",$G14<>""),ROW(),"") | V14: =IF(AND($D14="Casa nel Borgo",$G14<>""),ROW(),"") | W14: =IF(AND($D14="Via San Rocco",$G14<>""),ROW(),"") -> 14 | X14: =IF(AND($D14="Via Cavour",$G14<>""),ROW(),"") | Y14: =IF(AND($D14="Miramare",$G14<>""),ROW(),"") | Z14: =IF(AND($D14="Agantonio",$G14<>""),ROW(),"") | AA14: =IF(AND($D14="Casa Bella Gialla",$G14<>""),ROW(),"") | AB14: =IF(AND($D14="Casa Verde Oliva",$G14<>""),ROW(),"") | AC14: =IF(AND($D14="Casa Nicola",$G14<>""),ROW(),"") | AD14: =IF(AND($D14="White Cottage",$G14<>""),ROW(),"") | AE14: =IF(AND($D14="Villa Nella",$G14<>""),ROW(),"") | AF14: =IF(AND($D14="Villa Elena",$G14<>""),ROW(),"") | AG14: =IF(AND($D14="Sotto la Quercia",$G14=""),ROW(),"") | AH14: =IF(AND($D14="Villa Elena",$G14=""),ROW(),"") | AI14: =IF(AND($D14="Casa Letizia",$G14=""),ROW(),"") | AJ14: =IF(AND($D14="Casa nel Borgo",$G14=""),ROW(),"") | AK14: =IF(AND($D14="Via San Rocco",$G14=""),ROW(),"") | AL14: =IF(AND($D14="Via Cavour",$G14=""),ROW(),"") | AM14: =IF(AND($D14="Miramare",$G14=""),ROW(),"") | AN14: =IF(AND($D14="Agantonio",$G14=""),ROW(),"") | AO14: =IF(AND($D14="Casa Bella Gialla",$G14=""),ROW(),"") | AP14: =IF(AND($D14="Casa Verde Oliva",$G14=""),ROW(),"") | AQ14: =IF(AND($D14="Casa Nicola",$G14=""),ROW(),"") | AR14: =IF(AND($D14="White Cottage",$G14=""),ROW(),"") | AS14: =IF(AND($D14="Villa Nella",$G14=""),ROW(),"") | AT14: =IF(AND($D14="Nel Cuore di Lanciano",$G14<>""),ROW(),"") | AU14: =IF(AND($D14="Nel Cuore di Lanciano",$G14=""),ROW(),"")
A15: 46108 | B15: 46111 | C15: =IF(A15<>"",B15-A15,"") -> 3 | D15: Casa Bella Gialla | E15: Domenico Martorella | F15: 2 ad 1 b | G15: booking.com | H15: 202.65 | I15: =IF(AND(H15<>"",C15<>"",C15<>0),H15/C15,"") -> 67.55 | J15: =IF(AND(ISNUMBER(SEARCH("booking",G15)),OR(D15="Via San Rocco",D15="Via Cavour")),H15*0.165,IF(ISNUMBER(SEARCH("airbnb",G15)),H15*0.155,IF(ISNUMBER(SEARCH("booking",G15)),H15*0.15,""))) -> 30.3975 | K15: MASTER | L15: 4 | M15: =IF(H15<>"",H15*0.25,"") -> 50.6625 | N15: 30 | O15: DIANA | P15: 16.31 | S15: =IF(AND($D15="Sotto la Quercia",$G15<>""),ROW(),"") | T15: =IF($D15="Villa Elena",COUNTIF($D$3:$D15,"Villa Elena"),"") | U15: =IF(AND($D15="Casa Letizia",$G15<>""),ROW(),"") | V15: =IF(AND($D15="Casa nel Borgo",$G15<>""),ROW(),"") | W15: =IF(AND($D15="Via San Rocco",$G15<>""),ROW(),"") | X15: =IF(AND($D15="Via Cavour",$G15<>""),ROW(),"") | Y15: =IF(AND($D15="Miramare",$G15<>""),ROW(),"") | Z15: =IF(AND($D15="Agantonio",$G15<>""),ROW(),"") | AA15: =IF(AND($D15="Casa Bella Gialla",$G15<>""),ROW(),"") -> 15 | AB15: =IF(AND($D15="Casa Verde Oliva",$G15<>""),ROW(),"") | AC15: =IF(AND($D15="Casa Nicola",$G15<>""),ROW(),"") | AD15: =IF(AND($D15="White Cottage",$G15<>""),ROW(),"") | AE15: =IF(AND($D15="Villa Nella",$G15<>""),ROW(),"") | AF15: =IF(AND($D15="Villa Elena",$G15<>""),ROW(),"") | AG15: =IF(AND($D15="Sotto la Quercia",$G15=""),ROW(),"") | AH15: =IF(AND($D15="Villa Elena",$G15=""),ROW(),"") | AI15: =IF(AND($D15="Casa Letizia",$G15=""),ROW(),"") | AJ15: =IF(AND($D15="Casa nel Borgo",$G15=""),ROW(),"") | AK15: =IF(AND($D15="Via San Rocco",$G15=""),ROW(),"") | AL15: =IF(AND($D15="Via Cavour",$G15=""),ROW(),"") | AM15: =IF(AND($D15="Miramare",$G15=""),ROW(),"") | AN15: =IF(AND($D15="Agantonio",$G15=""),ROW(),"") | AO15: =IF(AND($D15="Casa Bella Gialla",$G15=""),ROW(),"") | AP15: =IF(AND($D15="Casa Verde Oliva",$G15=""),ROW(),"") | AQ15: =IF(AND($D15="Casa Nicola",$G15=""),ROW(),"") | AR15: =IF(AND($D15="White Cottage",$G15=""),ROW(),"") | AS15: =IF(AND($D15="Villa Nella",$G15=""),ROW(),"") | AT15: =IF(AND($D15="Nel Cuore di Lanciano",$G15<>""),ROW(),"") | AU15: =IF(AND($D15="Nel Cuore di Lanciano",$G15=""),ROW(),"")
A16: 46114 | B16: 46118 | C16: =IF(A16<>"",B16-A16,"") -> 4 | D16: Casa nel Borgo | E16: Tommaso Rossini | F16: 2 ad 1 b | G16: booking.com | H16: 383.08 | I16: =IF(AND(H16<>"",C16<>"",C16<>0),H16/C16,"") -> 95.77 | J16: =IF(AND(ISNUMBER(SEARCH("booking",G16)),OR(D16="Via San Rocco",D16="Via Cavour")),H16*0.165,IF(ISNUMBER(SEARCH("airbnb",G16)),H16*0.155,IF(ISNUMBER(SEARCH("booking",G16)),H16*0.15,""))) -> 57.462 | K16: BONIFICO | L16: 4 | M16: =IF(H16<>"",H16*0.25,"") -> 95.77 | N16: 20 | O16: JESSICA | P16: 16.31 | S16: =IF(AND($D16="Sotto la Quercia",$G16<>""),ROW(),"") | T16: =IF($D16="Villa Elena",COUNTIF($D$3:$D16,"Villa Elena"),"") | U16: =IF(AND($D16="Casa Letizia",$G16<>""),ROW(),"") | V16: =IF(AND($D16="Casa nel Borgo",$G16<>""),ROW(),"") -> 16 | W16: =IF(AND($D16="Via San Rocco",$G16<>""),ROW(),"") | X16: =IF(AND($D16="Via Cavour",$G16<>""),ROW(),"") | Y16: =IF(AND($D16="Miramare",$G16<>""),ROW(),"") | Z16: =IF(AND($D16="Agantonio",$G16<>""),ROW(),"") | AA16: =IF(AND($D16="Casa Bella Gialla",$G16<>""),ROW(),"") | AB16: =IF(AND($D16="Casa Verde Oliva",$G16<>""),ROW(),"") | AC16: =IF(AND($D16="Casa Nicola",$G16<>""),ROW(),"") | AD16: =IF(AND($D16="White Cottage",$G16<>""),ROW(),"") | AE16: =IF(AND($D16="Villa Nella",$G16<>""),ROW(),"") | AF16: =IF(AND($D16="Villa Elena",$G16<>""),ROW(),"") | AG16: =IF(AND($D16="Sotto la Quercia",$G16=""),ROW(),"") | AH16: =IF(AND($D16="Villa Elena",$G16=""),ROW(),"") | AI16: =IF(AND($D16="Casa Letizia",$G16=""),ROW(),"") | AJ16: =IF(AND($D16="Casa nel Borgo",$G16=""),ROW(),"") | AK16: =IF(AND($D16="Via San Rocco",$G16=""),ROW(),"") | AL16: =IF(AND($D16="Via Cavour",$G16=""),ROW(),"") | AM16: =IF(AND($D16="Miramare",$G16=""),ROW(),"") | AN16: =IF(AND($D16="Agantonio",$G16=""),ROW(),"") | AO16: =IF(AND($D16="Casa Bella Gialla",$G16=""),ROW(),"") | AP16: =IF(AND($D16="Casa Verde Oliva",$G16=""),ROW(),"") | AQ16: =IF(AND($D16="Casa Nicola",$G16=""),ROW(),"") | AR16: =IF(AND($D16="White Cottage",$G16=""),ROW(),"") | AS16: =IF(AND($D16="Villa Nella",$G16=""),ROW(),"") | AT16: =IF(AND($D16="Nel Cuore di Lanciano",$G16<>""),ROW(),"") | AU16: =IF(AND($D16="Nel Cuore di Lanciano",$G16=""),ROW(),"")
A17: 46115 | B17: 46118 | C17: =IF(A17<>"",B17-A17,"") -> 3 | D17: Agantonio | E17: Alessandro / Guido Peroni | F17: 2 ad | G17: booking.com | H17: 210.71 | I17: =IF(AND(H17<>"",C17<>"",C17<>0),H17/C17,"") -> 70.236667 | J17: =IF(AND(ISNUMBER(SEARCH("booking",G17)),OR(D17="Via San Rocco",D17="Via Cavour")),H17*0.165,IF(ISNUMBER(SEARCH("airbnb",G17)),H17*0.155,IF(ISNUMBER(SEARCH("booking",G17)),H17*0.15,""))) -> 31.6065 | K17: contanti | L17: 6 | M17: =IF(H17<>"",H17*0.25,"") -> 52.6775 | N17: 40 | O17: MARILENA | P17: 10.38 | S17: =IF(AND($D17="Sotto la Quercia",$G17<>""),ROW(),"") | T17: =IF($D17="Villa Elena",COUNTIF($D$3:$D17,"Villa Elena"),"") | U17: =IF(AND($D17="Casa Letizia",$G17<>""),ROW(),"") | V17: =IF(AND($D17="Casa nel Borgo",$G17<>""),ROW(),"") | W17: =IF(AND($D17="Via San Rocco",$G17<>""),ROW(),"") | X17: =IF(AND($D17="Via Cavour",$G17<>""),ROW(),"") | Y17: =IF(AND($D17="Miramare",$G17<>""),ROW(),"") | Z17: =IF(AND($D17="Agantonio",$G17<>""),ROW(),"") -> 17 | AA17: =IF(AND($D17="Casa Bella Gialla",$G17<>""),ROW(),"") | AB17: =IF(AND($D17="Casa Verde Oliva",$G17<>""),ROW(),"") | AC17: =IF(AND($D17="Casa Nicola",$G17<>""),ROW(),"") | AD17: =IF(AND($D17="White Cottage",$G17<>""),ROW(),"") | AE17: =IF(AND($D17="Villa Nella",$G17<>""),ROW(),"") | AF17: =IF(AND($D17="Villa Elena",$G17<>""),ROW(),"") | AG17: =IF(AND($D17="Sotto la Quercia",$G17=""),ROW(),"") | AH17: =IF(AND($D17="Villa Elena",$G17=""),ROW(),"") | AI17: =IF(AND($D17="Casa Letizia",$G17=""),ROW(),"") | AJ17: =IF(AND($D17="Casa nel Borgo",$G17=""),ROW(),"") | AK17: =IF(AND($D17="Via San Rocco",$G17=""),ROW(),"") | AL17: =IF(AND($D17="Via Cavour",$G17=""),ROW(),"") | AM17: =IF(AND($D17="Miramare",$G17=""),ROW(),"") | AN17: =IF(AND($D17="Agantonio",$G17=""),ROW(),"") | AO17: =IF(AND($D17="Casa Bella Gialla",$G17=""),ROW(),"") | AP17: =IF(AND($D17="Casa Verde Oliva",$G17=""),ROW(),"") | AQ17: =IF(AND($D17="Casa Nicola",$G17=""),ROW(),"") | AR17: =IF(AND($D17="White Cottage",$G17=""),ROW(),"") | AS17: =IF(AND($D17="Villa Nella",$G17=""),ROW(),"") | AT17: =IF(AND($D17="Nel Cuore di Lanciano",$G17<>""),ROW(),"") | AU17: =IF(AND($D17="Nel Cuore di Lanciano",$G17=""),ROW(),"")
A18: 46116 | B18: 46118 | C18: =IF(A18<>"",B18-A18,"") -> 2 | D18: Sotto la Quercia | E18: Giada Bruni | F18: 4 ad + 2 b | G18: booking.com | H18: 511.6 | I18: =IF(AND(H18<>"",C18<>"",C18<>0),H18/C18,"") -> 255.8 | J18: =IF(AND(ISNUMBER(SEARCH("booking",G18)),OR(D18="Via San Rocco",D18="Via Cavour")),H18*0.165,IF(ISNUMBER(SEARCH("airbnb",G18)),H18*0.155,IF(ISNUMBER(SEARCH("booking",G18)),H18*0.15,""))) -> 76.74 | K18: contanti | L18: 12 | M18: =IF(H18<>"",H18*0.25,"") -> 127.9 | N18: 30 | O18: RITA | P18: 38.55 | S18: =IF(AND($D18="Sotto la Quercia",$G18<>""),ROW(),"") -> 18 | T18: =IF($D18="Villa Elena",COUNTIF($D$3:$D18,"Villa Elena"),"") | U18: =IF(AND($D18="Casa Letizia",$G18<>""),ROW(),"") | V18: =IF(AND($D18="Casa nel Borgo",$G18<>""),ROW(),"") | W18: =IF(AND($D18="Via San Rocco",$G18<>""),ROW(),"") | X18: =IF(AND($D18="Via Cavour",$G18<>""),ROW(),"") | Y18: =IF(AND($D18="Miramare",$G18<>""),ROW(),"") | Z18: =IF(AND($D18="Agantonio",$G18<>""),ROW(),"") | AA18: =IF(AND($D18="Casa Bella Gialla",$G18<>""),ROW(),"") | AB18: =IF(AND($D18="Casa Verde Oliva",$G18<>""),ROW(),"") | AC18: =IF(AND($D18="Casa Nicola",$G18<>""),ROW(),"") | AD18: =IF(AND($D18="White Cottage",$G18<>""),ROW(),"") | AE18: =IF(AND($D18="Villa Nella",$G18<>""),ROW(),"") | AF18: =IF(AND($D18="Villa Elena",$G18<>""),ROW(),"") | AG18: =IF(AND($D18="Sotto la Quercia",$G18=""),ROW(),"") | AH18: =IF(AND($D18="Villa Elena",$G18=""),ROW(),"") | AI18: =IF(AND($D18="Casa Letizia",$G18=""),ROW(),"") | AJ18: =IF(AND($D18="Casa nel Borgo",$G18=""),ROW(),"") | AK18: =IF(AND($D18="Via San Rocco",$G18=""),ROW(),"") | AL18: =IF(AND($D18="Via Cavour",$G18=""),ROW(),"") | AM18: =IF(AND($D18="Miramare",$G18=""),ROW(),"") | AN18: =IF(AND($D18="Agantonio",$G18=""),ROW(),"") | AO18: =IF(AND($D18="Casa Bella Gialla",$G18=""),ROW(),"") | AP18: =IF(AND($D18="Casa Verde Oliva",$G18=""),ROW(),"") | AQ18: =IF(AND($D18="Casa Nicola",$G18=""),ROW(),"") | AR18: =IF(AND($D18="White Cottage",$G18=""),ROW(),"") | AS18: =IF(AND($D18="Villa Nella",$G18=""),ROW(),"") | AT18: =IF(AND($D18="Nel Cuore di Lanciano",$G18<>""),ROW(),"") | AU18: =IF(AND($D18="Nel Cuore di Lanciano",$G18=""),ROW(),"")
A19: 46116 | B19: 46119 | C19: =IF(A19<>"",B19-A19,"") -> 3 | D19: Via San Rocco | E19: Sharon Ilaria Zangirolami | F19: 2 ad 1 b | G19: booking.com | H19: 328.22 | I19: =IF(AND(H19<>"",C19<>"",C19<>0),H19/C19,"") -> 109.40667 | J19: =IF(AND(ISNUMBER(SEARCH("booking",G19)),OR(D19="Via San Rocco",D19="Via Cavour")),H19*0.165,IF(ISNUMBER(SEARCH("airbnb",G19)),H19*0.155,IF(ISNUMBER(SEARCH("booking",G19)),H19*0.15,""))) -> 54.1563 | L19: 4 | M19: =IF(H19<>"",H19*0.1,"") -> 32.822 | S19: =IF(AND($D19="Sotto la Quercia",$G19<>""),ROW(),"") | T19: =IF($D19="Villa Elena",COUNTIF($D$3:$D19,"Villa Elena"),"") | U19: =IF(AND($D19="Casa Letizia",$G19<>""),ROW(),"") | V19: =IF(AND($D19="Casa nel Borgo",$G19<>""),ROW(),"") | W19: =IF(AND($D19="Via San Rocco",$G19<>""),ROW(),"") -> 19 | X19: =IF(AND($D19="Via Cavour",$G19<>""),ROW(),"") | Y19: =IF(AND($D19="Miramare",$G19<>""),ROW(),"") | Z19: =IF(AND($D19="Agantonio",$G19<>""),ROW(),"") | AA19: =IF(AND($D19="Casa Bella Gialla",$G19<>""),ROW(),"") | AB19: =IF(AND($D19="Casa Verde Oliva",$G19<>""),ROW(),"") | AC19: =IF(AND($D19="Casa Nicola",$G19<>""),ROW(),"") | AD19: =IF(AND($D19="White Cottage",$G19<>""),ROW(),"") | AE19: =IF(AND($D19="Villa Nella",$G19<>""),ROW(),"") | AF19: =IF(AND($D19="Villa Elena",$G19<>""),ROW(),"") | AG19: =IF(AND($D19="Sotto la Quercia",$G19=""),ROW(),"") | AH19: =IF(AND($D19="Villa Elena",$G19=""),ROW(),"") | AI19: =IF(AND($D19="Casa Letizia",$G19=""),ROW(),"") | AJ19: =IF(AND($D19="Casa nel Borgo",$G19=""),ROW(),"") | AK19: =IF(AND($D19="Via San Rocco",$G19=""),ROW(),"") | AL19: =IF(AND($D19="Via Cavour",$G19=""),ROW(),"") | AM19: =IF(AND($D19="Miramare",$G19=""),ROW(),"") | AN19: =IF(AND($D19="Agantonio",$G19=""),ROW(),"") | AO19: =IF(AND($D19="Casa Bella Gialla",$G19=""),ROW(),"") | AP19: =IF(AND($D19="Casa Verde Oliva",$G19=""),ROW(),"") | AQ19: =IF(AND($D19="Casa Nicola",$G19=""),ROW(),"") | AR19: =IF(AND($D19="White Cottage",$G19=""),ROW(),"") | AS19: =IF(AND($D19="Villa Nella",$G19=""),ROW(),"") | AT19: =IF(AND($D19="Nel Cuore di Lanciano",$G19<>""),ROW(),"") | AU19: =IF(AND($D19="Nel Cuore di Lanciano",$G19=""),ROW(),"")
A20: 46123 | B20: 46136 | C20: =IF(A20<>"",B20-A20,"") -> 13 | D20: Via San Rocco | E20: Concetta D'Orsogna | F20: 2 ad | G20: diretta | H20: 1105 | I20: =IF(AND(H20<>"",C20<>"",C20<>0),H20/C20,"") -> 85 | J20: =IF(AND(ISNUMBER(SEARCH("booking",G20)),OR(D20="Via San Rocco",D20="Via Cavour")),H20*0.165,IF(ISNUMBER(SEARCH("airbnb",G20)),H20*0.155,IF(ISNUMBER(SEARCH("booking",G20)),H20*0.15,""))) | L20: 4 | M20: =IF(H20<>"",H20*0.1,"") -> 110.5 | S20: =IF(AND($D20="Sotto la Quercia",$G20<>""),ROW(),"") | T20: =IF($D20="Villa Elena",COUNTIF($D$3:$D20,"Villa Elena"),"") | U20: =IF(AND($D20="Casa Letizia",$G20<>""),ROW(),"") | V20: =IF(AND($D20="Casa nel Borgo",$G20<>""),ROW(),"") | W20: =IF(AND($D20="Via San Rocco",$G20<>""),ROW(),"") -> 20 | X20: =IF(AND($D20="Via Cavour",$G20<>""),ROW(),"") | Y20: =IF(AND($D20="Miramare",$G20<>""),ROW(),"") | Z20: =IF(AND($D20="Agantonio",$G20<>""),ROW(),"") | AA20: =IF(AND($D20="Casa Bella Gialla",$G20<>""),ROW(),"") | AB20: =IF(AND($D20="Casa Verde Oliva",$G20<>""),ROW(),"") | AC20: =IF(AND($D20="Casa Nicola",$G20<>""),ROW(),"") | AD20: =IF(AND($D20="White Cottage",$G20<>""),ROW(),"") | AE20: =IF(AND($D20="Villa Nella",$G20<>""),ROW(),"") | AF20: =IF(AND($D20="Villa Elena",$G20<>""),ROW(),"") | AG20: =IF(AND($D20="Sotto la Quercia",$G20=""),ROW(),"") | AH20: =IF(AND($D20="Villa Elena",$G20=""),ROW(),"") | AI20: =IF(AND($D20="Casa Letizia",$G20=""),ROW(),"") | AJ20: =IF(AND($D20="Casa nel Borgo",$G20=""),ROW(),"") | AK20: =IF(AND($D20="Via San Rocco",$G20=""),ROW(),"") | AL20: =IF(AND($D20="Via Cavour",$G20=""),ROW(),"") | AM20: =IF(AND($D20="Miramare",$G20=""),ROW(),"") | AN20: =IF(AND($D20="Agantonio",$G20=""),ROW(),"") | AO20: =IF(AND($D20="Casa Bella Gialla",$G20=""),ROW(),"") | AP20: =IF(AND($D20="Casa Verde Oliva",$G20=""),ROW(),"") | AQ20: =IF(AND($D20="Casa Nicola",$G20=""),ROW(),"") | AR20: =IF(AND($D20="White Cottage",$G20=""),ROW(),"") | AS20: =IF(AND($D20="Villa Nella",$G20=""),ROW(),"") | AT20: =IF(AND($D20="Nel Cuore di Lanciano",$G20<>""),ROW(),"") | AU20: =IF(AND($D20="Nel Cuore di Lanciano",$G20=""),ROW(),"")
A21: 46124 | B21: 46128 | C21: =IF(A21<>"",B21-A21,"") -> 4 | D21: Via Cavour | E21: Luca D'Orsogna | F21: 2 ad + 3 b | G21: diretta | H21: 420 | I21: =IF(AND(H21<>"",C21<>"",C21<>0),H21/C21,"") -> 105 | J21: =IF(AND(ISNUMBER(SEARCH("booking",G21)),OR(D21="Via San Rocco",D21="Via Cavour")),H21*0.165,IF(ISNUMBER(SEARCH("airbnb",G21)),H21*0.155,IF(ISNUMBER(SEARCH("booking",G21)),H21*0.15,""))) | L21: 4 | M21: =IF(H21<>"",H21*0.1,"") -> 42 | S21: =IF(AND($D21="Sotto la Quercia",$G21<>""),ROW(),"") | T21: =IF($D21="Villa Elena",COUNTIF($D$3:$D21,"Villa Elena"),"") | U21: =IF(AND($D21="Casa Letizia",$G21<>""),ROW(),"") | V21: =IF(AND($D21="Casa nel Borgo",$G21<>""),ROW(),"") | W21: =IF(AND($D21="Via San Rocco",$G21<>""),ROW(),"") | X21: =IF(AND($D21="Via Cavour",$G21<>""),ROW(),"") -> 21 | Y21: =IF(AND($D21="Miramare",$G21<>""),ROW(),"") | Z21: =IF(AND($D21="Agantonio",$G21<>""),ROW(),"") | AA21: =IF(AND($D21="Casa Bella Gialla",$G21<>""),ROW(),"") | AB21: =IF(AND($D21="Casa Verde Oliva",$G21<>""),ROW(),"") | AC21: =IF(AND($D21="Casa Nicola",$G21<>""),ROW(),"") | AD21: =IF(AND($D21="White Cottage",$G21<>""),ROW(),"") | AE21: =IF(AND($D21="Villa Nella",$G21<>""),ROW(),"") | AF21: =IF(AND($D21="Villa Elena",$G21<>""),ROW(),"") | AG21: =IF(AND($D21="Sotto la Quercia",$G21=""),ROW(),"") | AH21: =IF(AND($D21="Villa Elena",$G21=""),ROW(),"") | AI21: =IF(AND($D21="Casa Letizia",$G21=""),ROW(),"") | AJ21: =IF(AND($D21="Casa nel Borgo",$G21=""),ROW(),"") | AK21: =IF(AND($D21="Via San Rocco",$G21=""),ROW(),"") | AL21: =IF(AND($D21="Via Cavour",$G21=""),ROW(),"") | AM21: =IF(AND($D21="Miramare",$G21=""),ROW(),"") | AN21: =IF(AND($D21="Agantonio",$G21=""),ROW(),"") | AO21: =IF(AND($D21="Casa Bella Gialla",$G21=""),ROW(),"") | AP21: =IF(AND($D21="Casa Verde Oliva",$G21=""),ROW(),"") | AQ21: =IF(AND($D21="Casa Nicola",$G21=""),ROW(),"") | AR21: =IF(AND($D21="White Cottage",$G21=""),ROW(),"") | AS21: =IF(AND($D21="Villa Nella",$G21=""),ROW(),"") | AT21: =IF(AND($D21="Nel Cuore di Lanciano",$G21<>""),ROW(),"") | AU21: =IF(AND($D21="Nel Cuore di Lanciano",$G21=""),ROW(),"")
A22: 46129 | B22: 46131 | C22: =IF(A22<>"",B22-A22,"") -> 2 | D22: Sotto la Quercia | E22: Raffaele Guasco | F22: 4 ad | G22: booking.com | H22: 388.92 | I22: =IF(AND(H22<>"",C22<>"",C22<>0),H22/C22,"") -> 194.46 | J22: =IF(AND(ISNUMBER(SEARCH("booking",G22)),OR(D22="Via San Rocco",D22="Via Cavour")),H22*0.165,IF(ISNUMBER(SEARCH("airbnb",G22)),H22*0.155,IF(ISNUMBER(SEARCH("booking",G22)),H22*0.15,""))) -> 58.338 | K22: MASTER | L22: 0 | M22: =IF(H22<>"",H22*0.25,"") -> 97.23 | O22: NESSUNO | R22: NON RIMBORSABILE - pagamento effettuato 30-01. NO SHOW | S22: =IF(AND($D22="Sotto la Quercia",$G22<>""),ROW(),"") -> 22 | T22: =IF($D22="Villa Elena",COUNTIF($D$3:$D22,"Villa Elena"),"") | U22: =IF(AND($D22="Casa Letizia",$G22<>""),ROW(),"") | V22: =IF(AND($D22="Casa nel Borgo",$G22<>""),ROW(),"") | W22: =IF(AND($D22="Via San Rocco",$G22<>""),ROW(),"") | X22: =IF(AND($D22="Via Cavour",$G22<>""),ROW(),"") | Y22: =IF(AND($D22="Miramare",$G22<>""),ROW(),"") | Z22: =IF(AND($D22="Agantonio",$G22<>""),ROW(),"") | AA22: =IF(AND($D22="Casa Bella Gialla",$G22<>""),ROW(),"") | AB22: =IF(AND($D22="Casa Verde Oliva",$G22<>""),ROW(),"") | AC22: =IF(AND($D22="Casa Nicola",$G22<>""),ROW(),"") | AD22: =IF(AND($D22="White Cottage",$G22<>""),ROW(),"") | AE22: =IF(AND($D22="Villa Nella",$G22<>""),ROW(),"") | AF22: =IF(AND($D22="Villa Elena",$G22<>""),ROW(),"") | AG22: =IF(AND($D22="Sotto la Quercia",$G22=""),ROW(),"") | AH22: =IF(AND($D22="Villa Elena",$G22=""),ROW(),"") | AI22: =IF(AND($D22="Casa Letizia",$G22=""),ROW(),"") | AJ22: =IF(AND($D22="Casa nel Borgo",$G22=""),ROW(),"") | AK22: =IF(AND($D22="Via San Rocco",$G22=""),ROW(),"") | AL22: =IF(AND($D22="Via Cavour",$G22=""),ROW(),"") | AM22: =IF(AND($D22="Miramare",$G22=""),ROW(),"") | AN22: =IF(AND($D22="Agantonio",$G22=""),ROW(),"") | AO22: =IF(AND($D22="Casa Bella Gialla",$G22=""),ROW(),"") | AP22: =IF(AND($D22="Casa Verde Oliva",$G22=""),ROW(),"") | AQ22: =IF(AND($D22="Casa Nicola",$G22=""),ROW(),"") | AR22: =IF(AND($D22="White Cottage",$G22=""),ROW(),"") | AS22: =IF(AND($D22="Villa Nella",$G22=""),ROW(),"") | AT22: =IF(AND($D22="Nel Cuore di Lanciano",$G22<>""),ROW(),"") | AU22: =IF(AND($D22="Nel Cuore di Lanciano",$G22=""),ROW(),"")
A23: 46129 | B23: 46132 | C23: =IF(A23<>"",B23-A23,"") -> 3 | D23: Villa Elena | E23: Luca Ferrari | F23: 3 ad | G23: diretta | H23: 300 | I23: =IF(AND(H23<>"",C23<>"",C23<>0),H23/C23,"") -> 100 | J23: 0 | L23: 6 | M23: =IF(H23<>"",H23*0.25,"") -> 75 | N23: 20 | O23: JESSICA | P23: 19 | S23: =IF(AND($D23="Sotto la Quercia",$G23<>""),ROW(),"") | T23: =IF($D23="Villa Elena",COUNTIF($D$3:$D23,"Villa Elena"),"") -> 4 | U23: =IF(AND($D23="Casa Letizia",$G23<>""),ROW(),"") | V23: =IF(AND($D23="Casa nel Borgo",$G23<>""),ROW(),"") | W23: =IF(AND($D23="Via San Rocco",$G23<>""),ROW(),"") | X23: =IF(AND($D23="Via Cavour",$G23<>""),ROW(),"") | Y23: =IF(AND($D23="Miramare",$G23<>""),ROW(),"") | Z23: =IF(AND($D23="Agantonio",$G23<>""),ROW(),"") | AA23: =IF(AND($D23="Casa Bella Gialla",$G23<>""),ROW(),"") | AB23: =IF(AND($D23="Casa Verde Oliva",$G23<>""),ROW(),"") | AC23: =IF(AND($D23="Casa Nicola",$G23<>""),ROW(),"") | AD23: =IF(AND($D23="White Cottage",$G23<>""),ROW(),"") | AE23: =IF(AND($D23="Villa Nella",$G23<>""),ROW(),"") | AF23: =IF(AND($D23="Villa Elena",$G23<>""),ROW(),"") -> 23 | AG23: =IF(AND($D23="Sotto la Quercia",$G23=""),ROW(),"") | AH23: =IF(AND($D23="Villa Elena",$G23=""),ROW(),"") | AI23: =IF(AND($D23="Casa Letizia",$G23=""),ROW(),"") | AJ23: =IF(AND($D23="Casa nel Borgo",$G23=""),ROW(),"") | AK23: =IF(AND($D23="Via San Rocco",$G23=""),ROW(),"") | AL23: =IF(AND($D23="Via Cavour",$G23=""),ROW(),"") | AM23: =IF(AND($D23="Miramare",$G23=""),ROW(),"") | AN23: =IF(AND($D23="Agantonio",$G23=""),ROW(),"") | AO23: =IF(AND($D23="Casa Bella Gialla",$G23=""),ROW(),"") | AP23: =IF(AND($D23="Casa Verde Oliva",$G23=""),ROW(),"") | AQ23: =IF(AND($D23="Casa Nicola",$G23=""),ROW(),"") | AR23: =IF(AND($D23="White Cottage",$G23=""),ROW(),"") | AS23: =IF(AND($D23="Villa Nella",$G23=""),ROW(),"") | AT23: =IF(AND($D23="Nel Cuore di Lanciano",$G23<>""),ROW(),"") | AU23: =IF(AND($D23="Nel Cuore di Lanciano",$G23=""),ROW(),"")
A24: 46134 | B24: 46136 | C24: =IF(A24<>"",B24-A24,"") -> 2 | D24: Casa nel Borgo | E24: Marina Alves | F24: 1 ad | G24: Airbnb | H24: 196 | I24: =IF(AND(H24<>"",C24<>"",C24<>0),H24/C24,"") -> 98 | J24: =IF(AND(ISNUMBER(SEARCH("booking",G24)),OR(D24="Via San Rocco",D24="Via Cavour")),H24*0.165,IF(ISNUMBER(SEARCH("airbnb",G24)),H24*0.155,IF(ISNUMBER(SEARCH("booking",G24)),H24*0.15,""))) -> 30.38 | K24: Airbnb | L24: 2 | M24: =IF(H24<>"",H24*0.25,"") -> 49 | N24: 10 | O24: JESSICA | P24: 8.27 | S24: =IF(AND($D24="Sotto la Quercia",$G24<>""),ROW(),"") | T24: =IF($D24="Villa Elena",COUNTIF($D$3:$D24,"Villa Elena"),"") | U24: =IF(AND($D24="Casa Letizia",$G24<>""),ROW(),"") | V24: =IF(AND($D24="Casa nel Borgo",$G24<>""),ROW(),"") -> 24 | W24: =IF(AND($D24="Via San Rocco",$G24<>""),ROW(),"") | X24: =IF(AND($D24="Via Cavour",$G24<>""),ROW(),"") | Y24: =IF(AND($D24="Miramare",$G24<>""),ROW(),"") | Z24: =IF(AND($D24="Agantonio",$G24<>""),ROW(),"") | AA24: =IF(AND($D24="Casa Bella Gialla",$G24<>""),ROW(),"") | AB24: =IF(AND($D24="Casa Verde Oliva",$G24<>""),ROW(),"") | AC24: =IF(AND($D24="Casa Nicola",$G24<>""),ROW(),"") | AD24: =IF(AND($D24="White Cottage",$G24<>""),ROW(),"") | AE24: =IF(AND($D24="Villa Nella",$G24<>""),ROW(),"") | AF24: =IF(AND($D24="Villa Elena",$G24<>""),ROW(),"") | AG24: =IF(AND($D24="Sotto la Quercia",$G24=""),ROW(),"") | AH24: =IF(AND($D24="Villa Elena",$G24=""),ROW(),"") | AI24: =IF(AND($D24="Casa Letizia",$G24=""),ROW(),"") | AJ24: =IF(AND($D24="Casa nel Borgo",$G24=""),ROW(),"") | AK24: =IF(AND($D24="Via San Rocco",$G24=""),ROW(),"") | AL24: =IF(AND($D24="Via Cavour",$G24=""),ROW(),"") | AM24: =IF(AND($D24="Miramare",$G24=""),ROW(),"") | AN24: =IF(AND($D24="Agantonio",$G24=""),ROW(),"") | AO24: =IF(AND($D24="Casa Bella Gialla",$G24=""),ROW(),"") | AP24: =IF(AND($D24="Casa Verde Oliva",$G24=""),ROW(),"") | AQ24: =IF(AND($D24="Casa Nicola",$G24=""),ROW(),"") | AR24: =IF(AND($D24="White Cottage",$G24=""),ROW(),"") | AS24: =IF(AND($D24="Villa Nella",$G24=""),ROW(),"") | AT24: =IF(AND($D24="Nel Cuore di Lanciano",$G24<>""),ROW(),"") | AU24: =IF(AND($D24="Nel Cuore di Lanciano",$G24=""),ROW(),"")
A25: 46142 | B25: 46145 | C25: =IF(A25<>"",B25-A25,"") -> 3 | D25: Agantonio | E25: Martina Pieri | F25: 1 ad 2 b | G25: booking.com | H25: 218 | I25: =IF(AND(H25<>"",C25<>"",C25<>0),H25/C25,"") -> 72.666667 | J25: =IF(AND(ISNUMBER(SEARCH("booking",G25)),OR(D25="Via San Rocco",D25="Via Cavour")),H25*0.165,IF(ISNUMBER(SEARCH("airbnb",G25)),H25*0.155,IF(ISNUMBER(SEARCH("booking",G25)),H25*0.15,""))) -> 32.7 | K25: MASTER | L25: 3 | M25: =IF(H25<>"",H25*0.25,"") -> 54.5 | N25: 20 | O25: MARILENA | P25: 16.14 | S25: =IF(AND($D25="Sotto la Quercia",$G25<>""),ROW(),"") | T25: =IF($D25="Villa Elena",COUNTIF($D$3:$D25,"Villa Elena"),"") | U25: =IF(AND($D25="Casa Letizia",$G25<>""),ROW(),"") | V25: =IF(AND($D25="Casa nel Borgo",$G25<>""),ROW(),"") | W25: =IF(AND($D25="Via San Rocco",$G25<>""),ROW(),"") | X25: =IF(AND($D25="Via Cavour",$G25<>""),ROW(),"") | Y25: =IF(AND($D25="Miramare",$G25<>""),ROW(),"") | Z25: =IF(AND($D25="Agantonio",$G25<>""),ROW(),"") -> 25 | AA25: =IF(AND($D25="Casa Bella Gialla",$G25<>""),ROW(),"") | AB25: =IF(AND($D25="Casa Verde Oliva",$G25<>""),ROW(),"") | AC25: =IF(AND($D25="Casa Nicola",$G25<>""),ROW(),"") | AD25: =IF(AND($D25="White Cottage",$G25<>""),ROW(),"") | AE25: =IF(AND($D25="Villa Nella",$G25<>""),ROW(),"") | AF25: =IF(AND($D25="Villa Elena",$G25<>""),ROW(),"") | AG25: =IF(AND($D25="Sotto la Quercia",$G25=""),ROW(),"") | AH25: =IF(AND($D25="Villa Elena",$G25=""),ROW(),"") | AI25: =IF(AND($D25="Casa Letizia",$G25=""),ROW(),"") | AJ25: =IF(AND($D25="Casa nel Borgo",$G25=""),ROW(),"") | AK25: =IF(AND($D25="Via San Rocco",$G25=""),ROW(),"") | AL25: =IF(AND($D25="Via Cavour",$G25=""),ROW(),"") | AM25: =IF(AND($D25="Miramare",$G25=""),ROW(),"") | AN25: =IF(AND($D25="Agantonio",$G25=""),ROW(),"") | AO25: =IF(AND($D25="Casa Bella Gialla",$G25=""),ROW(),"") | AP25: =IF(AND($D25="Casa Verde Oliva",$G25=""),ROW(),"") | AQ25: =IF(AND($D25="Casa Nicola",$G25=""),ROW(),"") | AR25: =IF(AND($D25="White Cottage",$G25=""),ROW(),"") | AS25: =IF(AND($D25="Villa Nella",$G25=""),ROW(),"") | AT25: =IF(AND($D25="Nel Cuore di Lanciano",$G25<>""),ROW(),"") | AU25: =IF(AND($D25="Nel Cuore di Lanciano",$G25=""),ROW(),"")
A26: 46142 | B26: 46148 | C26: =IF(A26<>"",B26-A26,"") -> 6 | D26: Sotto la Quercia | E26: Karatina Svitekova | F26: 3 ad | G26: diretta | H26: 900 | I26: =IF(AND(H26<>"",C26<>"",C26<>0),H26/C26,"") -> 150 | J26: 0 | K26: VISA | L26: 6 | M26: =IF(H26<>"",H26*0.25,"") -> 225 | N26: 50 | O26: RITA | P26: 19.93 | R26: preparare due matrimoniali + 1 singolo | S26: =IF(AND($D26="Sotto la Quercia",$G26<>""),ROW(),"") -> 26 | T26: =IF($D26="Villa Elena",COUNTIF($D$3:$D26,"Villa Elena"),"") | U26: =IF(AND($D26="Casa Letizia",$G26<>""),ROW(),"") | V26: =IF(AND($D26="Casa nel Borgo",$G26<>""),ROW(),"") | W26: =IF(AND($D26="Via San Rocco",$G26<>""),ROW(),"") | X26: =IF(AND($D26="Via Cavour",$G26<>""),ROW(),"") | Y26: =IF(AND($D26="Miramare",$G26<>""),ROW(),"") | Z26: =IF(AND($D26="Agantonio",$G26<>""),ROW(),"") | AA26: =IF(AND($D26="Casa Bella Gialla",$G26<>""),ROW(),"") | AB26: =IF(AND($D26="Casa Verde Oliva",$G26<>""),ROW(),"") | AC26: =IF(AND($D26="Casa Nicola",$G26<>""),ROW(),"") | AD26: =IF(AND($D26="White Cottage",$G26<>""),ROW(),"") | AE26: =IF(AND($D26="Villa Nella",$G26<>""),ROW(),"") | AF26: =IF(AND($D26="Villa Elena",$G26<>""),ROW(),"") | AG26: =IF(AND($D26="Sotto la Quercia",$G26=""),ROW(),"") | AH26: =IF(AND($D26="Villa Elena",$G26=""),ROW(),"") | AI26: =IF(AND($D26="Casa Letizia",$G26=""),ROW(),"") | AJ26: =IF(AND($D26="Casa nel Borgo",$G26=""),ROW(),"") | AK26: =IF(AND($D26="Via San Rocco",$G26=""),ROW(),"") | AL26: =IF(AND($D26="Via Cavour",$G26=""),ROW(),"") | AM26: =IF(AND($D26="Miramare",$G26=""),ROW(),"") | AN26: =IF(AND($D26="Agantonio",$G26=""),ROW(),"") | AO26: =IF(AND($D26="Casa Bella Gialla",$G26=""),ROW(),"") | AP26: =IF(AND($D26="Casa Verde Oliva",$G26=""),ROW(),"") | AQ26: =IF(AND($D26="Casa Nicola",$G26=""),ROW(),"") | AR26: =IF(AND($D26="White Cottage",$G26=""),ROW(),"") | AS26: =IF(AND($D26="Villa Nella",$G26=""),ROW(),"") | AT26: =IF(AND($D26="Nel Cuore di Lanciano",$G26<>""),ROW(),"") | AU26: =IF(AND($D26="Nel Cuore di Lanciano",$G26=""),ROW(),"")
A27: 46152 | B27: 46157 | C27: =IF(A27<>"",B27-A27,"") -> 5 | D27: Via San Rocco | E27: Korkrum kerri | F27: 2 ad | G27: booking.com | H27: 433.4 | I27: =IF(AND(H27<>"",C27<>"",C27<>0),H27/C27,"") -> 86.68 | J27: =IF(AND(ISNUMBER(SEARCH("booking",G27)),OR(D27="Via San Rocco",D27="Via Cavour")),H27*0.165,IF(ISNUMBER(SEARCH("airbnb",G27)),H27*0.155,IF(ISNUMBER(SEARCH("booking",G27)),H27*0.15,""))) -> 71.511 | L27: 4 | M27: =IF(H27<>"",H27*0.1,"") -> 43.34 | S27: =IF(AND($D27="Sotto la Quercia",$G27<>""),ROW(),"") | T27: =IF($D27="Villa Elena",COUNTIF($D$3:$D27,"Villa Elena"),"") | U27: =IF(AND($D27="Casa Letizia",$G27<>""),ROW(),"") | V27: =IF(AND($D27="Casa nel Borgo",$G27<>""),ROW(),"") | W27: =IF(AND($D27="Via San Rocco",$G27<>""),ROW(),"") -> 27 | X27: =IF(AND($D27="Via Cavour",$G27<>""),ROW(),"") | Y27: =IF(AND($D27="Miramare",$G27<>""),ROW(),"") | Z27: =IF(AND($D27="Agantonio",$G27<>""),ROW(),"") | AA27: =IF(AND($D27="Casa Bella Gialla",$G27<>""),ROW(),"") | AB27: =IF(AND($D27="Casa Verde Oliva",$G27<>""),ROW(),"") | AC27: =IF(AND($D27="Casa Nicola",$G27<>""),ROW(),"") | AD27: =IF(AND($D27="White Cottage",$G27<>""),ROW(),"") | AE27: =IF(AND($D27="Villa Nella",$G27<>""),ROW(),"") | AF27: =IF(AND($D27="Villa Elena",$G27<>""),ROW(),"") | AG27: =IF(AND($D27="Sotto la Quercia",$G27=""),ROW(),"") | AH27: =IF(AND($D27="Villa Elena",$G27=""),ROW(),"") | AI27: =IF(AND($D27="Casa Letizia",$G27=""),ROW(),"") | AJ27: =IF(AND($D27="Casa nel Borgo",$G27=""),ROW(),"") | AK27: =IF(AND($D27="Via San Rocco",$G27=""),ROW(),"") | AL27: =IF(AND($D27="Via Cavour",$G27=""),ROW(),"") | AM27: =IF(AND($D27="Miramare",$G27=""),ROW(),"") | AN27: =IF(AND($D27="Agantonio",$G27=""),ROW(),"") | AO27: =IF(AND($D27="Casa Bella Gialla",$G27=""),ROW(),"") | AP27: =IF(AND($D27="Casa Verde Oliva",$G27=""),ROW(),"") | AQ27: =IF(AND($D27="Casa Nicola",$G27=""),ROW(),"") | AR27: =IF(AND($D27="White Cottage",$G27=""),ROW(),"") | AS27: =IF(AND($D27="Villa Nella",$G27=""),ROW(),"") | AT27: =IF(AND($D27="Nel Cuore di Lanciano",$G27<>""),ROW(),"") | AU27: =IF(AND($D27="Nel Cuore di Lanciano",$G27=""),ROW(),"")
A28: 46153 | B28: 46155 | C28: =IF(A28<>"",B28-A28,"") -> 2 | D28: Villa Elena | E28: Monia Cardo | F28: 1 ad | H28: 162 | I28: =IF(AND(H28<>"",C28<>"",C28<>0),H28/C28,"") -> 81 | J28: 0 | K28: contanti | M28: =IF(H28<>"",H28*0.25,"") -> 40.5 | O28: matteo | P28: 10.38 | S28: =IF(AND($D28="Sotto la Quercia",$G28<>""),ROW(),"") | T28: =IF($D28="Villa Elena",COUNTIF($D$3:$D28,"Villa Elena"),"") -> 5 | U28: =IF(AND($D28="Casa Letizia",$G28<>""),ROW(),"") | V28: =IF(AND($D28="Casa nel Borgo",$G28<>""),ROW(),"") | W28: =IF(AND($D28="Via San Rocco",$G28<>""),ROW(),"") | X28: =IF(AND($D28="Via Cavour",$G28<>""),ROW(),"") | Y28: =IF(AND($D28="Miramare",$G28<>""),ROW(),"") | Z28: =IF(AND($D28="Agantonio",$G28<>""),ROW(),"") | AA28: =IF(AND($D28="Casa Bella Gialla",$G28<>""),ROW(),"") | AB28: =IF(AND($D28="Casa Verde Oliva",$G28<>""),ROW(),"") | AC28: =IF(AND($D28="Casa Nicola",$G28<>""),ROW(),"") | AD28: =IF(AND($D28="White Cottage",$G28<>""),ROW(),"") | AE28: =IF(AND($D28="Villa Nella",$G28<>""),ROW(),"") | AF28: =IF(AND($D28="Villa Elena",$G28<>""),ROW(),"") | AG28: =IF(AND($D28="Sotto la Quercia",$G28=""),ROW(),"") | AH28: =IF(AND($D28="Villa Elena",$G28=""),ROW(),"") -> 28 | AI28: =IF(AND($D28="Casa Letizia",$G28=""),ROW(),"") | AJ28: =IF(AND($D28="Casa nel Borgo",$G28=""),ROW(),"") | AK28: =IF(AND($D28="Via San Rocco",$G28=""),ROW(),"") | AL28: =IF(AND($D28="Via Cavour",$G28=""),ROW(),"") | AM28: =IF(AND($D28="Miramare",$G28=""),ROW(),"") | AN28: =IF(AND($D28="Agantonio",$G28=""),ROW(),"") | AO28: =IF(AND($D28="Casa Bella Gialla",$G28=""),ROW(),"") | AP28: =IF(AND($D28="Casa Verde Oliva",$G28=""),ROW(),"") | AQ28: =IF(AND($D28="Casa Nicola",$G28=""),ROW(),"") | AR28: =IF(AND($D28="White Cottage",$G28=""),ROW(),"") | AS28: =IF(AND($D28="Villa Nella",$G28=""),ROW(),"") | AT28: =IF(AND($D28="Nel Cuore di Lanciano",$G28<>""),ROW(),"") | AU28: =IF(AND($D28="Nel Cuore di Lanciano",$G28=""),ROW(),"")
A29: 46162 | B29: 46165 | C29: =IF(A29<>"",B29-A29,"") -> 3 | D29: Agantonio | E29: Enrico Minante | F29: 1 ad | G29: booking.com | H29: 173.8 | I29: =IF(AND(H29<>"",C29<>"",C29<>0),H29/C29,"") -> 57.933333 | J29: 29.55 | K29: MASTER | L29: 3 | M29: =IF(H29<>"",H29*0.25,"") -> 43.45 | N29: 20 | O29: MARILENA | P29: 10.38 | S29: =IF(AND($D29="Sotto la Quercia",$G29<>""),ROW(),"") | T29: =IF($D29="Villa Elena",COUNTIF($D$3:$D29,"Villa Elena"),"") | U29: =IF(AND($D29="Casa Letizia",$G29<>""),ROW(),"") | V29: =IF(AND($D29="Casa nel Borgo",$G29<>""),ROW(),"") | W29: =IF(AND($D29="Via San Rocco",$G29<>""),ROW(),"") | X29: =IF(AND($D29="Via Cavour",$G29<>""),ROW(),"") | Y29: =IF(AND($D29="Miramare",$G29<>""),ROW(),"") | Z29: =IF(AND($D29="Agantonio",$G29<>""),ROW(),"") -> 29 | AA29: =IF(AND($D29="Casa Bella Gialla",$G29<>""),ROW(),"") | AB29: =IF(AND($D29="Casa Verde Oliva",$G29<>""),ROW(),"") | AC29: =IF(AND($D29="Casa Nicola",$G29<>""),ROW(),"") | AD29: =IF(AND($D29="White Cottage",$G29<>""),ROW(),"") | AE29: =IF(AND($D29="Villa Nella",$G29<>""),ROW(),"") | AF29: =IF(AND($D29="Villa Elena",$G29<>""),ROW(),"") | AG29: =IF(AND($D29="Sotto la Quercia",$G29=""),ROW(),"") | AH29: =IF(AND($D29="Villa Elena",$G29=""),ROW(),"") | AI29: =IF(AND($D29="Casa Letizia",$G29=""),ROW(),"") | AJ29: =IF(AND($D29="Casa nel Borgo",$G29=""),ROW(),"") | AK29: =IF(AND($D29="Via San Rocco",$G29=""),ROW(),"") | AL29: =IF(AND($D29="Via Cavour",$G29=""),ROW(),"") | AM29: =IF(AND($D29="Miramare",$G29=""),ROW(),"") | AN29: =IF(AND($D29="Agantonio",$G29=""),ROW(),"") | AO29: =IF(AND($D29="Casa Bella Gialla",$G29=""),ROW(),"") | AP29: =IF(AND($D29="Casa Verde Oliva",$G29=""),ROW(),"") | AQ29: =IF(AND($D29="Casa Nicola",$G29=""),ROW(),"") | AR29: =IF(AND($D29="White Cottage",$G29=""),ROW(),"") | AS29: =IF(AND($D29="Villa Nella",$G29=""),ROW(),"") | AT29: =IF(AND($D29="Nel Cuore di Lanciano",$G29<>""),ROW(),"") | AU29: =IF(AND($D29="Nel Cuore di Lanciano",$G29=""),ROW(),"")
A30: 46170 | B30: 46172 | C30: =IF(A30<>"",B30-A30,"") -> 2 | D30: Via San Rocco | E30: Mirella Bonomelli | F30: 2 ad | G30: booking.com | H30: 214.78 | I30: =IF(AND(H30<>"",C30<>"",C30<>0),H30/C30,"") -> 107.39 | J30: =IF(AND(ISNUMBER(SEARCH("booking",G30)),OR(D30="Via San Rocco",D30="Via Cavour")),H30*0.165,IF(ISNUMBER(SEARCH("airbnb",G30)),H30*0.155,IF(ISNUMBER(SEARCH("booking",G30)),H30*0.15,""))) -> 35.4387 | L30: 4 | M30: =IF(H30<>"",H30*0.1,"") -> 21.478 | S30: =IF(AND($D30="Sotto la Quercia",$G30<>""),ROW(),"") | T30: =IF($D30="Villa Elena",COUNTIF($D$3:$D30,"Villa Elena"),"") | U30: =IF(AND($D30="Casa Letizia",$G30<>""),ROW(),"") | V30: =IF(AND($D30="Casa nel Borgo",$G30<>""),ROW(),"") | W30: =IF(AND($D30="Via San Rocco",$G30<>""),ROW(),"") -> 30 | X30: =IF(AND($D30="Via Cavour",$G30<>""),ROW(),"") | Y30: =IF(AND($D30="Miramare",$G30<>""),ROW(),"") | Z30: =IF(AND($D30="Agantonio",$G30<>""),ROW(),"") | AA30: =IF(AND($D30="Casa Bella Gialla",$G30<>""),ROW(),"") | AB30: =IF(AND($D30="Casa Verde Oliva",$G30<>""),ROW(),"") | AC30: =IF(AND($D30="Casa Nicola",$G30<>""),ROW(),"") | AD30: =IF(AND($D30="White Cottage",$G30<>""),ROW(),"") | AE30: =IF(AND($D30="Villa Nella",$G30<>""),ROW(),"") | AF30: =IF(AND($D30="Villa Elena",$G30<>""),ROW(),"") | AG30: =IF(AND($D30="Sotto la Quercia",$G30=""),ROW(),"") | AH30: =IF(AND($D30="Villa Elena",$G30=""),ROW(),"") | AI30: =IF(AND($D30="Casa Letizia",$G30=""),ROW(),"") | AJ30: =IF(AND($D30="Casa nel Borgo",$G30=""),ROW(),"") | AK30: =IF(AND($D30="Via San Rocco",$G30=""),ROW(),"") | AL30: =IF(AND($D30="Via Cavour",$G30=""),ROW(),"") | AM30: =IF(AND($D30="Miramare",$G30=""),ROW(),"") | AN30: =IF(AND($D30="Agantonio",$G30=""),ROW(),"") | AO30: =IF(AND($D30="Casa Bella Gialla",$G30=""),ROW(),"") | AP30: =IF(AND($D30="Casa Verde Oliva",$G30=""),ROW(),"") | AQ30: =IF(AND($D30="Casa Nicola",$G30=""),ROW(),"") | AR30: =IF(AND($D30="White Cottage",$G30=""),ROW(),"") | AS30: =IF(AND($D30="Villa Nella",$G30=""),ROW(),"") | AT30: =IF(AND($D30="Nel Cuore di Lanciano",$G30<>""),ROW(),"") | AU30: =IF(AND($D30="Nel Cuore di Lanciano",$G30=""),ROW(),"")
A31: 46172 | B31: 46175 | C31: =IF(A31<>"",B31-A31,"") -> 3 | D31: Casa Letizia | E31: Elisabetta Cappuccini | F31: 2 ad + 2 b | G31: booking.com | H31: 301.31 | I31: =IF(AND(H31<>"",C31<>"",C31<>0),H31/C31,"") -> 100.43667 | J31: =IF(AND(ISNUMBER(SEARCH("booking",G31)),OR(D31="Via San Rocco",D31="Via Cavour")),H31*0.165,IF(ISNUMBER(SEARCH("airbnb",G31)),H31*0.155,IF(ISNUMBER(SEARCH("booking",G31)),H31*0.15,""))) -> 45.1965 | K31: VISA | L31: 6 | M31: =IF(H31<>"",H31*0.25,"") -> 75.3275 | N31: 20 | O31: MARILENA | P31: 20 | S31: =IF(AND($D31="Sotto la Quercia",$G31<>""),ROW(),"") | T31: =IF($D31="Villa Elena",COUNTIF($D$3:$D31,"Villa Elena"),"") | U31: =IF(AND($D31="Casa Letizia",$G31<>""),ROW(),"") -> 31 | V31: =IF(AND($D31="Casa nel Borgo",$G31<>""),ROW(),"") | W31: =IF(AND($D31="Via San Rocco",$G31<>""),ROW(),"") | X31: =IF(AND($D31="Via Cavour",$G31<>""),ROW(),"") | Y31: =IF(AND($D31="Miramare",$G31<>""),ROW(),"") | Z31: =IF(AND($D31="Agantonio",$G31<>""),ROW(),"") | AA31: =IF(AND($D31="Casa Bella Gialla",$G31<>""),ROW(),"") | AB31: =IF(AND($D31="Casa Verde Oliva",$G31<>""),ROW(),"") | AC31: =IF(AND($D31="Casa Nicola",$G31<>""),ROW(),"") | AD31: =IF(AND($D31="White Cottage",$G31<>""),ROW(),"") | AE31: =IF(AND($D31="Villa Nella",$G31<>""),ROW(),"") | AF31: =IF(AND($D31="Villa Elena",$G31<>""),ROW(),"") | AG31: =IF(AND($D31="Sotto la Quercia",$G31=""),ROW(),"") | AH31: =IF(AND($D31="Villa Elena",$G31=""),ROW(),"") | AI31: =IF(AND($D31="Casa Letizia",$G31=""),ROW(),"") | AJ31: =IF(AND($D31="Casa nel Borgo",$G31=""),ROW(),"") | AK31: =IF(AND($D31="Via San Rocco",$G31=""),ROW(),"") | AL31: =IF(AND($D31="Via Cavour",$G31=""),ROW(),"") | AM31: =IF(AND($D31="Miramare",$G31=""),ROW(),"") | AN31: =IF(AND($D31="Agantonio",$G31=""),ROW(),"") | AO31: =IF(AND($D31="Casa Bella Gialla",$G31=""),ROW(),"") | AP31: =IF(AND($D31="Casa Verde Oliva",$G31=""),ROW(),"") | AQ31: =IF(AND($D31="Casa Nicola",$G31=""),ROW(),"") | AR31: =IF(AND($D31="White Cottage",$G31=""),ROW(),"") | AS31: =IF(AND($D31="Villa Nella",$G31=""),ROW(),"") | AT31: =IF(AND($D31="Nel Cuore di Lanciano",$G31<>""),ROW(),"") | AU31: =IF(AND($D31="Nel Cuore di Lanciano",$G31=""),ROW(),"")
A32: 46172 | B32: 46175 | C32: =IF(A32<>"",B32-A32,"") -> 3 | D32: Agantonio | E32: Colombara Fabio | F32: 2 ad | G32: booking.com | H32: 300.52 | I32: =IF(AND(H32<>"",C32<>"",C32<>0),H32/C32,"") -> 100.17333 | J32: =IF(AND(ISNUMBER(SEARCH("booking",G32)),OR(D32="Via San Rocco",D32="Via Cavour")),H32*0.165,IF(ISNUMBER(SEARCH("airbnb",G32)),H32*0.155,IF(ISNUMBER(SEARCH("booking",G32)),H32*0.15,""))) -> 45.078 | K32: contanti | L32: 6 | M32: =IF(H32<>"",H32*0.25,"") -> 75.13 | N32: 40 | O32: MARILENA | P32: 10.38 | S32: =IF(AND($D32="Sotto la Quercia",$G32<>""),ROW(),"") | T32: =IF($D32="Villa Elena",COUNTIF($D$3:$D32,"Villa Elena"),"") | U32: =IF(AND($D32="Casa Letizia",$G32<>""),ROW(),"") | V32: =IF(AND($D32="Casa nel Borgo",$G32<>""),ROW(),"") | W32: =IF(AND($D32="Via San Rocco",$G32<>""),ROW(),"") | X32: =IF(AND($D32="Via Cavour",$G32<>""),ROW(),"") | Y32: =IF(AND($D32="Miramare",$G32<>""),ROW(),"") | Z32: =IF(AND($D32="Agantonio",$G32<>""),ROW(),"") -> 32 | AA32: =IF(AND($D32="Casa Bella Gialla",$G32<>""),ROW(),"") | AB32: =IF(AND($D32="Casa Verde Oliva",$G32<>""),ROW(),"") | AC32: =IF(AND($D32="Casa Nicola",$G32<>""),ROW(),"") | AD32: =IF(AND($D32="White Cottage",$G32<>""),ROW(),"") | AE32: =IF(AND($D32="Villa Nella",$G32<>""),ROW(),"") | AF32: =IF(AND($D32="Villa Elena",$G32<>""),ROW(),"") | AG32: =IF(AND($D32="Sotto la Quercia",$G32=""),ROW(),"") | AH32: =IF(AND($D32="Villa Elena",$G32=""),ROW(),"") | AI32: =IF(AND($D32="Casa Letizia",$G32=""),ROW(),"") | AJ32: =IF(AND($D32="Casa nel Borgo",$G32=""),ROW(),"") | AK32: =IF(AND($D32="Via San Rocco",$G32=""),ROW(),"") | AL32: =IF(AND($D32="Via Cavour",$G32=""),ROW(),"") | AM32: =IF(AND($D32="Miramare",$G32=""),ROW(),"") | AN32: =IF(AND($D32="Agantonio",$G32=""),ROW(),"") | AO32: =IF(AND($D32="Casa Bella Gialla",$G32=""),ROW(),"") | AP32: =IF(AND($D32="Casa Verde Oliva",$G32=""),ROW(),"") | AQ32: =IF(AND($D32="Casa Nicola",$G32=""),ROW(),"") | AR32: =IF(AND($D32="White Cottage",$G32=""),ROW(),"") | AS32: =IF(AND($D32="Villa Nella",$G32=""),ROW(),"") | AT32: =IF(AND($D32="Nel Cuore di Lanciano",$G32<>""),ROW(),"") | AU32: =IF(AND($D32="Nel Cuore di Lanciano",$G32=""),ROW(),"")
A33: 46183 | B33: 46191 | C33: =IF(A33<>"",B33-A33,"") -> 8 | D33: Miramare | E33: francesco Paradisi | F33: 2 ad | G33: booking.com | H33: 704.01 | I33: =IF(AND(H33<>"",C33<>"",C33<>0),H33/C33,"") -> 88.00125 | J33: =IF(AND(ISNUMBER(SEARCH("booking",G33)),OR(D33="Via San Rocco",D33="Via Cavour")),H33*0.165,IF(ISNUMBER(SEARCH("airbnb",G33)),H33*0.155,IF(ISNUMBER(SEARCH("booking",G33)),H33*0.15,""))) -> 105.6015 | K33: MASTER | L33: 16 | M33: =IF(H33<>"",H33*0.25,"") -> 176.0025 | N33: 40 | O33: MARILENA | P33: 10.38 | S33: =IF(AND($D33="Sotto la Quercia",$G33<>""),ROW(),"") | T33: =IF($D33="Villa Elena",COUNTIF($D$3:$D33,"Villa Elena"),"") | U33: =IF(AND($D33="Casa Letizia",$G33<>""),ROW(),"") | V33: =IF(AND($D33="Casa nel Borgo",$G33<>""),ROW(),"") | W33: =IF(AND($D33="Via San Rocco",$G33<>""),ROW(),"") | X33: =IF(AND($D33="Via Cavour",$G33<>""),ROW(),"") | Y33: =IF(AND($D33="Miramare",$G33<>""),ROW(),"") -> 33 | Z33: =IF(AND($D33="Agantonio",$G33<>""),ROW(),"") | AA33: =IF(AND($D33="Casa Bella Gialla",$G33<>""),ROW(),"") | AB33: =IF(AND($D33="Casa Verde Oliva",$G33<>""),ROW(),"") | AC33: =IF(AND($D33="Casa Nicola",$G33<>""),ROW(),"") | AD33: =IF(AND($D33="White Cottage",$G33<>""),ROW(),"") | AE33: =IF(AND($D33="Villa Nella",$G33<>""),ROW(),"") | AF33: =IF(AND($D33="Villa Elena",$G33<>""),ROW(),"") | AG33: =IF(AND($D33="Sotto la Quercia",$G33=""),ROW(),"") | AH33: =IF(AND($D33="Villa Elena",$G33=""),ROW(),"") | AI33: =IF(AND($D33="Casa Letizia",$G33=""),ROW(),"") | AJ33: =IF(AND($D33="Casa nel Borgo",$G33=""),ROW(),"") | AK33: =IF(AND($D33="Via San Rocco",$G33=""),ROW(),"") | AL33: =IF(AND($D33="Via Cavour",$G33=""),ROW(),"") | AM33: =IF(AND($D33="Miramare",$G33=""),ROW(),"") | AN33: =IF(AND($D33="Agantonio",$G33=""),ROW(),"") | AO33: =IF(AND($D33="Casa Bella Gialla",$G33=""),ROW(),"") | AP33: =IF(AND($D33="Casa Verde Oliva",$G33=""),ROW(),"") | AQ33: =IF(AND($D33="Casa Nicola",$G33=""),ROW(),"") | AR33: =IF(AND($D33="White Cottage",$G33=""),ROW(),"") | AS33: =IF(AND($D33="Villa Nella",$G33=""),ROW(),"") | AT33: =IF(AND($D33="Nel Cuore di Lanciano",$G33<>""),ROW(),"") | AU33: =IF(AND($D33="Nel Cuore di Lanciano",$G33=""),ROW(),"")
A34: 46183 | B34: 46186 | C34: =IF(A34<>"",B34-A34,"") -> 3 | D34: Via San Rocco | E34: Illia Tushin | F34: 2 ad | G34: booking.com | H34: 331.17 | I34: =IF(AND(H34<>"",C34<>"",C34<>0),H34/C34,"") -> 110.39 | J34: =IF(AND(ISNUMBER(SEARCH("booking",G34)),OR(D34="Via San Rocco",D34="Via Cavour")),H34*0.165,IF(ISNUMBER(SEARCH("airbnb",G34)),H34*0.155,IF(ISNUMBER(SEARCH("booking",G34)),H34*0.15,""))) -> 54.64305 | L34: 4 | M34: =IF(H34<>"",H34*0.1,"") -> 33.117 | S34: =IF(AND($D34="Sotto la Quercia",$G34<>""),ROW(),"") | T34: =IF($D34="Villa Elena",COUNTIF($D$3:$D34,"Villa Elena"),"") | U34: =IF(AND($D34="Casa Letizia",$G34<>""),ROW(),"") | V34: =IF(AND($D34="Casa nel Borgo",$G34<>""),ROW(),"") | W34: =IF(AND($D34="Via San Rocco",$G34<>""),ROW(),"") -> 34 | X34: =IF(AND($D34="Via Cavour",$G34<>""),ROW(),"") | Y34: =IF(AND($D34="Miramare",$G34<>""),ROW(),"") | Z34: =IF(AND($D34="Agantonio",$G34<>""),ROW(),"") | AA34: =IF(AND($D34="Casa Bella Gialla",$G34<>""),ROW(),"") | AB34: =IF(AND($D34="Casa Verde Oliva",$G34<>""),ROW(),"") | AC34: =IF(AND($D34="Casa Nicola",$G34<>""),ROW(),"") | AD34: =IF(AND($D34="White Cottage",$G34<>""),ROW(),"") | AE34: =IF(AND($D34="Villa Nella",$G34<>""),ROW(),"") | AF34: =IF(AND($D34="Villa Elena",$G34<>""),ROW(),"") | AG34: =IF(AND($D34="Sotto la Quercia",$G34=""),ROW(),"") | AH34: =IF(AND($D34="Villa Elena",$G34=""),ROW(),"") | AI34: =IF(AND($D34="Casa Letizia",$G34=""),ROW(),"") | AJ34: =IF(AND($D34="Casa nel Borgo",$G34=""),ROW(),"") | AK34: =IF(AND($D34="Via San Rocco",$G34=""),ROW(),"") | AL34: =IF(AND($D34="Via Cavour",$G34=""),ROW(),"") | AM34: =IF(AND($D34="Miramare",$G34=""),ROW(),"") | AN34: =IF(AND($D34="Agantonio",$G34=""),ROW(),"") | AO34: =IF(AND($D34="Casa Bella Gialla",$G34=""),ROW(),"") | AP34: =IF(AND($D34="Casa Verde Oliva",$G34=""),ROW(),"") | AQ34: =IF(AND($D34="Casa Nicola",$G34=""),ROW(),"") | AR34: =IF(AND($D34="White Cottage",$G34=""),ROW(),"") | AS34: =IF(AND($D34="Villa Nella",$G34=""),ROW(),"") | AT34: =IF(AND($D34="Nel Cuore di Lanciano",$G34<>""),ROW(),"") | AU34: =IF(AND($D34="Nel Cuore di Lanciano",$G34=""),ROW(),"")
A35: 46186 | B35: 46193 | C35: =IF(A35<>"",B35-A35,"") -> 7 | D35: Agantonio | E35: Orazio Di Nunzio | F35: 2 ad | G35: booking.com | H35: 709.26 | I35: =IF(AND(H35<>"",C35<>"",C35<>0),H35/C35,"") -> 101.32286 | J35: =IF(AND(ISNUMBER(SEARCH("booking",G35)),OR(D35="Via San Rocco",D35="Via Cavour")),H35*0.165,IF(ISNUMBER(SEARCH("airbnb",G35)),H35*0.155,IF(ISNUMBER(SEARCH("booking",G35)),H35*0.15,""))) -> 106.389 | K35: MASTER | L35: 14 | M35: =IF(H35<>"",H35*0.25,"") -> 177.315 | N35: 20 | O35: MARILENA | P35: 10.38 | S35: =IF(AND($D35="Sotto la Quercia",$G35<>""),ROW(),"") | T35: =IF($D35="Villa Elena",COUNTIF($D$3:$D35,"Villa Elena"),"") | U35: =IF(AND($D35="Casa Letizia",$G35<>""),ROW(),"") | V35: =IF(AND($D35="Casa nel Borgo",$G35<>""),ROW(),"") | W35: =IF(AND($D35="Via San Rocco",$G35<>""),ROW(),"") | X35: =IF(AND($D35="Via Cavour",$G35<>""),ROW(),"") | Y35: =IF(AND($D35="Miramare",$G35<>""),ROW(),"") | Z35: =IF(AND($D35="Agantonio",$G35<>""),ROW(),"") -> 35 | AA35: =IF(AND($D35="Casa Bella Gialla",$G35<>""),ROW(),"") | AB35: =IF(AND($D35="Casa Verde Oliva",$G35<>""),ROW(),"") | AC35: =IF(AND($D35="Casa Nicola",$G35<>""),ROW(),"") | AD35: =IF(AND($D35="White Cottage",$G35<>""),ROW(),"") | AE35: =IF(AND($D35="Villa Nella",$G35<>""),ROW(),"") | AF35: =IF(AND($D35="Villa Elena",$G35<>""),ROW(),"") | AG35: =IF(AND($D35="Sotto la Quercia",$G35=""),ROW(),"") | AH35: =IF(AND($D35="Villa Elena",$G35=""),ROW(),"") | AI35: =IF(AND($D35="Casa Letizia",$G35=""),ROW(),"") | AJ35: =IF(AND($D35="Casa nel Borgo",$G35=""),ROW(),"") | AK35: =IF(AND($D35="Via San Rocco",$G35=""),ROW(),"") | AL35: =IF(AND($D35="Via Cavour",$G35=""),ROW(),"") | AM35: =IF(AND($D35="Miramare",$G35=""),ROW(),"") | AN35: =IF(AND($D35="Agantonio",$G35=""),ROW(),"") | AO35: =IF(AND($D35="Casa Bella Gialla",$G35=""),ROW(),"") | AP35: =IF(AND($D35="Casa Verde Oliva",$G35=""),ROW(),"") | AQ35: =IF(AND($D35="Casa Nicola",$G35=""),ROW(),"") | AR35: =IF(AND($D35="White Cottage",$G35=""),ROW(),"") | AS35: =IF(AND($D35="Villa Nella",$G35=""),ROW(),"") | AT35: =IF(AND($D35="Nel Cuore di Lanciano",$G35<>""),ROW(),"") | AU35: =IF(AND($D35="Nel Cuore di Lanciano",$G35=""),ROW(),"")
A36: 46187 | B36: 46199 | C36: =IF(A36<>"",B36-A36,"") -> 12 | D36: Villa Nella | E36: Adrian Motylewski | F36: 4 ad | G36: booking.com | H36: 3231.36 | I36: =IF(AND(H36<>"",C36<>"",C36<>0),H36/C36,"") -> 269.28 | J36: =IF(AND(ISNUMBER(SEARCH("booking",G36)),OR(D36="Via San Rocco",D36="Via Cavour")),H36*0.165,IF(ISNUMBER(SEARCH("airbnb",G36)),H36*0.155,IF(ISNUMBER(SEARCH("booking",G36)),H36*0.15,""))) -> 484.704 | K36: VISA | L36: 0 | M36: =IF(H36<>"",H36*0.25,"") -> 807.84 | N36: 0 | O36: - | P36: 30 | R36: NON RIMBORSABILE - pagamento effettuato il 06-06 | S36: =IF(AND($D36="Sotto la Quercia",$G36<>""),ROW(),"") | T36: =IF($D36="Villa Elena",COUNTIF($D$3:$D36,"Villa Elena"),"") | U36: =IF(AND($D36="Casa Letizia",$G36<>""),ROW(),"") | V36: =IF(AND($D36="Casa nel Borgo",$G36<>""),ROW(),"") | W36: =IF(AND($D36="Via San Rocco",$G36<>""),ROW(),"") | X36: =IF(AND($D36="Via Cavour",$G36<>""),ROW(),"") | Y36: =IF(AND($D36="Miramare",$G36<>""),ROW(),"") | Z36: =IF(AND($D36="Agantonio",$G36<>""),ROW(),"") | AA36: =IF(AND($D36="Casa Bella Gialla",$G36<>""),ROW(),"") | AB36: =IF(AND($D36="Casa Verde Oliva",$G36<>""),ROW(),"") | AC36: =IF(AND($D36="Casa Nicola",$G36<>""),ROW(),"") | AD36: =IF(AND($D36="White Cottage",$G36<>""),ROW(),"") | AE36: =IF(AND($D36="Villa Nella",$G36<>""),ROW(),"") -> 36 | AF36: =IF(AND($D36="Villa Elena",$G36<>""),ROW(),"") | AG36: =IF(AND($D36="Sotto la Quercia",$G36=""),ROW(),"") | AH36: =IF(AND($D36="Villa Elena",$G36=""),ROW(),"") | AI36: =IF(AND($D36="Casa Letizia",$G36=""),ROW(),"") | AJ36: =IF(AND($D36="Casa nel Borgo",$G36=""),ROW(),"") | AK36: =IF(AND($D36="Via San Rocco",$G36=""),ROW(),"") | AL36: =IF(AND($D36="Via Cavour",$G36=""),ROW(),"") | AM36: =IF(AND($D36="Miramare",$G36=""),ROW(),"") | AN36: =IF(AND($D36="Agantonio",$G36=""),ROW(),"") | AO36: =IF(AND($D36="Casa Bella Gialla",$G36=""),ROW(),"") | AP36: =IF(AND($D36="Casa Verde Oliva",$G36=""),ROW(),"") | AQ36: =IF(AND($D36="Casa Nicola",$G36=""),ROW(),"") | AR36: =IF(AND($D36="White Cottage",$G36=""),ROW(),"") | AS36: =IF(AND($D36="Villa Nella",$G36=""),ROW(),"") | AT36: =IF(AND($D36="Nel Cuore di Lanciano",$G36<>""),ROW(),"") | AU36: =IF(AND($D36="Nel Cuore di Lanciano",$G36=""),ROW(),"")
A37: 46193 | B37: 46200 | C37: =IF(A37<>"",B37-A37,"") -> 7 | D37: Sotto la Quercia | E37: Lugi Miscia | F37: 2 ad 1 b | G37: diretta | H37: 520 | I37: =IF(AND(H37<>"",C37<>"",C37<>0),H37/C37,"") -> 74.285714 | J37: 0 | K37: contanti | L37: 4 | M37: =IF(H37<>"",H37*0.25,"") -> 130 | N37: 40 | O37: MARILENA | P37: 20.21 | R37: CANE - check in fatto con krissi 25€ | S37: =IF(AND($D37="Sotto la Quercia",$G37<>""),ROW(),"") -> 37 | T37: =IF($D37="Villa Elena",COUNTIF($D$3:$D37,"Villa Elena"),"") | U37: =IF(AND($D37="Casa Letizia",$G37<>""),ROW(),"") | V37: =IF(AND($D37="Casa nel Borgo",$G37<>""),ROW(),"") | W37: =IF(AND($D37="Via San Rocco",$G37<>""),ROW(),"") | X37: =IF(AND($D37="Via Cavour",$G37<>""),ROW(),"") | Y37: =IF(AND($D37="Miramare",$G37<>""),ROW(),"") | Z37: =IF(AND($D37="Agantonio",$G37<>""),ROW(),"") | AA37: =IF(AND($D37="Casa Bella Gialla",$G37<>""),ROW(),"") | AB37: =IF(AND($D37="Casa Verde Oliva",$G37<>""),ROW(),"") | AC37: =IF(AND($D37="Casa Nicola",$G37<>""),ROW(),"") | AD37: =IF(AND($D37="White Cottage",$G37<>""),ROW(),"") | AE37: =IF(AND($D37="Villa Nella",$G37<>""),ROW(),"") | AF37: =IF(AND($D37="Villa Elena",$G37<>""),ROW(),"") | AG37: =IF(AND($D37="Sotto la Quercia",$G37=""),ROW(),"") | AH37: =IF(AND($D37="Villa Elena",$G37=""),ROW(),"") | AI37: =IF(AND($D37="Casa Letizia",$G37=""),ROW(),"") | AJ37: =IF(AND($D37="Casa nel Borgo",$G37=""),ROW(),"") | AK37: =IF(AND($D37="Via San Rocco",$G37=""),ROW(),"") | AL37: =IF(AND($D37="Via Cavour",$G37=""),ROW(),"") | AM37: =IF(AND($D37="Miramare",$G37=""),ROW(),"") | AN37: =IF(AND($D37="Agantonio",$G37=""),ROW(),"") | AO37: =IF(AND($D37="Casa Bella Gialla",$G37=""),ROW(),"") | AP37: =IF(AND($D37="Casa Verde Oliva",$G37=""),ROW(),"") | AQ37: =IF(AND($D37="Casa Nicola",$G37=""),ROW(),"") | AR37: =IF(AND($D37="White Cottage",$G37=""),ROW(),"") | AS37: =IF(AND($D37="Villa Nella",$G37=""),ROW(),"") | AT37: =IF(AND($D37="Nel Cuore di Lanciano",$G37<>""),ROW(),"") | AU37: =IF(AND($D37="Nel Cuore di Lanciano",$G37=""),ROW(),"")
A38: 46194 | B38: 46197 | C38: =IF(A38<>"",B38-A38,"") -> 3 | D38: Villa Elena | E38: Roberto Fontana | F38: 2 ad + 2 b | G38: booking.com | H38: 369.3 | I38: =IF(AND(H38<>"",C38<>"",C38<>0),H38/C38,"") -> 123.1 | J38: =IF(AND(ISNUMBER(SEARCH("booking",G38)),OR(D38="Via San Rocco",D38="Via Cavour")),H38*0.165,IF(ISNUMBER(SEARCH("airbnb",G38)),H38*0.155,IF(ISNUMBER(SEARCH("booking",G38)),H38*0.15,""))) -> 55.395 | K38: VISA | L38: 4 | M38: =IF(H38<>"",H38*0.25,"") -> 92.325 | N38: 20 | O38: MARILENA | P38: 15 | S38: =IF(AND($D38="Sotto la Quercia",$G38<>""),ROW(),"") | T38: =IF($D38="Villa Elena",COUNTIF($D$3:$D38,"Villa Elena"),"") -> 6 | U38: =IF(AND($D38="Casa Letizia",$G38<>""),ROW(),"") | V38: =IF(AND($D38="Casa nel Borgo",$G38<>""),ROW(),"") | W38: =IF(AND($D38="Via San Rocco",$G38<>""),ROW(),"") | X38: =IF(AND($D38="Via Cavour",$G38<>""),ROW(),"") | Y38: =IF(AND($D38="Miramare",$G38<>""),ROW(),"") | Z38: =IF(AND($D38="Agantonio",$G38<>""),ROW(),"") | AA38: =IF(AND($D38="Casa Bella Gialla",$G38<>""),ROW(),"") | AB38: =IF(AND($D38="Casa Verde Oliva",$G38<>""),ROW(),"") | AC38: =IF(AND($D38="Casa Nicola",$G38<>""),ROW(),"") | AD38: =IF(AND($D38="White Cottage",$G38<>""),ROW(),"") | AE38: =IF(AND($D38="Villa Nella",$G38<>""),ROW(),"") | AF38: =IF(AND($D38="Villa Elena",$G38<>""),ROW(),"") -> 38 | AG38: =IF(AND($D38="Sotto la Quercia",$G38=""),ROW(),"") | AH38: =IF(AND($D38="Villa Elena",$G38=""),ROW(),"") | AI38: =IF(AND($D38="Casa Letizia",$G38=""),ROW(),"") | AJ38: =IF(AND($D38="Casa nel Borgo",$G38=""),ROW(),"") | AK38: =IF(AND($D38="Via San Rocco",$G38=""),ROW(),"") | AL38: =IF(AND($D38="Via Cavour",$G38=""),ROW(),"") | AM38: =IF(AND($D38="Miramare",$G38=""),ROW(),"") | AN38: =IF(AND($D38="Agantonio",$G38=""),ROW(),"") | AO38: =IF(AND($D38="Casa Bella Gialla",$G38=""),ROW(),"") | AP38: =IF(AND($D38="Casa Verde Oliva",$G38=""),ROW(),"") | AQ38: =IF(AND($D38="Casa Nicola",$G38=""),ROW(),"") | AR38: =IF(AND($D38="White Cottage",$G38=""),ROW(),"") | AS38: =IF(AND($D38="Villa Nella",$G38=""),ROW(),"") | AT38: =IF(AND($D38="Nel Cuore di Lanciano",$G38<>""),ROW(),"") | AU38: =IF(AND($D38="Nel Cuore di Lanciano",$G38=""),ROW(),"")
A39: 46197 | B39: 46203 | C39: =IF(A39<>"",B39-A39,"") -> 6 | D39: Agantonio | E39: Maurizio Mercuri | F39: 2 ad + 2 b | G39: booking.com | H39: 594.27 | I39: =IF(AND(H39<>"",C39<>"",C39<>0),H39/C39,"") -> 99.045 | J39: =IF(AND(ISNUMBER(SEARCH("booking",G39)),OR(D39="Via San Rocco",D39="Via Cavour")),H39*0.165,IF(ISNUMBER(SEARCH("airbnb",G39)),H39*0.155,IF(ISNUMBER(SEARCH("booking",G39)),H39*0.15,""))) -> 89.1405 | K39: MASTER | L39: 12 | M39: =IF(H39<>"",H39*0.25,"") -> 148.5675 | N39: 10 | O39: MARILENA | P39: 20.04 | S39: =IF(AND($D39="Sotto la Quercia",$G39<>""),ROW(),"") | T39: =IF($D39="Villa Elena",COUNTIF($D$3:$D39,"Villa Elena"),"") | U39: =IF(AND($D39="Casa Letizia",$G39<>""),ROW(),"") | V39: =IF(AND($D39="Casa nel Borgo",$G39<>""),ROW(),"") | W39: =IF(AND($D39="Via San Rocco",$G39<>""),ROW(),"") | X39: =IF(AND($D39="Via Cavour",$G39<>""),ROW(),"") | Y39: =IF(AND($D39="Miramare",$G39<>""),ROW(),"") | Z39: =IF(AND($D39="Agantonio",$G39<>""),ROW(),"") -> 39 | AA39: =IF(AND($D39="Casa Bella Gialla",$G39<>""),ROW(),"") | AB39: =IF(AND($D39="Casa Verde Oliva",$G39<>""),ROW(),"") | AC39: =IF(AND($D39="Casa Nicola",$G39<>""),ROW(),"") | AD39: =IF(AND($D39="White Cottage",$G39<>""),ROW(),"") | AE39: =IF(AND($D39="Villa Nella",$G39<>""),ROW(),"") | AF39: =IF(AND($D39="Villa Elena",$G39<>""),ROW(),"") | AG39: =IF(AND($D39="Sotto la Quercia",$G39=""),ROW(),"") | AH39: =IF(AND($D39="Villa Elena",$G39=""),ROW(),"") | AI39: =IF(AND($D39="Casa Letizia",$G39=""),ROW(),"") | AJ39: =IF(AND($D39="Casa nel Borgo",$G39=""),ROW(),"") | AK39: =IF(AND($D39="Via San Rocco",$G39=""),ROW(),"") | AL39: =IF(AND($D39="Via Cavour",$G39=""),ROW(),"") | AM39: =IF(AND($D39="Miramare",$G39=""),ROW(),"") | AN39: =IF(AND($D39="Agantonio",$G39=""),ROW(),"") | AO39: =IF(AND($D39="Casa Bella Gialla",$G39=""),ROW(),"") | AP39: =IF(AND($D39="Casa Verde Oliva",$G39=""),ROW(),"") | AQ39: =IF(AND($D39="Casa Nicola",$G39=""),ROW(),"") | AR39: =IF(AND($D39="White Cottage",$G39=""),ROW(),"") | AS39: =IF(AND($D39="Villa Nella",$G39=""),ROW(),"") | AT39: =IF(AND($D39="Nel Cuore di Lanciano",$G39<>""),ROW(),"") | AU39: =IF(AND($D39="Nel Cuore di Lanciano",$G39=""),ROW(),"")
A40: 46199 | B40: 46202 | C40: =IF(A40<>"",B40-A40,"") -> 3 | D40: Via Cavour | E40: Ernesta Gargarella | F40: 3 ad | H40: 350 | I40: =IF(AND(H40<>"",C40<>"",C40<>0),H40/C40,"") -> 116.66667 | J40: =IF(AND(ISNUMBER(SEARCH("booking",G40)),OR(D40="Via San Rocco",D40="Via Cavour")),H40*0.165,IF(ISNUMBER(SEARCH("airbnb",G40)),H40*0.155,IF(ISNUMBER(SEARCH("booking",G40)),H40*0.15,""))) | L40: 0 | M40: =IF(H40<>"",H40*0.1,"") -> 35 | R40: chiedere persone e prezzo | S40: =IF(AND($D40="Sotto la Quercia",$G40<>""),ROW(),"") | T40: =IF($D40="Villa Elena",COUNTIF($D$3:$D40,"Villa Elena"),"") | U40: =IF(AND($D40="Casa Letizia",$G40<>""),ROW(),"") | V40: =IF(AND($D40="Casa nel Borgo",$G40<>""),ROW(),"") | W40: =IF(AND($D40="Via San Rocco",$G40<>""),ROW(),"") | X40: =IF(AND($D40="Via Cavour",$G40<>""),ROW(),"") | Y40: =IF(AND($D40="Miramare",$G40<>""),ROW(),"") | Z40: =IF(AND($D40="Agantonio",$G40<>""),ROW(),"") | AA40: =IF(AND($D40="Casa Bella Gialla",$G40<>""),ROW(),"") | AB40: =IF(AND($D40="Casa Verde Oliva",$G40<>""),ROW(),"") | AC40: =IF(AND($D40="Casa Nicola",$G40<>""),ROW(),"") | AD40: =IF(AND($D40="White Cottage",$G40<>""),ROW(),"") | AE40: =IF(AND($D40="Villa Nella",$G40<>""),ROW(),"") | AF40: =IF(AND($D40="Villa Elena",$G40<>""),ROW(),"") | AG40: =IF(AND($D40="Sotto la Quercia",$G40=""),ROW(),"") | AH40: =IF(AND($D40="Villa Elena",$G40=""),ROW(),"") | AI40: =IF(AND($D40="Casa Letizia",$G40=""),ROW(),"") | AJ40: =IF(AND($D40="Casa nel Borgo",$G40=""),ROW(),"") | AK40: =IF(AND($D40="Via San Rocco",$G40=""),ROW(),"") | AL40: =IF(AND($D40="Via Cavour",$G40=""),ROW(),"") -> 40 | AM40: =IF(AND($D40="Miramare",$G40=""),ROW(),"") | AN40: =IF(AND($D40="Agantonio",$G40=""),ROW(),"") | AO40: =IF(AND($D40="Casa Bella Gialla",$G40=""),ROW(),"") | AP40: =IF(AND($D40="Casa Verde Oliva",$G40=""),ROW(),"") | AQ40: =IF(AND($D40="Casa Nicola",$G40=""),ROW(),"") | AR40: =IF(AND($D40="White Cottage",$G40=""),ROW(),"") | AS40: =IF(AND($D40="Villa Nella",$G40=""),ROW(),"") | AT40: =IF(AND($D40="Nel Cuore di Lanciano",$G40<>""),ROW(),"") | AU40: =IF(AND($D40="Nel Cuore di Lanciano",$G40=""),ROW(),"")
A41: 46201 | B41: 46211 | C41: =IF(A41<>"",B41-A41,"") -> 10 | D41: Casa Letizia | E41: Sara Gandossini | F41: 2 ad | G41: booking.com | H41: 1056.78 | I41: =IF(AND(H41<>"",C41<>"",C41<>0),H41/C41,"") -> 105.678 | J41: =IF(AND(ISNUMBER(SEARCH("booking",G41)),OR(D41="Via San Rocco",D41="Via Cavour")),H41*0.165,IF(ISNUMBER(SEARCH("airbnb",G41)),H41*0.155,IF(ISNUMBER(SEARCH("booking",G41)),H41*0.15,""))) -> 158.517 | K41: VISA | L41: 10 | M41: =IF(H41<>"",H41*0.25,"") -> 264.195 | N41: 10 | O41: MARILENA | P41: 10.38 | S41: =IF(AND($D41="Sotto la Quercia",$G41<>""),ROW(),"") | T41: =IF($D41="Villa Elena",COUNTIF($D$3:$D41,"Villa Elena"),"") | U41: =IF(AND($D41="Casa Letizia",$G41<>""),ROW(),"") -> 41 | V41: =IF(AND($D41="Casa nel Borgo",$G41<>""),ROW(),"") | W41: =IF(AND($D41="Via San Rocco",$G41<>""),ROW(),"") | X41: =IF(AND($D41="Via Cavour",$G41<>""),ROW(),"") | Y41: =IF(AND($D41="Miramare",$G41<>""),ROW(),"") | Z41: =IF(AND($D41="Agantonio",$G41<>""),ROW(),"") | AA41: =IF(AND($D41="Casa Bella Gialla",$G41<>""),ROW(),"") | AB41: =IF(AND($D41="Casa Verde Oliva",$G41<>""),ROW(),"") | AC41: =IF(AND($D41="Casa Nicola",$G41<>""),ROW(),"") | AD41: =IF(AND($D41="White Cottage",$G41<>""),ROW(),"") | AE41: =IF(AND($D41="Villa Nella",$G41<>""),ROW(),"") | AF41: =IF(AND($D41="Villa Elena",$G41<>""),ROW(),"") | AG41: =IF(AND($D41="Sotto la Quercia",$G41=""),ROW(),"") | AH41: =IF(AND($D41="Villa Elena",$G41=""),ROW(),"") | AI41: =IF(AND($D41="Casa Letizia",$G41=""),ROW(),"") | AJ41: =IF(AND($D41="Casa nel Borgo",$G41=""),ROW(),"") | AK41: =IF(AND($D41="Via San Rocco",$G41=""),ROW(),"") | AL41: =IF(AND($D41="Via Cavour",$G41=""),ROW(),"") | AM41: =IF(AND($D41="Miramare",$G41=""),ROW(),"") | AN41: =IF(AND($D41="Agantonio",$G41=""),ROW(),"") | AO41: =IF(AND($D41="Casa Bella Gialla",$G41=""),ROW(),"") | AP41: =IF(AND($D41="Casa Verde Oliva",$G41=""),ROW(),"") | AQ41: =IF(AND($D41="Casa Nicola",$G41=""),ROW(),"") | AR41: =IF(AND($D41="White Cottage",$G41=""),ROW(),"") | AS41: =IF(AND($D41="Villa Nella",$G41=""),ROW(),"") | AT41: =IF(AND($D41="Nel Cuore di Lanciano",$G41<>""),ROW(),"") | AU41: =IF(AND($D41="Nel Cuore di Lanciano",$G41=""),ROW(),"")
A42: 46206 | B42: 46213 | C42: =IF(A42<>"",B42-A42,"") -> 7 | D42: Villa Nella | E42: Maria Teresa Jaravata Gabrillo | F42: 8 ad | G42: diretta | H42: 2859.5 | I42: =IF(AND(H42<>"",C42<>"",C42<>0),H42/C42,"") -> 408.5 | J42: 0 | K42: BONIFICO | L42: 0 | M42: =IF(H42<>"",H42*0.25,"") -> 714.875 | N42: 40 | O42: MARILENA | P42: 43 | R42: NON RIMBORSABILE - pagamento effettuato con amentiz | S42: =IF(AND($D42="Sotto la Quercia",$G42<>""),ROW(),"") | T42: =IF($D42="Villa Elena",COUNTIF($D$3:$D42,"Villa Elena"),"") | U42: =IF(AND($D42="Casa Letizia",$G42<>""),ROW(),"") | V42: =IF(AND($D42="Casa nel Borgo",$G42<>""),ROW(),"") | W42: =IF(AND($D42="Via San Rocco",$G42<>""),ROW(),"") | X42: =IF(AND($D42="Via Cavour",$G42<>""),ROW(),"") | Y42: =IF(AND($D42="Miramare",$G42<>""),ROW(),"") | Z42: =IF(AND($D42="Agantonio",$G42<>""),ROW(),"") | AA42: =IF(AND($D42="Casa Bella Gialla",$G42<>""),ROW(),"") | AB42: =IF(AND($D42="Casa Verde Oliva",$G42<>""),ROW(),"") | AC42: =IF(AND($D42="Casa Nicola",$G42<>""),ROW(),"") | AD42: =IF(AND($D42="White Cottage",$G42<>""),ROW(),"") | AE42: =IF(AND($D42="Villa Nella",$G42<>""),ROW(),"") -> 42 | AF42: =IF(AND($D42="Villa Elena",$G42<>""),ROW(),"") | AG42: =IF(AND($D42="Sotto la Quercia",$G42=""),ROW(),"") | AH42: =IF(AND($D42="Villa Elena",$G42=""),ROW(),"") | AI42: =IF(AND($D42="Casa Letizia",$G42=""),ROW(),"") | AJ42: =IF(AND($D42="Casa nel Borgo",$G42=""),ROW(),"") | AK42: =IF(AND($D42="Via San Rocco",$G42=""),ROW(),"") | AL42: =IF(AND($D42="Via Cavour",$G42=""),ROW(),"") | AM42: =IF(AND($D42="Miramare",$G42=""),ROW(),"") | AN42: =IF(AND($D42="Agantonio",$G42=""),ROW(),"") | AO42: =IF(AND($D42="Casa Bella Gialla",$G42=""),ROW(),"") | AP42: =IF(AND($D42="Casa Verde Oliva",$G42=""),ROW(),"") | AQ42: =IF(AND($D42="Casa Nicola",$G42=""),ROW(),"") | AR42: =IF(AND($D42="White Cottage",$G42=""),ROW(),"") | AS42: =IF(AND($D42="Villa Nella",$G42=""),ROW(),"") | AT42: =IF(AND($D42="Nel Cuore di Lanciano",$G42<>""),ROW(),"") | AU42: =IF(AND($D42="Nel Cuore di Lanciano",$G42=""),ROW(),"")
A43: 46207 | B43: 46214 | C43: =IF(A43<>"",B43-A43,"") -> 7 | D43: Miramare | E43: Simona Chieli | F43: 2 ad | G43: booking.com | H43: 585.22 | I43: =IF(AND(H43<>"",C43<>"",C43<>0),H43/C43,"") -> 83.602857 | J43: =IF(AND(ISNUMBER(SEARCH("booking",G43)),OR(D43="Via San Rocco",D43="Via Cavour")),H43*0.165,IF(ISNUMBER(SEARCH("airbnb",G43)),H43*0.155,IF(ISNUMBER(SEARCH("booking",G43)),H43*0.15,""))) -> 87.783 | K43: MASTER E CASH | L43: 21 | M43: =IF(H43<>"",H43*0.25,"") -> 146.305 | N43: 20 | O43: MARILENA | P43: 21.69 | R43: pagato 265 con carta e resto in contanti | S43: =IF(AND($D43="Sotto la Quercia",$G43<>""),ROW(),"") | T43: =IF($D43="Villa Elena",COUNTIF($D$3:$D43,"Villa Elena"),"") | U43: =IF(AND($D43="Casa Letizia",$G43<>""),ROW(),"") | V43: =IF(AND($D43="Casa nel Borgo",$G43<>""),ROW(),"") | W43: =IF(AND($D43="Via San Rocco",$G43<>""),ROW(),"") | X43: =IF(AND($D43="Via Cavour",$G43<>""),ROW(),"") | Y43: =IF(AND($D43="Miramare",$G43<>""),ROW(),"") -> 43 | Z43: =IF(AND($D43="Agantonio",$G43<>""),ROW(),"") | AA43: =IF(AND($D43="Casa Bella Gialla",$G43<>""),ROW(),"") | AB43: =IF(AND($D43="Casa Verde Oliva",$G43<>""),ROW(),"") | AC43: =IF(AND($D43="Casa Nicola",$G43<>""),ROW(),"") | AD43: =IF(AND($D43="White Cottage",$G43<>""),ROW(),"") | AE43: =IF(AND($D43="Villa Nella",$G43<>""),ROW(),"") | AF43: =IF(AND($D43="Villa Elena",$G43<>""),ROW(),"") | AG43: =IF(AND($D43="Sotto la Quercia",$G43=""),ROW(),"") | AH43: =IF(AND($D43="Villa Elena",$G43=""),ROW(),"") | AI43: =IF(AND($D43="Casa Letizia",$G43=""),ROW(),"") | AJ43: =IF(AND($D43="Casa nel Borgo",$G43=""),ROW(),"") | AK43: =IF(AND($D43="Via San Rocco",$G43=""),ROW(),"") | AL43: =IF(AND($D43="Via Cavour",$G43=""),ROW(),"") | AM43: =IF(AND($D43="Miramare",$G43=""),ROW(),"") | AN43: =IF(AND($D43="Agantonio",$G43=""),ROW(),"") | AO43: =IF(AND($D43="Casa Bella Gialla",$G43=""),ROW(),"") | AP43: =IF(AND($D43="Casa Verde Oliva",$G43=""),ROW(),"") | AQ43: =IF(AND($D43="Casa Nicola",$G43=""),ROW(),"") | AR43: =IF(AND($D43="White Cottage",$G43=""),ROW(),"") | AS43: =IF(AND($D43="Villa Nella",$G43=""),ROW(),"") | AT43: =IF(AND($D43="Nel Cuore di Lanciano",$G43<>""),ROW(),"") | AU43: =IF(AND($D43="Nel Cuore di Lanciano",$G43=""),ROW(),"")
A44: 46207 | B44: 46222 | C44: =IF(A44<>"",B44-A44,"") -> 15 | D44: Sotto la Quercia | E44: Lubini Nicoletta | F44: 2 ad + 3 b | G44: booking.com | H44: 2793.19 | I44: =IF(AND(H44<>"",C44<>"",C44<>0),H44/C44,"") -> 186.21267 | J44: =IF(AND(ISNUMBER(SEARCH("booking",G44)),OR(D44="Via San Rocco",D44="Via Cavour")),H44*0.165,IF(ISNUMBER(SEARCH("airbnb",G44)),H44*0.155,IF(ISNUMBER(SEARCH("booking",G44)),H44*0.15,""))) -> 418.9785 | L44: 8 | M44: =IF(H44<>"",H44*0.25,"") -> 698.2975 | N44: 30 | O44: MARILENA | P44: 32.07 | R44: NON RIMBORSABILE - pagamento effettuato 11-05 | S44: =IF(AND($D44="Sotto la Quercia",$G44<>""),ROW(),"") -> 44 | T44: =IF($D44="Villa Elena",COUNTIF($D$3:$D44,"Villa Elena"),"") | U44: =IF(AND($D44="Casa Letizia",$G44<>""),ROW(),"") | V44: =IF(AND($D44="Casa nel Borgo",$G44<>""),ROW(),"") | W44: =IF(AND($D44="Via San Rocco",$G44<>""),ROW(),"") | X44: =IF(AND($D44="Via Cavour",$G44<>""),ROW(),"") | Y44: =IF(AND($D44="Miramare",$G44<>""),ROW(),"") | Z44: =IF(AND($D44="Agantonio",$G44<>""),ROW(),"") | AA44: =IF(AND($D44="Casa Bella Gialla",$G44<>""),ROW(),"") | AB44: =IF(AND($D44="Casa Verde Oliva",$G44<>""),ROW(),"") | AC44: =IF(AND($D44="Casa Nicola",$G44<>""),ROW(),"") | AD44: =IF(AND($D44="White Cottage",$G44<>""),ROW(),"") | AE44: =IF(AND($D44="Villa Nella",$G44<>""),ROW(),"") | AF44: =IF(AND($D44="Villa Elena",$G44<>""),ROW(),"") | AG44: =IF(AND($D44="Sotto la Quercia",$G44=""),ROW(),"") | AH44: =IF(AND($D44="Villa Elena",$G44=""),ROW(),"") | AI44: =IF(AND($D44="Casa Letizia",$G44=""),ROW(),"") | AJ44: =IF(AND($D44="Casa nel Borgo",$G44=""),ROW(),"") | AK44: =IF(AND($D44="Via San Rocco",$G44=""),ROW(),"") | AL44: =IF(AND($D44="Via Cavour",$G44=""),ROW(),"") | AM44: =IF(AND($D44="Miramare",$G44=""),ROW(),"") | AN44: =IF(AND($D44="Agantonio",$G44=""),ROW(),"") | AO44: =IF(AND($D44="Casa Bella Gialla",$G44=""),ROW(),"") | AP44: =IF(AND($D44="Casa Verde Oliva",$G44=""),ROW(),"") | AQ44: =IF(AND($D44="Casa Nicola",$G44=""),ROW(),"") | AR44: =IF(AND($D44="White Cottage",$G44=""),ROW(),"") | AS44: =IF(AND($D44="Villa Nella",$G44=""),ROW(),"") | AT44: =IF(AND($D44="Nel Cuore di Lanciano",$G44<>""),ROW(),"") | AU44: =IF(AND($D44="Nel Cuore di Lanciano",$G44=""),ROW(),"")
A45: 46207 | B45: 46214 | C45: =IF(A45<>"",B45-A45,"") -> 7 | D45: casa nicola | E45: Ahmad Alkhalil | F45: 5 ad | G45: booking.com | H45: 933.72 | I45: =IF(AND(H45<>"",C45<>"",C45<>0),H45/C45,"") -> 133.38857 | J45: =IF(AND(ISNUMBER(SEARCH("booking",G45)),OR(D45="Via San Rocco",D45="Via Cavour")),H45*0.165,IF(ISNUMBER(SEARCH("airbnb",G45)),H45*0.155,IF(ISNUMBER(SEARCH("booking",G45)),H45*0.15,""))) -> 140.058 | L45: 35 | M45: =IF(H45<>"",H45*0.25,"") -> 233.43 | N45: 80 | O45: MARILENA | P45: 29.38 | S45: =IF(AND($D45="Sotto la Quercia",$G45<>""),ROW(),"") | T45: =IF($D45="Villa Elena",COUNTIF($D$3:$D45,"Villa Elena"),"") | U45: =IF(AND($D45="Casa Letizia",$G45<>""),ROW(),"") | V45: =IF(AND($D45="Casa nel Borgo",$G45<>""),ROW(),"") | W45: =IF(AND($D45="Via San Rocco",$G45<>""),ROW(),"") | X45: =IF(AND($D45="Via Cavour",$G45<>""),ROW(),"") | Y45: =IF(AND($D45="Miramare",$G45<>""),ROW(),"") | Z45: =IF(AND($D45="Agantonio",$G45<>""),ROW(),"") | AA45: =IF(AND($D45="Casa Bella Gialla",$G45<>""),ROW(),"") | AB45: =IF(AND($D45="Casa Verde Oliva",$G45<>""),ROW(),"") | AC45: =IF(AND($D45="Casa Nicola",$G45<>""),ROW(),"") -> 45 | AD45: =IF(AND($D45="White Cottage",$G45<>""),ROW(),"") | AE45: =IF(AND($D45="Villa Nella",$G45<>""),ROW(),"") | AF45: =IF(AND($D45="Villa Elena",$G45<>""),ROW(),"") | AG45: =IF(AND($D45="Sotto la Quercia",$G45=""),ROW(),"") | AH45: =IF(AND($D45="Villa Elena",$G45=""),ROW(),"") | AI45: =IF(AND($D45="Casa Letizia",$G45=""),ROW(),"") | AJ45: =IF(AND($D45="Casa nel Borgo",$G45=""),ROW(),"") | AK45: =IF(AND($D45="Via San Rocco",$G45=""),ROW(),"") | AL45: =IF(AND($D45="Via Cavour",$G45=""),ROW(),"") | AM45: =IF(AND($D45="Miramare",$G45=""),ROW(),"") | AN45: =IF(AND($D45="Agantonio",$G45=""),ROW(),"") | AO45: =IF(AND($D45="Casa Bella Gialla",$G45=""),ROW(),"") | AP45: =IF(AND($D45="Casa Verde Oliva",$G45=""),ROW(),"") | AQ45: =IF(AND($D45="Casa Nicola",$G45=""),ROW(),"") | AR45: =IF(AND($D45="White Cottage",$G45=""),ROW(),"") | AS45: =IF(AND($D45="Villa Nella",$G45=""),ROW(),"") | AT45: =IF(AND($D45="Nel Cuore di Lanciano",$G45<>""),ROW(),"") | AU45: =IF(AND($D45="Nel Cuore di Lanciano",$G45=""),ROW(),"")
A46: 46207 | B46: 46214 | C46: =IF(A46<>"",B46-A46,"") -> 7 | D46: Miramare | E46: Simona Chieli | F46: 1 ad | G46: diretta | H46: 210 | I46: =IF(AND(H46<>"",C46<>"",C46<>0),H46/C46,"") -> 30 | J46: =IF(AND(ISNUMBER(SEARCH("booking",G46)),OR(D46="Via San Rocco",D46="Via Cavour")),H46*0.165,IF(ISNUMBER(SEARCH("airbnb",G46)),H46*0.155,IF(ISNUMBER(SEARCH("booking",G46)),H46*0.15,""))) | K46: MASTER E CASH | L46: 0 | M46: =IF(H46<>"",H46*0.25,"") -> 52.5 | N46: 20 | O46: MARILENA | P46: 0 | R46: aggiunta alla prenotazione di booking | S46: =IF(AND($D46="Sotto la Quercia",$G46<>""),ROW(),"") | T46: =IF($D46="Villa Elena",COUNTIF($D$3:$D46,"Villa Elena"),"") | U46: =IF(AND($D46="Casa Letizia",$G46<>""),ROW(),"") | V46: =IF(AND($D46="Casa nel Borgo",$G46<>""),ROW(),"") | W46: =IF(AND($D46="Via San Rocco",$G46<>""),ROW(),"") | X46: =IF(AND($D46="Via Cavour",$G46<>""),ROW(),"") | Y46: =IF(AND($D46="Miramare",$G46<>""),ROW(),"") -> 46 | Z46: =IF(AND($D46="Agantonio",$G46<>""),ROW(),"") | AA46: =IF(AND($D46="Casa Bella Gialla",$G46<>""),ROW(),"") | AB46: =IF(AND($D46="Casa Verde Oliva",$G46<>""),ROW(),"") | AC46: =IF(AND($D46="Casa Nicola",$G46<>""),ROW(),"") | AD46: =IF(AND($D46="White Cottage",$G46<>""),ROW(),"") | AE46: =IF(AND($D46="Villa Nella",$G46<>""),ROW(),"") | AF46: =IF(AND($D46="Villa Elena",$G46<>""),ROW(),"") | AG46: =IF(AND($D46="Sotto la Quercia",$G46=""),ROW(),"") | AH46: =IF(AND($D46="Villa Elena",$G46=""),ROW(),"") | AI46: =IF(AND($D46="Casa Letizia",$G46=""),ROW(),"") | AJ46: =IF(AND($D46="Casa nel Borgo",$G46=""),ROW(),"") | AK46: =IF(AND($D46="Via San Rocco",$G46=""),ROW(),"") | AL46: =IF(AND($D46="Via Cavour",$G46=""),ROW(),"") | AM46: =IF(AND($D46="Miramare",$G46=""),ROW(),"") | AN46: =IF(AND($D46="Agantonio",$G46=""),ROW(),"") | AO46: =IF(AND($D46="Casa Bella Gialla",$G46=""),ROW(),"") | AP46: =IF(AND($D46="Casa Verde Oliva",$G46=""),ROW(),"") | AQ46: =IF(AND($D46="Casa Nicola",$G46=""),ROW(),"") | AR46: =IF(AND($D46="White Cottage",$G46=""),ROW(),"") | AS46: =IF(AND($D46="Villa Nella",$G46=""),ROW(),"") | AT46: =IF(AND($D46="Nel Cuore di Lanciano",$G46<>""),ROW(),"") | AU46: =IF(AND($D46="Nel Cuore di Lanciano",$G46=""),ROW(),"")
A47: 46213 | B47: 46218 | C47: =IF(A47<>"",B47-A47,"") -> 5 | D47: Casa Letizia | E47: Silvia Beltramea | F47: 2 ad | G47: diretta | H47: 500 | I47: =IF(AND(H47<>"",C47<>"",C47<>0),H47/C47,"") -> 100 | J47: 0 | K47: MASTER | L47: 10 | M47: =IF(H47<>"",H47*0.25,"") -> 125 | N47: 20 | O47: MARILENA | P47: 15.76 | S47: =IF(AND($D47="Sotto la Quercia",$G47<>""),ROW(),"") | T47: =IF($D47="Villa Elena",COUNTIF($D$3:$D47,"Villa Elena"),"") | U47: =IF(AND($D47="Casa Letizia",$G47<>""),ROW(),"") -> 47 | V47: =IF(AND($D47="Casa nel Borgo",$G47<>""),ROW(),"") | W47: =IF(AND($D47="Via San Rocco",$G47<>""),ROW(),"") | X47: =IF(AND($D47="Via Cavour",$G47<>""),ROW(),"") | Y47: =IF(AND($D47="Miramare",$G47<>""),ROW(),"") | Z47: =IF(AND($D47="Agantonio",$G47<>""),ROW(),"") | AA47: =IF(AND($D47="Casa Bella Gialla",$G47<>""),ROW(),"") | AB47: =IF(AND($D47="Casa Verde Oliva",$G47<>""),ROW(),"") | AC47: =IF(AND($D47="Casa Nicola",$G47<>""),ROW(),"") | AD47: =IF(AND($D47="White Cottage",$G47<>""),ROW(),"") | AE47: =IF(AND($D47="Villa Nella",$G47<>""),ROW(),"") | AF47: =IF(AND($D47="Villa Elena",$G47<>""),ROW(),"") | AG47: =IF(AND($D47="Sotto la Quercia",$G47=""),ROW(),"") | AH47: =IF(AND($D47="Villa Elena",$G47=""),ROW(),"") | AI47: =IF(AND($D47="Casa Letizia",$G47=""),ROW(),"") | AJ47: =IF(AND($D47="Casa nel Borgo",$G47=""),ROW(),"") | AK47: =IF(AND($D47="Via San Rocco",$G47=""),ROW(),"") | AL47: =IF(AND($D47="Via Cavour",$G47=""),ROW(),"") | AM47: =IF(AND($D47="Miramare",$G47=""),ROW(),"") | AN47: =IF(AND($D47="Agantonio",$G47=""),ROW(),"") | AO47: =IF(AND($D47="Casa Bella Gialla",$G47=""),ROW(),"") | AP47: =IF(AND($D47="Casa Verde Oliva",$G47=""),ROW(),"") | AQ47: =IF(AND($D47="Casa Nicola",$G47=""),ROW(),"") | AR47: =IF(AND($D47="White Cottage",$G47=""),ROW(),"") | AS47: =IF(AND($D47="Villa Nella",$G47=""),ROW(),"") | AT47: =IF(AND($D47="Nel Cuore di Lanciano",$G47<>""),ROW(),"") | AU47: =IF(AND($D47="Nel Cuore di Lanciano",$G47=""),ROW(),"")
A48: 46213 | B48: 46216 | C48: 4 | D48: Via San Rocco | E48: Mario Ucci | F48: 2 ad | H48: 320 | I48: =IF(AND(H48<>"",C48<>"",C48<>0),H48/C48,"") -> 80 | J48: =IF(AND(ISNUMBER(SEARCH("booking",G48)),OR(D48="Via San Rocco",D48="Via Cavour")),H48*0.165,IF(ISNUMBER(SEARCH("airbnb",G48)),H48*0.155,IF(ISNUMBER(SEARCH("booking",G48)),H48*0.15,""))) | L48: 4 | M48: =IF(H48<>"",H48*0.1,"") -> 32 | S48: =IF(AND($D48="Sotto la Quercia",$G48<>""),ROW(),"") | T48: =IF($D48="Villa Elena",COUNTIF($D$3:$D48,"Villa Elena"),"") | U48: =IF(AND($D48="Casa Letizia",$G48<>""),ROW(),"") | V48: =IF(AND($D48="Casa nel Borgo",$G48<>""),ROW(),"") | W48: =IF(AND($D48="Via San Rocco",$G48<>""),ROW(),"") | X48: =IF(AND($D48="Via Cavour",$G48<>""),ROW(),"") | Y48: =IF(AND($D48="Miramare",$G48<>""),ROW(),"") | Z48: =IF(AND($D48="Agantonio",$G48<>""),ROW(),"") | AA48: =IF(AND($D48="Casa Bella Gialla",$G48<>""),ROW(),"") | AB48: =IF(AND($D48="Casa Verde Oliva",$G48<>""),ROW(),"") | AC48: =IF(AND($D48="Casa Nicola",$G48<>""),ROW(),"") | AD48: =IF(AND($D48="White Cottage",$G48<>""),ROW(),"") | AE48: =IF(AND($D48="Villa Nella",$G48<>""),ROW(),"") | AF48: =IF(AND($D48="Villa Elena",$G48<>""),ROW(),"") | AG48: =IF(AND($D48="Sotto la Quercia",$G48=""),ROW(),"") | AH48: =IF(AND($D48="Villa Elena",$G48=""),ROW(),"") | AI48: =IF(AND($D48="Casa Letizia",$G48=""),ROW(),"") | AJ48: =IF(AND($D48="Casa nel Borgo",$G48=""),ROW(),"") | AK48: =IF(AND($D48="Via San Rocco",$G48=""),ROW(),"") -> 48 | AL48: =IF(AND($D48="Via Cavour",$G48=""),ROW(),"") | AM48: =IF(AND($D48="Miramare",$G48=""),ROW(),"") | AN48: =IF(AND($D48="Agantonio",$G48=""),ROW(),"") | AO48: =IF(AND($D48="Casa Bella Gialla",$G48=""),ROW(),"") | AP48: =IF(AND($D48="Casa Verde Oliva",$G48=""),ROW(),"") | AQ48: =IF(AND($D48="Casa Nicola",$G48=""),ROW(),"") | AR48: =IF(AND($D48="White Cottage",$G48=""),ROW(),"") | AS48: =IF(AND($D48="Villa Nella",$G48=""),ROW(),"") | AT48: =IF(AND($D48="Nel Cuore di Lanciano",$G48<>""),ROW(),"") | AU48: =IF(AND($D48="Nel Cuore di Lanciano",$G48=""),ROW(),"")
A49: 46214 | B49: 46220 | C49: =IF(A49<>"",B49-A49,"") -> 6 | D49: Miramare | E49: Burko oleksi | F49: 2 ad + 3 b | G49: booking.com | H49: 702.54 | I49: =IF(AND(H49<>"",C49<>"",C49<>0),H49/C49,"") -> 117.09 | J49: =IF(AND(ISNUMBER(SEARCH("booking",G49)),OR(D49="Via San Rocco",D49="Via Cavour")),H49*0.165,IF(ISNUMBER(SEARCH("airbnb",G49)),H49*0.155,IF(ISNUMBER(SEARCH("booking",G49)),H49*0.15,""))) -> 105.381 | K49: contanti | L49: 12 | M49: =IF(H49<>"",H49*0.25,"") -> 175.635 | N49: 20 | O49: MARILENA | P49: 28.66 | S49: =IF(AND($D49="Sotto la Quercia",$G49<>""),ROW(),"") | T49: =IF($D49="Villa Elena",COUNTIF($D$3:$D49,"Villa Elena"),"") | U49: =IF(AND($D49="Casa Letizia",$G49<>""),ROW(),"") | V49: =IF(AND($D49="Casa nel Borgo",$G49<>""),ROW(),"") | W49: =IF(AND($D49="Via San Rocco",$G49<>""),ROW(),"") | X49: =IF(AND($D49="Via Cavour",$G49<>""),ROW(),"") | Y49: =IF(AND($D49="Miramare",$G49<>""),ROW(),"") -> 49 | Z49: =IF(AND($D49="Agantonio",$G49<>""),ROW(),"") | AA49: =IF(AND($D49="Casa Bella Gialla",$G49<>""),ROW(),"") | AB49: =IF(AND($D49="Casa Verde Oliva",$G49<>""),ROW(),"") | AC49: =IF(AND($D49="Casa Nicola",$G49<>""),ROW(),"") | AD49: =IF(AND($D49="White Cottage",$G49<>""),ROW(),"") | AE49: =IF(AND($D49="Villa Nella",$G49<>""),ROW(),"") | AF49: =IF(AND($D49="Villa Elena",$G49<>""),ROW(),"") | AG49: =IF(AND($D49="Sotto la Quercia",$G49=""),ROW(),"") | AH49: =IF(AND($D49="Villa Elena",$G49=""),ROW(),"") | AI49: =IF(AND($D49="Casa Letizia",$G49=""),ROW(),"") | AJ49: =IF(AND($D49="Casa nel Borgo",$G49=""),ROW(),"") | AK49: =IF(AND($D49="Via San Rocco",$G49=""),ROW(),"") | AL49: =IF(AND($D49="Via Cavour",$G49=""),ROW(),"") | AM49: =IF(AND($D49="Miramare",$G49=""),ROW(),"") | AN49: =IF(AND($D49="Agantonio",$G49=""),ROW(),"") | AO49: =IF(AND($D49="Casa Bella Gialla",$G49=""),ROW(),"") | AP49: =IF(AND($D49="Casa Verde Oliva",$G49=""),ROW(),"") | AQ49: =IF(AND($D49="Casa Nicola",$G49=""),ROW(),"") | AR49: =IF(AND($D49="White Cottage",$G49=""),ROW(),"") | AS49: =IF(AND($D49="Villa Nella",$G49=""),ROW(),"") | AT49: =IF(AND($D49="Nel Cuore di Lanciano",$G49<>""),ROW(),"") | AU49: =IF(AND($D49="Nel Cuore di Lanciano",$G49=""),ROW(),"")
A50: 46218 | B50: 46225 | C50: =IF(A50<>"",B50-A50,"") -> 7 | D50: Casa Verde Oliva | E50: Mariano Sambucari | F50: 3 ad + 1 b | G50: booking.com | H50: 1060.63 | I50: =IF(AND(H50<>"",C50<>"",C50<>0),H50/C50,"") -> 151.51857 | J50: =IF(AND(ISNUMBER(SEARCH("booking",G50)),OR(D50="Via San Rocco",D50="Via Cavour")),H50*0.165,IF(ISNUMBER(SEARCH("airbnb",G50)),H50*0.155,IF(ISNUMBER(SEARCH("booking",G50)),H50*0.15,""))) -> 159.0945 | K50: MASTER | L50: 20 | M50: =IF(H50<>"",H50*0.25,"") -> 265.1575 | N50: 40 | O50: MARILENA | P50: 20.76 | S50: =IF(AND($D50="Sotto la Quercia",$G50<>""),ROW(),"") | T50: =IF($D50="Villa Elena",COUNTIF($D$3:$D50,"Villa Elena"),"") | U50: =IF(AND($D50="Casa Letizia",$G50<>""),ROW(),"") | V50: =IF(AND($D50="Casa nel Borgo",$G50<>""),ROW(),"") | W50: =IF(AND($D50="Via San Rocco",$G50<>""),ROW(),"") | X50: =IF(AND($D50="Via Cavour",$G50<>""),ROW(),"") | Y50: =IF(AND($D50="Miramare",$G50<>""),ROW(),"") | Z50: =IF(AND($D50="Agantonio",$G50<>""),ROW(),"") | AA50: =IF(AND($D50="Casa Bella Gialla",$G50<>""),ROW(),"") | AB50: =IF(AND($D50="Casa Verde Oliva",$G50<>""),ROW(),"") -> 50 | AC50: =IF(AND($D50="Casa Nicola",$G50<>""),ROW(),"") | AD50: =IF(AND($D50="White Cottage",$G50<>""),ROW(),"") | AE50: =IF(AND($D50="Villa Nella",$G50<>""),ROW(),"") | AF50: =IF(AND($D50="Villa Elena",$G50<>""),ROW(),"") | AG50: =IF(AND($D50="Sotto la Quercia",$G50=""),ROW(),"") | AH50: =IF(AND($D50="Villa Elena",$G50=""),ROW(),"") | AI50: =IF(AND($D50="Casa Letizia",$G50=""),ROW(),"") | AJ50: =IF(AND($D50="Casa nel Borgo",$G50=""),ROW(),"") | AK50: =IF(AND($D50="Via San Rocco",$G50=""),ROW(),"") | AL50: =IF(AND($D50="Via Cavour",$G50=""),ROW(),"") | AM50: =IF(AND($D50="Miramare",$G50=""),ROW(),"") | AN50: =IF(AND($D50="Agantonio",$G50=""),ROW(),"") | AO50: =IF(AND($D50="Casa Bella Gialla",$G50=""),ROW(),"") | AP50: =IF(AND($D50="Casa Verde Oliva",$G50=""),ROW(),"") | AQ50: =IF(AND($D50="Casa Nicola",$G50=""),ROW(),"") | AR50: =IF(AND($D50="White Cottage",$G50=""),ROW(),"") | AS50: =IF(AND($D50="Villa Nella",$G50=""),ROW(),"") | AT50: =IF(AND($D50="Nel Cuore di Lanciano",$G50<>""),ROW(),"") | AU50: =IF(AND($D50="Nel Cuore di Lanciano",$G50=""),ROW(),"")
A51: 46220 | B51: 46228 | C51: =IF(A51<>"",B51-A51,"") -> 8 | D51: Casa Letizia | E51: Emidio Colabrese | F51: 3 ad | G51: diretta | H51: 1000 | I51: =IF(AND(H51<>"",C51<>"",C51<>0),H51/C51,"") -> 125 | J51: 0 | K51: contanti | L51: 15 | M51: =IF(H51<>"",H51*0.25,"") -> 250 | N51: 10 | O51: MARILENA | P51: 19 | S51: =IF(AND($D51="Sotto la Quercia",$G51<>""),ROW(),"") | T51: =IF($D51="Villa Elena",COUNTIF($D$3:$D51,"Villa Elena"),"") | U51: =IF(AND($D51="Casa Letizia",$G51<>""),ROW(),"") -> 51 | V51: =IF(AND($D51="Casa nel Borgo",$G51<>""),ROW(),"") | W51: =IF(AND($D51="Via San Rocco",$G51<>""),ROW(),"") | X51: =IF(AND($D51="Via Cavour",$G51<>""),ROW(),"") | Y51: =IF(AND($D51="Miramare",$G51<>""),ROW(),"") | Z51: =IF(AND($D51="Agantonio",$G51<>""),ROW(),"") | AA51: =IF(AND($D51="Casa Bella Gialla",$G51<>""),ROW(),"") | AB51: =IF(AND($D51="Casa Verde Oliva",$G51<>""),ROW(),"") | AC51: =IF(AND($D51="Casa Nicola",$G51<>""),ROW(),"") | AD51: =IF(AND($D51="White Cottage",$G51<>""),ROW(),"") | AE51: =IF(AND($D51="Villa Nella",$G51<>""),ROW(),"") | AF51: =IF(AND($D51="Villa Elena",$G51<>""),ROW(),"") | AG51: =IF(AND($D51="Sotto la Quercia",$G51=""),ROW(),"") | AH51: =IF(AND($D51="Villa Elena",$G51=""),ROW(),"") | AI51: =IF(AND($D51="Casa Letizia",$G51=""),ROW(),"") | AJ51: =IF(AND($D51="Casa nel Borgo",$G51=""),ROW(),"") | AK51: =IF(AND($D51="Via San Rocco",$G51=""),ROW(),"") | AL51: =IF(AND($D51="Via Cavour",$G51=""),ROW(),"") | AM51: =IF(AND($D51="Miramare",$G51=""),ROW(),"") | AN51: =IF(AND($D51="Agantonio",$G51=""),ROW(),"") | AO51: =IF(AND($D51="Casa Bella Gialla",$G51=""),ROW(),"") | AP51: =IF(AND($D51="Casa Verde Oliva",$G51=""),ROW(),"") | AQ51: =IF(AND($D51="Casa Nicola",$G51=""),ROW(),"") | AR51: =IF(AND($D51="White Cottage",$G51=""),ROW(),"") | AS51: =IF(AND($D51="Villa Nella",$G51=""),ROW(),"") | AT51: =IF(AND($D51="Nel Cuore di Lanciano",$G51<>""),ROW(),"") | AU51: =IF(AND($D51="Nel Cuore di Lanciano",$G51=""),ROW(),"")
A52: 46220 | B52: 46223 | C52: =IF(A52<>"",B52-A52,"") -> 3 | D52: Via San Rocco | E52: Mario Ucci | F52: 2 ad | H52: 240 | I52: =IF(AND(H52<>"",C52<>"",C52<>0),H52/C52,"") -> 80 | J52: =IF(AND(ISNUMBER(SEARCH("booking",G52)),OR(D52="Via San Rocco",D52="Via Cavour")),H52*0.165,IF(ISNUMBER(SEARCH("airbnb",G52)),H52*0.155,IF(ISNUMBER(SEARCH("booking",G52)),H52*0.15,""))) | M52: =IF(H52<>"",H52*0.1,"") -> 24 | S52: =IF(AND($D52="Sotto la Quercia",$G52<>""),ROW(),"") | T52: =IF($D52="Villa Elena",COUNTIF($D$3:$D52,"Villa Elena"),"") | U52: =IF(AND($D52="Casa Letizia",$G52<>""),ROW(),"") | V52: =IF(AND($D52="Casa nel Borgo",$G52<>""),ROW(),"") | W52: =IF(AND($D52="Via San Rocco",$G52<>""),ROW(),"") | X52: =IF(AND($D52="Via Cavour",$G52<>""),ROW(),"") | Y52: =IF(AND($D52="Miramare",$G52<>""),ROW(),"") | Z52: =IF(AND($D52="Agantonio",$G52<>""),ROW(),"") | AA52: =IF(AND($D52="Casa Bella Gialla",$G52<>""),ROW(),"") | AB52: =IF(AND($D52="Casa Verde Oliva",$G52<>""),ROW(),"") | AC52: =IF(AND($D52="Casa Nicola",$G52<>""),ROW(),"") | AD52: =IF(AND($D52="White Cottage",$G52<>""),ROW(),"") | AE52: =IF(AND($D52="Villa Nella",$G52<>""),ROW(),"") | AF52: =IF(AND($D52="Villa Elena",$G52<>""),ROW(),"") | AG52: =IF(AND($D52="Sotto la Quercia",$G52=""),ROW(),"") | AH52: =IF(AND($D52="Villa Elena",$G52=""),ROW(),"") | AI52: =IF(AND($D52="Casa Letizia",$G52=""),ROW(),"") | AJ52: =IF(AND($D52="Casa nel Borgo",$G52=""),ROW(),"") | AK52: =IF(AND($D52="Via San Rocco",$G52=""),ROW(),"") -> 52 | AL52: =IF(AND($D52="Via Cavour",$G52=""),ROW(),"") | AM52: =IF(AND($D52="Miramare",$G52=""),ROW(),"") | AN52: =IF(AND($D52="Agantonio",$G52=""),ROW(),"") | AO52: =IF(AND($D52="Casa Bella Gialla",$G52=""),ROW(),"") | AP52: =IF(AND($D52="Casa Verde Oliva",$G52=""),ROW(),"") | AQ52: =IF(AND($D52="Casa Nicola",$G52=""),ROW(),"") | AR52: =IF(AND($D52="White Cottage",$G52=""),ROW(),"") | AS52: =IF(AND($D52="Villa Nella",$G52=""),ROW(),"") | AT52: =IF(AND($D52="Nel Cuore di Lanciano",$G52<>""),ROW(),"") | AU52: =IF(AND($D52="Nel Cuore di Lanciano",$G52=""),ROW(),"")
A53: 46221 | B53: 46229 | C53: =IF(A53<>"",B53-A53,"") -> 8 | D53: Casa nel Borgo | E53: Giorgio Gangiulio | F53: 1 ad | H53: 520 | I53: =IF(AND(H53<>"",C53<>"",C53<>0),H53/C53,"") -> 65 | J53: =IF(AND(ISNUMBER(SEARCH("booking",G53)),OR(D53="Via San Rocco",D53="Via Cavour")),H53*0.165,IF(ISNUMBER(SEARCH("airbnb",G53)),H53*0.155,IF(ISNUMBER(SEARCH("booking",G53)),H53*0.15,""))) | K53: contanti | M53: =IF(H53<>"",H53*0.25,"") -> 130 | N53: 40 | O53: MARILENA | P53: 10.38 | S53: =IF(AND($D53="Sotto la Quercia",$G53<>""),ROW(),"") | T53: =IF($D53="Villa Elena",COUNTIF($D$3:$D53,"Villa Elena"),"") | U53: =IF(AND($D53="Casa Letizia",$G53<>""),ROW(),"") | V53: =IF(AND($D53="Casa nel Borgo",$G53<>""),ROW(),"") | W53: =IF(AND($D53="Via San Rocco",$G53<>""),ROW(),"") | X53: =IF(AND($D53="Via Cavour",$G53<>""),ROW(),"") | Y53: =IF(AND($D53="Miramare",$G53<>""),ROW(),"") | Z53: =IF(AND($D53="Agantonio",$G53<>""),ROW(),"") | AA53: =IF(AND($D53="Casa Bella Gialla",$G53<>""),ROW(),"") | AB53: =IF(AND($D53="Casa Verde Oliva",$G53<>""),ROW(),"") | AC53: =IF(AND($D53="Casa Nicola",$G53<>""),ROW(),"") | AD53: =IF(AND($D53="White Cottage",$G53<>""),ROW(),"") | AE53: =IF(AND($D53="Villa Nella",$G53<>""),ROW(),"") | AF53: =IF(AND($D53="Villa Elena",$G53<>""),ROW(),"") | AG53: =IF(AND($D53="Sotto la Quercia",$G53=""),ROW(),"") | AH53: =IF(AND($D53="Villa Elena",$G53=""),ROW(),"") | AI53: =IF(AND($D53="Casa Letizia",$G53=""),ROW(),"") | AJ53: =IF(AND($D53="Casa nel Borgo",$G53=""),ROW(),"") -> 53 | AK53: =IF(AND($D53="Via San Rocco",$G53=""),ROW(),"") | AL53: =IF(AND($D53="Via Cavour",$G53=""),ROW(),"") | AM53: =IF(AND($D53="Miramare",$G53=""),ROW(),"") | AN53: =IF(AND($D53="Agantonio",$G53=""),ROW(),"") | AO53: =IF(AND($D53="Casa Bella Gialla",$G53=""),ROW(),"") | AP53: =IF(AND($D53="Casa Verde Oliva",$G53=""),ROW(),"") | AQ53: =IF(AND($D53="Casa Nicola",$G53=""),ROW(),"") | AR53: =IF(AND($D53="White Cottage",$G53=""),ROW(),"") | AS53: =IF(AND($D53="Villa Nella",$G53=""),ROW(),"") | AT53: =IF(AND($D53="Nel Cuore di Lanciano",$G53<>""),ROW(),"") | AU53: =IF(AND($D53="Nel Cuore di Lanciano",$G53=""),ROW(),"")
A54: 46222 | B54: 46229 | C54: =IF(A54<>"",B54-A54,"") -> 7 | D54: Via Cavour | E54: Sara di Benedetto | F54: 2 ad | G54: booking.com | H54: 935.41 | I54: =IF(AND(H54<>"",C54<>"",C54<>0),H54/C54,"") -> 133.63 | J54: =IF(AND(ISNUMBER(SEARCH("booking",G54)),OR(D54="Via San Rocco",D54="Via Cavour")),H54*0.165,IF(ISNUMBER(SEARCH("airbnb",G54)),H54*0.155,IF(ISNUMBER(SEARCH("booking",G54)),H54*0.15,""))) -> 154.34265 | L54: 4 | M54: =IF(H54<>"",H54*0.1,"") -> 93.541 | S54: =IF(AND($D54="Sotto la Quercia",$G54<>""),ROW(),"") | T54: =IF($D54="Villa Elena",COUNTIF($D$3:$D54,"Villa Elena"),"") | U54: =IF(AND($D54="Casa Letizia",$G54<>""),ROW(),"") | V54: =IF(AND($D54="Casa nel Borgo",$G54<>""),ROW(),"") | W54: =IF(AND($D54="Via San Rocco",$G54<>""),ROW(),"") | X54: =IF(AND($D54="Via Cavour",$G54<>""),ROW(),"") -> 54 | Y54: =IF(AND($D54="Miramare",$G54<>""),ROW(),"") | Z54: =IF(AND($D54="Agantonio",$G54<>""),ROW(),"") | AA54: =IF(AND($D54="Casa Bella Gialla",$G54<>""),ROW(),"") | AB54: =IF(AND($D54="Casa Verde Oliva",$G54<>""),ROW(),"") | AC54: =IF(AND($D54="Casa Nicola",$G54<>""),ROW(),"") | AD54: =IF(AND($D54="White Cottage",$G54<>""),ROW(),"") | AE54: =IF(AND($D54="Villa Nella",$G54<>""),ROW(),"") | AF54: =IF(AND($D54="Villa Elena",$G54<>""),ROW(),"") | AG54: =IF(AND($D54="Sotto la Quercia",$G54=""),ROW(),"") | AH54: =IF(AND($D54="Villa Elena",$G54=""),ROW(),"") | AI54: =IF(AND($D54="Casa Letizia",$G54=""),ROW(),"") | AJ54: =IF(AND($D54="Casa nel Borgo",$G54=""),ROW(),"") | AK54: =IF(AND($D54="Via San Rocco",$G54=""),ROW(),"") | AL54: =IF(AND($D54="Via Cavour",$G54=""),ROW(),"") | AM54: =IF(AND($D54="Miramare",$G54=""),ROW(),"") | AN54: =IF(AND($D54="Agantonio",$G54=""),ROW(),"") | AO54: =IF(AND($D54="Casa Bella Gialla",$G54=""),ROW(),"") | AP54: =IF(AND($D54="Casa Verde Oliva",$G54=""),ROW(),"") | AQ54: =IF(AND($D54="Casa Nicola",$G54=""),ROW(),"") | AR54: =IF(AND($D54="White Cottage",$G54=""),ROW(),"") | AS54: =IF(AND($D54="Villa Nella",$G54=""),ROW(),"") | AT54: =IF(AND($D54="Nel Cuore di Lanciano",$G54<>""),ROW(),"") | AU54: =IF(AND($D54="Nel Cuore di Lanciano",$G54=""),ROW(),"")
A55: 46223 | B55: 46231 | C55: =IF(A55<>"",B55-A55,"") -> 8 | D55: Miramare | E55: Baracca Pasquale | F55: 4 ad | G55: diretta | H55: 1552 | I55: =IF(AND(H55<>"",C55<>"",C55<>0),H55/C55,"") -> 194 | J55: =IF(AND(ISNUMBER(SEARCH("booking",G55)),OR(D55="Via San Rocco",D55="Via Cavour")),H55*0.165,IF(ISNUMBER(SEARCH("airbnb",G55)),H55*0.155,IF(ISNUMBER(SEARCH("booking",G55)),H55*0.15,""))) | K55: BONIFICO | L55: 32 | M55: =IF(H55<>"",H55*0.25,"") -> 388 | N55: 40 | O55: MARILENA | P55: 28.17 | S55: =IF(AND($D55="Sotto la Quercia",$G55<>""),ROW(),"") | T55: =IF($D55="Villa Elena",COUNTIF($D$3:$D55,"Villa Elena"),"") | U55: =IF(AND($D55="Casa Letizia",$G55<>""),ROW(),"") | V55: =IF(AND($D55="Casa nel Borgo",$G55<>""),ROW(),"") | W55: =IF(AND($D55="Via San Rocco",$G55<>""),ROW(),"") | X55: =IF(AND($D55="Via Cavour",$G55<>""),ROW(),"") | Y55: =IF(AND($D55="Miramare",$G55<>""),ROW(),"") -> 55 | Z55: =IF(AND($D55="Agantonio",$G55<>""),ROW(),"") | AA55: =IF(AND($D55="Casa Bella Gialla",$G55<>""),ROW(),"") | AB55: =IF(AND($D55="Casa Verde Oliva",$G55<>""),ROW(),"") | AC55: =IF(AND($D55="Casa Nicola",$G55<>""),ROW(),"") | AD55: =IF(AND($D55="White Cottage",$G55<>""),ROW(),"") | AE55: =IF(AND($D55="Villa Nella",$G55<>""),ROW(),"") | AF55: =IF(AND($D55="Villa Elena",$G55<>""),ROW(),"") | AG55: =IF(AND($D55="Sotto la Quercia",$G55=""),ROW(),"") | AH55: =IF(AND($D55="Villa Elena",$G55=""),ROW(),"") | AI55: =IF(AND($D55="Casa Letizia",$G55=""),ROW(),"") | AJ55: =IF(AND($D55="Casa nel Borgo",$G55=""),ROW(),"") | AK55: =IF(AND($D55="Via San Rocco",$G55=""),ROW(),"") | AL55: =IF(AND($D55="Via Cavour",$G55=""),ROW(),"") | AM55: =IF(AND($D55="Miramare",$G55=""),ROW(),"") | AN55: =IF(AND($D55="Agantonio",$G55=""),ROW(),"") | AO55: =IF(AND($D55="Casa Bella Gialla",$G55=""),ROW(),"") | AP55: =IF(AND($D55="Casa Verde Oliva",$G55=""),ROW(),"") | AQ55: =IF(AND($D55="Casa Nicola",$G55=""),ROW(),"") | AR55: =IF(AND($D55="White Cottage",$G55=""),ROW(),"") | AS55: =IF(AND($D55="Villa Nella",$G55=""),ROW(),"") | AT55: =IF(AND($D55="Nel Cuore di Lanciano",$G55<>""),ROW(),"") | AU55: =IF(AND($D55="Nel Cuore di Lanciano",$G55=""),ROW(),"")
A56: 46224 | B56: 46237 | C56: =IF(A56<>"",B56-A56,"") -> 13 | D56: Sotto la Quercia | E56: Sindey Outtara | F56: 2 ad | G56: Airbnb | H56: 2172.64 | I56: =IF(AND(H56<>"",C56<>"",C56<>0),H56/C56,"") -> 167.12615 | J56: =IF(AND(ISNUMBER(SEARCH("booking",G56)),OR(D56="Via San Rocco",D56="Via Cavour")),H56*0.165,IF(ISNUMBER(SEARCH("airbnb",G56)),H56*0.155,IF(ISNUMBER(SEARCH("booking",G56)),H56*0.15,""))) -> 336.7592 | L56: 4 | M56: =IF(H56<>"",H56*0.25,"") -> 543.16 | N56: 30 | O56: MARILENA | P56: 14.28 | R56: Cane | S56: =IF(AND($D56="Sotto la Quercia",$G56<>""),ROW(),"") -> 56 | T56: =IF($D56="Villa Elena",COUNTIF($D$3:$D56,"Villa Elena"),"") | U56: =IF(AND($D56="Casa Letizia",$G56<>""),ROW(),"") | V56: =IF(AND($D56="Casa nel Borgo",$G56<>""),ROW(),"") | W56: =IF(AND($D56="Via San Rocco",$G56<>""),ROW(),"") | X56: =IF(AND($D56="Via Cavour",$G56<>""),ROW(),"") | Y56: =IF(AND($D56="Miramare",$G56<>""),ROW(),"") | Z56: =IF(AND($D56="Agantonio",$G56<>""),ROW(),"") | AA56: =IF(AND($D56="Casa Bella Gialla",$G56<>""),ROW(),"") | AB56: =IF(AND($D56="Casa Verde Oliva",$G56<>""),ROW(),"") | AC56: =IF(AND($D56="Casa Nicola",$G56<>""),ROW(),"") | AD56: =IF(AND($D56="White Cottage",$G56<>""),ROW(),"") | AE56: =IF(AND($D56="Villa Nella",$G56<>""),ROW(),"") | AF56: =IF(AND($D56="Villa Elena",$G56<>""),ROW(),"") | AG56: =IF(AND($D56="Sotto la Quercia",$G56=""),ROW(),"") | AH56: =IF(AND($D56="Villa Elena",$G56=""),ROW(),"") | AI56: =IF(AND($D56="Casa Letizia",$G56=""),ROW(),"") | AJ56: =IF(AND($D56="Casa nel Borgo",$G56=""),ROW(),"") | AK56: =IF(AND($D56="Via San Rocco",$G56=""),ROW(),"") | AL56: =IF(AND($D56="Via Cavour",$G56=""),ROW(),"") | AM56: =IF(AND($D56="Miramare",$G56=""),ROW(),"") | AN56: =IF(AND($D56="Agantonio",$G56=""),ROW(),"") | AO56: =IF(AND($D56="Casa Bella Gialla",$G56=""),ROW(),"") | AP56: =IF(AND($D56="Casa Verde Oliva",$G56=""),ROW(),"") | AQ56: =IF(AND($D56="Casa Nicola",$G56=""),ROW(),"") | AR56: =IF(AND($D56="White Cottage",$G56=""),ROW(),"") | AS56: =IF(AND($D56="Villa Nella",$G56=""),ROW(),"") | AT56: =IF(AND($D56="Nel Cuore di Lanciano",$G56<>""),ROW(),"") | AU56: =IF(AND($D56="Nel Cuore di Lanciano",$G56=""),ROW(),"")
A57: 46224 | B57: 46229 | C57: =IF(A57<>"",B57-A57,"") -> 5 | D57: Via San Rocco | E57: Luigi Vinci | F57: 2 ad 1 b | G57: booking.com | H57: 538.12 | I57: =IF(AND(H57<>"",C57<>"",C57<>0),H57/C57,"") -> 107.624 | J57: =IF(AND(ISNUMBER(SEARCH("booking",G57)),OR(D57="Via San Rocco",D57="Via Cavour")),H57*0.165,IF(ISNUMBER(SEARCH("airbnb",G57)),H57*0.155,IF(ISNUMBER(SEARCH("booking",G57)),H57*0.15,""))) -> 88.7898 | L57: 4 | M57: =IF(H57<>"",H57*0.1,"") -> 53.812 | S57: =IF(AND($D57="Sotto la Quercia",$G57<>""),ROW(),"") | T57: =IF($D57="Villa Elena",COUNTIF($D$3:$D57,"Villa Elena"),"") | U57: =IF(AND($D57="Casa Letizia",$G57<>""),ROW(),"") | V57: =IF(AND($D57="Casa nel Borgo",$G57<>""),ROW(),"") | W57: =IF(AND($D57="Via San Rocco",$G57<>""),ROW(),"") -> 57 | X57: =IF(AND($D57="Via Cavour",$G57<>""),ROW(),"") | Y57: =IF(AND($D57="Miramare",$G57<>""),ROW(),"") | Z57: =IF(AND($D57="Agantonio",$G57<>""),ROW(),"") | AA57: =IF(AND($D57="Casa Bella Gialla",$G57<>""),ROW(),"") | AB57: =IF(AND($D57="Casa Verde Oliva",$G57<>""),ROW(),"") | AC57: =IF(AND($D57="Casa Nicola",$G57<>""),ROW(),"") | AD57: =IF(AND($D57="White Cottage",$G57<>""),ROW(),"") | AE57: =IF(AND($D57="Villa Nella",$G57<>""),ROW(),"") | AF57: =IF(AND($D57="Villa Elena",$G57<>""),ROW(),"") | AG57: =IF(AND($D57="Sotto la Quercia",$G57=""),ROW(),"") | AH57: =IF(AND($D57="Villa Elena",$G57=""),ROW(),"") | AI57: =IF(AND($D57="Casa Letizia",$G57=""),ROW(),"") | AJ57: =IF(AND($D57="Casa nel Borgo",$G57=""),ROW(),"") | AK57: =IF(AND($D57="Via San Rocco",$G57=""),ROW(),"") | AL57: =IF(AND($D57="Via Cavour",$G57=""),ROW(),"") | AM57: =IF(AND($D57="Miramare",$G57=""),ROW(),"") | AN57: =IF(AND($D57="Agantonio",$G57=""),ROW(),"") | AO57: =IF(AND($D57="Casa Bella Gialla",$G57=""),ROW(),"") | AP57: =IF(AND($D57="Casa Verde Oliva",$G57=""),ROW(),"") | AQ57: =IF(AND($D57="Casa Nicola",$G57=""),ROW(),"") | AR57: =IF(AND($D57="White Cottage",$G57=""),ROW(),"") | AS57: =IF(AND($D57="Villa Nella",$G57=""),ROW(),"") | AT57: =IF(AND($D57="Nel Cuore di Lanciano",$G57<>""),ROW(),"") | AU57: =IF(AND($D57="Nel Cuore di Lanciano",$G57=""),ROW(),"")
A58: 46225 | B58: 46236 | C58: =IF(A58<>"",B58-A58,"") -> 11 | D58: Villa Nella | E58: Nicolle Bongers | F58: 5 ad | G58: booking.com | H58: 5189.41 | I58: =IF(AND(H58<>"",C58<>"",C58<>0),H58/C58,"") -> 471.76455 | J58: =IF(AND(ISNUMBER(SEARCH("booking",G58)),OR(D58="Via San Rocco",D58="Via Cavour")),H58*0.165,IF(ISNUMBER(SEARCH("airbnb",G58)),H58*0.155,IF(ISNUMBER(SEARCH("booking",G58)),H58*0.15,""))) -> 778.4115 | K58: MASTER | L58: 0 | M58: =IF(H58<>"",H58*0.25,"") -> 1297.3525 | N58: 50 | O58: MARILENA | P58: 33.28 | R58: NON RIMBORSABILE | S58: =IF(AND($D58="Sotto la Quercia",$G58<>""),ROW(),"") | T58: =IF($D58="Villa Elena",COUNTIF($D$3:$D58,"Villa Elena"),"") | U58: =IF(AND($D58="Casa Letizia",$G58<>""),ROW(),"") | V58: =IF(AND($D58="Casa nel Borgo",$G58<>""),ROW(),"") | W58: =IF(AND($D58="Via San Rocco",$G58<>""),ROW(),"") | X58: =IF(AND($D58="Via Cavour",$G58<>""),ROW(),"") | Y58: =IF(AND($D58="Miramare",$G58<>""),ROW(),"") | Z58: =IF(AND($D58="Agantonio",$G58<>""),ROW(),"") | AA58: =IF(AND($D58="Casa Bella Gialla",$G58<>""),ROW(),"") | AB58: =IF(AND($D58="Casa Verde Oliva",$G58<>""),ROW(),"") | AC58: =IF(AND($D58="Casa Nicola",$G58<>""),ROW(),"") | AD58: =IF(AND($D58="White Cottage",$G58<>""),ROW(),"") | AE58: =IF(AND($D58="Villa Nella",$G58<>""),ROW(),"") -> 58 | AF58: =IF(AND($D58="Villa Elena",$G58<>""),ROW(),"") | AG58: =IF(AND($D58="Sotto la Quercia",$G58=""),ROW(),"") | AH58: =IF(AND($D58="Villa Elena",$G58=""),ROW(),"") | AI58: =IF(AND($D58="Casa Letizia",$G58=""),ROW(),"") | AJ58: =IF(AND($D58="Casa nel Borgo",$G58=""),ROW(),"") | AK58: =IF(AND($D58="Via San Rocco",$G58=""),ROW(),"") | AL58: =IF(AND($D58="Via Cavour",$G58=""),ROW(),"") | AM58: =IF(AND($D58="Miramare",$G58=""),ROW(),"") | AN58: =IF(AND($D58="Agantonio",$G58=""),ROW(),"") | AO58: =IF(AND($D58="Casa Bella Gialla",$G58=""),ROW(),"") | AP58: =IF(AND($D58="Casa Verde Oliva",$G58=""),ROW(),"") | AQ58: =IF(AND($D58="Casa Nicola",$G58=""),ROW(),"") | AR58: =IF(AND($D58="White Cottage",$G58=""),ROW(),"") | AS58: =IF(AND($D58="Villa Nella",$G58=""),ROW(),"") | AT58: =IF(AND($D58="Nel Cuore di Lanciano",$G58<>""),ROW(),"") | AU58: =IF(AND($D58="Nel Cuore di Lanciano",$G58=""),ROW(),"")
A59: 46227 | B59: 46233 | C59: =IF(A59<>"",B59-A59,"") -> 6 | D59: Agantonio | E59: Daniele Charreron | F59: 2 ad | G59: booking.com | H59: 530.68 | I59: =IF(AND(H59<>"",C59<>"",C59<>0),H59/C59,"") -> 88.446667 | J59: =IF(AND(ISNUMBER(SEARCH("booking",G59)),OR(D59="Via San Rocco",D59="Via Cavour")),H59*0.165,IF(ISNUMBER(SEARCH("airbnb",G59)),H59*0.155,IF(ISNUMBER(SEARCH("booking",G59)),H59*0.15,""))) -> 79.602 | K59: VISA | L59: 12 | M59: =IF(H59<>"",H59*0.25,"") -> 132.67 | N59: 20 | O59: MARILENA | P59: 10.38 | S59: =IF(AND($D59="Sotto la Quercia",$G59<>""),ROW(),"") | T59: =IF($D59="Villa Elena",COUNTIF($D$3:$D59,"Villa Elena"),"") | U59: =IF(AND($D59="Casa Letizia",$G59<>""),ROW(),"") | V59: =IF(AND($D59="Casa nel Borgo",$G59<>""),ROW(),"") | W59: =IF(AND($D59="Via San Rocco",$G59<>""),ROW(),"") | X59: =IF(AND($D59="Via Cavour",$G59<>""),ROW(),"") | Y59: =IF(AND($D59="Miramare",$G59<>""),ROW(),"") | Z59: =IF(AND($D59="Agantonio",$G59<>""),ROW(),"") -> 59 | AA59: =IF(AND($D59="Casa Bella Gialla",$G59<>""),ROW(),"") | AB59: =IF(AND($D59="Casa Verde Oliva",$G59<>""),ROW(),"") | AC59: =IF(AND($D59="Casa Nicola",$G59<>""),ROW(),"") | AD59: =IF(AND($D59="White Cottage",$G59<>""),ROW(),"") | AE59: =IF(AND($D59="Villa Nella",$G59<>""),ROW(),"") | AF59: =IF(AND($D59="Villa Elena",$G59<>""),ROW(),"") | AG59: =IF(AND($D59="Sotto la Quercia",$G59=""),ROW(),"") | AH59: =IF(AND($D59="Villa Elena",$G59=""),ROW(),"") | AI59: =IF(AND($D59="Casa Letizia",$G59=""),ROW(),"") | AJ59: =IF(AND($D59="Casa nel Borgo",$G59=""),ROW(),"") | AK59: =IF(AND($D59="Via San Rocco",$G59=""),ROW(),"") | AL59: =IF(AND($D59="Via Cavour",$G59=""),ROW(),"") | AM59: =IF(AND($D59="Miramare",$G59=""),ROW(),"") | AN59: =IF(AND($D59="Agantonio",$G59=""),ROW(),"") | AO59: =IF(AND($D59="Casa Bella Gialla",$G59=""),ROW(),"") | AP59: =IF(AND($D59="Casa Verde Oliva",$G59=""),ROW(),"") | AQ59: =IF(AND($D59="Casa Nicola",$G59=""),ROW(),"") | AR59: =IF(AND($D59="White Cottage",$G59=""),ROW(),"") | AS59: =IF(AND($D59="Villa Nella",$G59=""),ROW(),"") | AT59: =IF(AND($D59="Nel Cuore di Lanciano",$G59<>""),ROW(),"") | AU59: =IF(AND($D59="Nel Cuore di Lanciano",$G59=""),ROW(),"")
A60: 46229 | B60: 46235 | C60: =IF(A60<>"",B60-A60,"") -> 6 | D60: Casa Letizia | E60: Massimo Marfella | F60: 2 ad + 1 n | G60: booking.com | H60: 687.31 | I60: =IF(AND(H60<>"",C60<>"",C60<>0),H60/C60,"") -> 114.55167 | J60: =IF(AND(ISNUMBER(SEARCH("booking",G60)),OR(D60="Via San Rocco",D60="Via Cavour")),H60*0.165,IF(ISNUMBER(SEARCH("airbnb",G60)),H60*0.155,IF(ISNUMBER(SEARCH("booking",G60)),H60*0.15,""))) -> 103.0965 | K60: VISA | L60: 10 | M60: =IF(H60<>"",H60*0.25,"") -> 171.8275 | N60: 20 | O60: MARILENA | P60: 26.14 | R60: NON RIMBORSABILE - pagamento effettuato 30-01 | S60: =IF(AND($D60="Sotto la Quercia",$G60<>""),ROW(),"") | T60: =IF($D60="Villa Elena",COUNTIF($D$3:$D60,"Villa Elena"),"") | U60: =IF(AND($D60="Casa Letizia",$G60<>""),ROW(),"") -> 60 | V60: =IF(AND($D60="Casa nel Borgo",$G60<>""),ROW(),"") | W60: =IF(AND($D60="Via San Rocco",$G60<>""),ROW(),"") | X60: =IF(AND($D60="Via Cavour",$G60<>""),ROW(),"") | Y60: =IF(AND($D60="Miramare",$G60<>""),ROW(),"") | Z60: =IF(AND($D60="Agantonio",$G60<>""),ROW(),"") | AA60: =IF(AND($D60="Casa Bella Gialla",$G60<>""),ROW(),"") | AB60: =IF(AND($D60="Casa Verde Oliva",$G60<>""),ROW(),"") | AC60: =IF(AND($D60="Casa Nicola",$G60<>""),ROW(),"") | AD60: =IF(AND($D60="White Cottage",$G60<>""),ROW(),"") | AE60: =IF(AND($D60="Villa Nella",$G60<>""),ROW(),"") | AF60: =IF(AND($D60="Villa Elena",$G60<>""),ROW(),"") | AG60: =IF(AND($D60="Sotto la Quercia",$G60=""),ROW(),"") | AH60: =IF(AND($D60="Villa Elena",$G60=""),ROW(),"") | AI60: =IF(AND($D60="Casa Letizia",$G60=""),ROW(),"") | AJ60: =IF(AND($D60="Casa nel Borgo",$G60=""),ROW(),"") | AK60: =IF(AND($D60="Via San Rocco",$G60=""),ROW(),"") | AL60: =IF(AND($D60="Via Cavour",$G60=""),ROW(),"") | AM60: =IF(AND($D60="Miramare",$G60=""),ROW(),"") | AN60: =IF(AND($D60="Agantonio",$G60=""),ROW(),"") | AO60: =IF(AND($D60="Casa Bella Gialla",$G60=""),ROW(),"") | AP60: =IF(AND($D60="Casa Verde Oliva",$G60=""),ROW(),"") | AQ60: =IF(AND($D60="Casa Nicola",$G60=""),ROW(),"") | AR60: =IF(AND($D60="White Cottage",$G60=""),ROW(),"") | AS60: =IF(AND($D60="Villa Nella",$G60=""),ROW(),"") | AT60: =IF(AND($D60="Nel Cuore di Lanciano",$G60<>""),ROW(),"") | AU60: =IF(AND($D60="Nel Cuore di Lanciano",$G60=""),ROW(),"")
A61: 46229 | B61: 46234 | C61: =IF(A61<>"",B61-A61,"") -> 5 | D61: Casa Verde Oliva | E61: Erika Sciuttini | F61: 2 ad | G61: booking.com | H61: 807.3 | I61: =IF(AND(H61<>"",C61<>"",C61<>0),H61/C61,"") -> 161.46 | J61: =IF(AND(ISNUMBER(SEARCH("booking",G61)),OR(D61="Via San Rocco",D61="Via Cavour")),H61*0.165,IF(ISNUMBER(SEARCH("airbnb",G61)),H61*0.155,IF(ISNUMBER(SEARCH("booking",G61)),H61*0.15,""))) -> 121.095 | L61: 10 | M61: =IF(H61<>"",H61*0.25,"") -> 201.825 | N61: 20 | O61: MARILENA | P61: 10.38 | S61: =IF(AND($D61="Sotto la Quercia",$G61<>""),ROW(),"") | T61: =IF($D61="Villa Elena",COUNTIF($D$3:$D61,"Villa Elena"),"") | U61: =IF(AND($D61="Casa Letizia",$G61<>""),ROW(),"") | V61: =IF(AND($D61="Casa nel Borgo",$G61<>""),ROW(),"") | W61: =IF(AND($D61="Via San Rocco",$G61<>""),ROW(),"") | X61: =IF(AND($D61="Via Cavour",$G61<>""),ROW(),"") | Y61: =IF(AND($D61="Miramare",$G61<>""),ROW(),"") | Z61: =IF(AND($D61="Agantonio",$G61<>""),ROW(),"") | AA61: =IF(AND($D61="Casa Bella Gialla",$G61<>""),ROW(),"") | AB61: =IF(AND($D61="Casa Verde Oliva",$G61<>""),ROW(),"") -> 61 | AC61: =IF(AND($D61="Casa Nicola",$G61<>""),ROW(),"") | AD61: =IF(AND($D61="White Cottage",$G61<>""),ROW(),"") | AE61: =IF(AND($D61="Villa Nella",$G61<>""),ROW(),"") | AF61: =IF(AND($D61="Villa Elena",$G61<>""),ROW(),"") | AG61: =IF(AND($D61="Sotto la Quercia",$G61=""),ROW(),"") | AH61: =IF(AND($D61="Villa Elena",$G61=""),ROW(),"") | AI61: =IF(AND($D61="Casa Letizia",$G61=""),ROW(),"") | AJ61: =IF(AND($D61="Casa nel Borgo",$G61=""),ROW(),"") | AK61: =IF(AND($D61="Via San Rocco",$G61=""),ROW(),"") | AL61: =IF(AND($D61="Via Cavour",$G61=""),ROW(),"") | AM61: =IF(AND($D61="Miramare",$G61=""),ROW(),"") | AN61: =IF(AND($D61="Agantonio",$G61=""),ROW(),"") | AO61: =IF(AND($D61="Casa Bella Gialla",$G61=""),ROW(),"") | AP61: =IF(AND($D61="Casa Verde Oliva",$G61=""),ROW(),"") | AQ61: =IF(AND($D61="Casa Nicola",$G61=""),ROW(),"") | AR61: =IF(AND($D61="White Cottage",$G61=""),ROW(),"") | AS61: =IF(AND($D61="Villa Nella",$G61=""),ROW(),"") | AT61: =IF(AND($D61="Nel Cuore di Lanciano",$G61<>""),ROW(),"") | AU61: =IF(AND($D61="Nel Cuore di Lanciano",$G61=""),ROW(),"")
A62: 46230 | B62: 46237 | C62: =IF(A62<>"",B62-A62,"") -> 7 | D62: Nel Cuore di Lanciano | E62: Salvatore Belsito | F62: 2 ad | G62: booking.com | H62: 554.4 | I62: =IF(AND(H62<>"",C62<>"",C62<>0),H62/C62,"") -> 79.2 | J62: =IF(AND(ISNUMBER(SEARCH("booking",G62)),OR(D62="Via San Rocco",D62="Via Cavour")),H62*0.165,IF(ISNUMBER(SEARCH("airbnb",G62)),H62*0.155,IF(ISNUMBER(SEARCH("booking",G62)),H62*0.15,""))) -> 83.16 | L62: 4 | M62: =IF(H62<>"",H62*0.25,"") -> 138.6 | N62: 50 | O62: MARILENA | P62: 27.72 | S62: =IF(AND($D62="Sotto la Quercia",$G62<>""),ROW(),"") | T62: =IF($D62="Villa Elena",COUNTIF($D$3:$D62,"Villa Elena"),"") | U62: =IF(AND($D62="Casa Letizia",$G62<>""),ROW(),"") | V62: =IF(AND($D62="Casa nel Borgo",$G62<>""),ROW(),"") | W62: =IF(AND($D62="Via San Rocco",$G62<>""),ROW(),"") | X62: =IF(AND($D62="Via Cavour",$G62<>""),ROW(),"") | Y62: =IF(AND($D62="Miramare",$G62<>""),ROW(),"") | Z62: =IF(AND($D62="Agantonio",$G62<>""),ROW(),"") | AA62: =IF(AND($D62="Casa Bella Gialla",$G62<>""),ROW(),"") | AB62: =IF(AND($D62="Casa Verde Oliva",$G62<>""),ROW(),"") | AC62: =IF(AND($D62="Casa Nicola",$G62<>""),ROW(),"") | AD62: =IF(AND($D62="White Cottage",$G62<>""),ROW(),"") | AE62: =IF(AND($D62="Villa Nella",$G62<>""),ROW(),"") | AF62: =IF(AND($D62="Villa Elena",$G62<>""),ROW(),"") | AG62: =IF(AND($D62="Sotto la Quercia",$G62=""),ROW(),"") | AH62: =IF(AND($D62="Villa Elena",$G62=""),ROW(),"") | AI62: =IF(AND($D62="Casa Letizia",$G62=""),ROW(),"") | AJ62: =IF(AND($D62="Casa nel Borgo",$G62=""),ROW(),"") | AK62: =IF(AND($D62="Via San Rocco",$G62=""),ROW(),"") | AL62: =IF(AND($D62="Via Cavour",$G62=""),ROW(),"") | AM62: =IF(AND($D62="Miramare",$G62=""),ROW(),"") | AN62: =IF(AND($D62="Agantonio",$G62=""),ROW(),"") | AO62: =IF(AND($D62="Casa Bella Gialla",$G62=""),ROW(),"") | AP62: =IF(AND($D62="Casa Verde Oliva",$G62=""),ROW(),"") | AQ62: =IF(AND($D62="Casa Nicola",$G62=""),ROW(),"") | AR62: =IF(AND($D62="White Cottage",$G62=""),ROW(),"") | AS62: =IF(AND($D62="Villa Nella",$G62=""),ROW(),"") | AT62: =IF(AND($D62="Nel Cuore di Lanciano",$G62<>""),ROW(),"") -> 62 | AU62: =IF(AND($D62="Nel Cuore di Lanciano",$G62=""),ROW(),"")
A63: 46231 | B63: 46237 | C63: =IF(A63<>"",B63-A63,"") -> 6 | D63: Casa nel Borgo | E63: Donatella Chiodo | F63: 2 ad | G63: diretta | H63: 420 | I63: =IF(AND(H63<>"",C63<>"",C63<>0),H63/C63,"") -> 70 | J63: =IF(AND(ISNUMBER(SEARCH("booking",G63)),OR(D63="Via San Rocco",D63="Via Cavour")),H63*0.165,IF(ISNUMBER(SEARCH("airbnb",G63)),H63*0.155,IF(ISNUMBER(SEARCH("booking",G63)),H63*0.15,""))) | K63: MASTER | L63: 4 | M63: =IF(H63<>"",H63*0.25,"") -> 105 | N63: 20 | O63: MARILENA | P63: 12.15 | S63: =IF(AND($D63="Sotto la Quercia",$G63<>""),ROW(),"") | T63: =IF($D63="Villa Elena",COUNTIF($D$3:$D63,"Villa Elena"),"") | U63: =IF(AND($D63="Casa Letizia",$G63<>""),ROW(),"") | V63: =IF(AND($D63="Casa nel Borgo",$G63<>""),ROW(),"") -> 63 | W63: =IF(AND($D63="Via San Rocco",$G63<>""),ROW(),"") | X63: =IF(AND($D63="Via Cavour",$G63<>""),ROW(),"") | Y63: =IF(AND($D63="Miramare",$G63<>""),ROW(),"") | Z63: =IF(AND($D63="Agantonio",$G63<>""),ROW(),"") | AA63: =IF(AND($D63="Casa Bella Gialla",$G63<>""),ROW(),"") | AB63: =IF(AND($D63="Casa Verde Oliva",$G63<>""),ROW(),"") | AC63: =IF(AND($D63="Casa Nicola",$G63<>""),ROW(),"") | AD63: =IF(AND($D63="White Cottage",$G63<>""),ROW(),"") | AE63: =IF(AND($D63="Villa Nella",$G63<>""),ROW(),"") | AF63: =IF(AND($D63="Villa Elena",$G63<>""),ROW(),"") | AG63: =IF(AND($D63="Sotto la Quercia",$G63=""),ROW(),"") | AH63: =IF(AND($D63="Villa Elena",$G63=""),ROW(),"") | AI63: =IF(AND($D63="Casa Letizia",$G63=""),ROW(),"") | AJ63: =IF(AND($D63="Casa nel Borgo",$G63=""),ROW(),"") | AK63: =IF(AND($D63="Via San Rocco",$G63=""),ROW(),"") | AL63: =IF(AND($D63="Via Cavour",$G63=""),ROW(),"") | AM63: =IF(AND($D63="Miramare",$G63=""),ROW(),"") | AN63: =IF(AND($D63="Agantonio",$G63=""),ROW(),"") | AO63: =IF(AND($D63="Casa Bella Gialla",$G63=""),ROW(),"") | AP63: =IF(AND($D63="Casa Verde Oliva",$G63=""),ROW(),"") | AQ63: =IF(AND($D63="Casa Nicola",$G63=""),ROW(),"") | AR63: =IF(AND($D63="White Cottage",$G63=""),ROW(),"") | AS63: =IF(AND($D63="Villa Nella",$G63=""),ROW(),"") | AT63: =IF(AND($D63="Nel Cuore di Lanciano",$G63<>""),ROW(),"") | AU63: =IF(AND($D63="Nel Cuore di Lanciano",$G63=""),ROW(),"")
A64: 46231 | B64: 46234 | C64: =IF(A64<>"",B64-A64,"") -> 3 | D64: Miramare | E64: Baracca Pasquale | F64: 4 ad | G64: diretta | H64: 582 | I64: =IF(AND(H64<>"",C64<>"",C64<>0),H64/C64,"") -> 194 | J64: =IF(AND(ISNUMBER(SEARCH("booking",G64)),OR(D64="Via San Rocco",D64="Via Cavour")),H64*0.165,IF(ISNUMBER(SEARCH("airbnb",G64)),H64*0.155,IF(ISNUMBER(SEARCH("booking",G64)),H64*0.15,""))) | K64: BONIFICO | L64: 12 | M64: =IF(H64<>"",H64*0.25,"") -> 145.5 | N64: 0 | O64: MARILENA | P64: 0 | R64: prolungato soggiorno | S64: =IF(AND($D64="Sotto la Quercia",$G64<>""),ROW(),"") | T64: =IF($D64="Villa Elena",COUNTIF($D$3:$D64,"Villa Elena"),"") | U64: =IF(AND($D64="Casa Letizia",$G64<>""),ROW(),"") | V64: =IF(AND($D64="Casa nel Borgo",$G64<>""),ROW(),"") | W64: =IF(AND($D64="Via San Rocco",$G64<>""),ROW(),"") | X64: =IF(AND($D64="Via Cavour",$G64<>""),ROW(),"") | Y64: =IF(AND($D64="Miramare",$G64<>""),ROW(),"") -> 64 | Z64: =IF(AND($D64="Agantonio",$G64<>""),ROW(),"") | AA64: =IF(AND($D64="Casa Bella Gialla",$G64<>""),ROW(),"") | AB64: =IF(AND($D64="Casa Verde Oliva",$G64<>""),ROW(),"") | AC64: =IF(AND($D64="Casa Nicola",$G64<>""),ROW(),"") | AD64: =IF(AND($D64="White Cottage",$G64<>""),ROW(),"") | AE64: =IF(AND($D64="Villa Nella",$G64<>""),ROW(),"") | AF64: =IF(AND($D64="Villa Elena",$G64<>""),ROW(),"") | AG64: =IF(AND($D64="Sotto la Quercia",$G64=""),ROW(),"") | AH64: =IF(AND($D64="Villa Elena",$G64=""),ROW(),"") | AI64: =IF(AND($D64="Casa Letizia",$G64=""),ROW(),"") | AJ64: =IF(AND($D64="Casa nel Borgo",$G64=""),ROW(),"") | AK64: =IF(AND($D64="Via San Rocco",$G64=""),ROW(),"") | AL64: =IF(AND($D64="Via Cavour",$G64=""),ROW(),"") | AM64: =IF(AND($D64="Miramare",$G64=""),ROW(),"") | AN64: =IF(AND($D64="Agantonio",$G64=""),ROW(),"") | AO64: =IF(AND($D64="Casa Bella Gialla",$G64=""),ROW(),"") | AP64: =IF(AND($D64="Casa Verde Oliva",$G64=""),ROW(),"") | AQ64: =IF(AND($D64="Casa Nicola",$G64=""),ROW(),"") | AR64: =IF(AND($D64="White Cottage",$G64=""),ROW(),"") | AS64: =IF(AND($D64="Villa Nella",$G64=""),ROW(),"") | AT64: =IF(AND($D64="Nel Cuore di Lanciano",$G64<>""),ROW(),"") | AU64: =IF(AND($D64="Nel Cuore di Lanciano",$G64=""),ROW(),"")
A65: 46232 | B65: 46237 | C65: =IF(A65<>"",B65-A65,"") -> 5 | D65: Via San Rocco | E65: Luigi Piovano | F65: 2 ad | G65: diretta | H65: 475 | I65: =IF(AND(H65<>"",C65<>"",C65<>0),H65/C65,"") -> 95 | J65: =IF(AND(ISNUMBER(SEARCH("booking",G65)),OR(D65="Via San Rocco",D65="Via Cavour")),H65*0.165,IF(ISNUMBER(SEARCH("airbnb",G65)),H65*0.155,IF(ISNUMBER(SEARCH("booking",G65)),H65*0.15,""))) | M65: =IF(H65<>"",H65*0.1,"") -> 47.5 | S65: =IF(AND($D65="Sotto la Quercia",$G65<>""),ROW(),"") | T65: =IF($D65="Villa Elena",COUNTIF($D$3:$D65,"Villa Elena"),"") | U65: =IF(AND($D65="Casa Letizia",$G65<>""),ROW(),"") | V65: =IF(AND($D65="Casa nel Borgo",$G65<>""),ROW(),"") | W65: =IF(AND($D65="Via San Rocco",$G65<>""),ROW(),"") -> 65 | X65: =IF(AND($D65="Via Cavour",$G65<>""),ROW(),"") | Y65: =IF(AND($D65="Miramare",$G65<>""),ROW(),"") | Z65: =IF(AND($D65="Agantonio",$G65<>""),ROW(),"") | AA65: =IF(AND($D65="Casa Bella Gialla",$G65<>""),ROW(),"") | AB65: =IF(AND($D65="Casa Verde Oliva",$G65<>""),ROW(),"") | AC65: =IF(AND($D65="Casa Nicola",$G65<>""),ROW(),"") | AD65: =IF(AND($D65="White Cottage",$G65<>""),ROW(),"") | AE65: =IF(AND($D65="Villa Nella",$G65<>""),ROW(),"") | AF65: =IF(AND($D65="Villa Elena",$G65<>""),ROW(),"") | AG65: =IF(AND($D65="Sotto la Quercia",$G65=""),ROW(),"") | AH65: =IF(AND($D65="Villa Elena",$G65=""),ROW(),"") | AI65: =IF(AND($D65="Casa Letizia",$G65=""),ROW(),"") | AJ65: =IF(AND($D65="Casa nel Borgo",$G65=""),ROW(),"") | AK65: =IF(AND($D65="Via San Rocco",$G65=""),ROW(),"") | AL65: =IF(AND($D65="Via Cavour",$G65=""),ROW(),"") | AM65: =IF(AND($D65="Miramare",$G65=""),ROW(),"") | AN65: =IF(AND($D65="Agantonio",$G65=""),ROW(),"") | AO65: =IF(AND($D65="Casa Bella Gialla",$G65=""),ROW(),"") | AP65: =IF(AND($D65="Casa Verde Oliva",$G65=""),ROW(),"") | AQ65: =IF(AND($D65="Casa Nicola",$G65=""),ROW(),"") | AR65: =IF(AND($D65="White Cottage",$G65=""),ROW(),"") | AS65: =IF(AND($D65="Villa Nella",$G65=""),ROW(),"") | AT65: =IF(AND($D65="Nel Cuore di Lanciano",$G65<>""),ROW(),"") | AU65: =IF(AND($D65="Nel Cuore di Lanciano",$G65=""),ROW(),"")
A66: 46235 | B66: 46241 | C66: =IF(A66<>"",B66-A66,"") -> 6 | D66: Casa Verde Oliva | E66: Angelo Città | F66: 3 ad | G66: booking.com | H66: 458 | I66: =IF(AND(H66<>"",C66<>"",C66<>0),H66/C66,"") -> 76.333333 | J66: =IF(AND(ISNUMBER(SEARCH("booking",G66)),OR(D66="Via San Rocco",D66="Via Cavour")),H66*0.165,IF(ISNUMBER(SEARCH("airbnb",G66)),H66*0.155,IF(ISNUMBER(SEARCH("booking",G66)),H66*0.15,""))) -> 68.7 | K66: MASTER | L66: 15 | M66: =IF(H66<>"",H66*0.25,"") -> 114.5 | N66: 20 | O66: MARILENA | P66: 17.52 | S66: =IF(AND($D66="Sotto la Quercia",$G66<>""),ROW(),"") | T66: =IF($D66="Villa Elena",COUNTIF($D$3:$D66,"Villa Elena"),"") | U66: =IF(AND($D66="Casa Letizia",$G66<>""),ROW(),"") | V66: =IF(AND($D66="Casa nel Borgo",$G66<>""),ROW(),"") | W66: =IF(AND($D66="Via San Rocco",$G66<>""),ROW(),"") | X66: =IF(AND($D66="Via Cavour",$G66<>""),ROW(),"") | Y66: =IF(AND($D66="Miramare",$G66<>""),ROW(),"") | Z66: =IF(AND($D66="Agantonio",$G66<>""),ROW(),"") | AA66: =IF(AND($D66="Casa Bella Gialla",$G66<>""),ROW(),"") | AB66: =IF(AND($D66="Casa Verde Oliva",$G66<>""),ROW(),"") -> 66 | AC66: =IF(AND($D66="Casa Nicola",$G66<>""),ROW(),"") | AD66: =IF(AND($D66="White Cottage",$G66<>""),ROW(),"") | AE66: =IF(AND($D66="Villa Nella",$G66<>""),ROW(),"") | AF66: =IF(AND($D66="Villa Elena",$G66<>""),ROW(),"") | AG66: =IF(AND($D66="Sotto la Quercia",$G66=""),ROW(),"") | AH66: =IF(AND($D66="Villa Elena",$G66=""),ROW(),"") | AI66: =IF(AND($D66="Casa Letizia",$G66=""),ROW(),"") | AJ66: =IF(AND($D66="Casa nel Borgo",$G66=""),ROW(),"") | AK66: =IF(AND($D66="Via San Rocco",$G66=""),ROW(),"") | AL66: =IF(AND($D66="Via Cavour",$G66=""),ROW(),"") | AM66: =IF(AND($D66="Miramare",$G66=""),ROW(),"") | AN66: =IF(AND($D66="Agantonio",$G66=""),ROW(),"") | AO66: =IF(AND($D66="Casa Bella Gialla",$G66=""),ROW(),"") | AP66: =IF(AND($D66="Casa Verde Oliva",$G66=""),ROW(),"") | AQ66: =IF(AND($D66="Casa Nicola",$G66=""),ROW(),"") | AR66: =IF(AND($D66="White Cottage",$G66=""),ROW(),"") | AS66: =IF(AND($D66="Villa Nella",$G66=""),ROW(),"") | AT66: =IF(AND($D66="Nel Cuore di Lanciano",$G66<>""),ROW(),"") | AU66: =IF(AND($D66="Nel Cuore di Lanciano",$G66=""),ROW(),"")
A67: 46235 | B67: 46242 | C67: =IF(A67<>"",B67-A67,"") -> 7 | D67: Miramare | E67: Napolitano Antonio | F67: 2 ad | G67: booking.com | H67: 830.76 | I67: =IF(AND(H67<>"",C67<>"",C67<>0),H67/C67,"") -> 118.68 | J67: =IF(AND(ISNUMBER(SEARCH("booking",G67)),OR(D67="Via San Rocco",D67="Via Cavour")),H67*0.165,IF(ISNUMBER(SEARCH("airbnb",G67)),H67*0.155,IF(ISNUMBER(SEARCH("booking",G67)),H67*0.15,""))) -> 124.614 | K67: contanti | L67: 14 | M67: =IF(H67<>"",H67*0.25,"") -> 207.69 | N67: 40 | O67: MARILENA | P67: 10.38 | S67: =IF(AND($D67="Sotto la Quercia",$G67<>""),ROW(),"") | T67: =IF($D67="Villa Elena",COUNTIF($D$3:$D67,"Villa Elena"),"") | U67: =IF(AND($D67="Casa Letizia",$G67<>""),ROW(),"") | V67: =IF(AND($D67="Casa nel Borgo",$G67<>""),ROW(),"") | W67: =IF(AND($D67="Via San Rocco",$G67<>""),ROW(),"") | X67: =IF(AND($D67="Via Cavour",$G67<>""),ROW(),"") | Y67: =IF(AND($D67="Miramare",$G67<>""),ROW(),"") -> 67 | Z67: =IF(AND($D67="Agantonio",$G67<>""),ROW(),"") | AA67: =IF(AND($D67="Casa Bella Gialla",$G67<>""),ROW(),"") | AB67: =IF(AND($D67="Casa Verde Oliva",$G67<>""),ROW(),"") | AC67: =IF(AND($D67="Casa Nicola",$G67<>""),ROW(),"") | AD67: =IF(AND($D67="White Cottage",$G67<>""),ROW(),"") | AE67: =IF(AND($D67="Villa Nella",$G67<>""),ROW(),"") | AF67: =IF(AND($D67="Villa Elena",$G67<>""),ROW(),"") | AG67: =IF(AND($D67="Sotto la Quercia",$G67=""),ROW(),"") | AH67: =IF(AND($D67="Villa Elena",$G67=""),ROW(),"") | AI67: =IF(AND($D67="Casa Letizia",$G67=""),ROW(),"") | AJ67: =IF(AND($D67="Casa nel Borgo",$G67=""),ROW(),"") | AK67: =IF(AND($D67="Via San Rocco",$G67=""),ROW(),"") | AL67: =IF(AND($D67="Via Cavour",$G67=""),ROW(),"") | AM67: =IF(AND($D67="Miramare",$G67=""),ROW(),"") | AN67: =IF(AND($D67="Agantonio",$G67=""),ROW(),"") | AO67: =IF(AND($D67="Casa Bella Gialla",$G67=""),ROW(),"") | AP67: =IF(AND($D67="Casa Verde Oliva",$G67=""),ROW(),"") | AQ67: =IF(AND($D67="Casa Nicola",$G67=""),ROW(),"") | AR67: =IF(AND($D67="White Cottage",$G67=""),ROW(),"") | AS67: =IF(AND($D67="Villa Nella",$G67=""),ROW(),"") | AT67: =IF(AND($D67="Nel Cuore di Lanciano",$G67<>""),ROW(),"") | AU67: =IF(AND($D67="Nel Cuore di Lanciano",$G67=""),ROW(),"")
A68: 46236 | B68: 46242 | C68: =IF(A68<>"",B68-A68,"") -> 6 | D68: Casa Letizia | E68: Barbara Maresti | F68: 2 ad | G68: booking.com | H68: 706.96 | I68: =IF(AND(H68<>"",C68<>"",C68<>0),H68/C68,"") -> 117.82667 | J68: =IF(AND(ISNUMBER(SEARCH("booking",G68)),OR(D68="Via San Rocco",D68="Via Cavour")),H68*0.165,IF(ISNUMBER(SEARCH("airbnb",G68)),H68*0.155,IF(ISNUMBER(SEARCH("booking",G68)),H68*0.15,""))) -> 106.044 | K68: MASTER | L68: 10 | M68: =IF(H68<>"",H68*0.25,"") -> 176.74 | N68: 20 | O68: MARILENA | P68: 13.56 | S68: =IF(AND($D68="Sotto la Quercia",$G68<>""),ROW(),"") | T68: =IF($D68="Villa Elena",COUNTIF($D$3:$D68,"Villa Elena"),"") | U68: =IF(AND($D68="Casa Letizia",$G68<>""),ROW(),"") -> 68 | V68: =IF(AND($D68="Casa nel Borgo",$G68<>""),ROW(),"") | W68: =IF(AND($D68="Via San Rocco",$G68<>""),ROW(),"") | X68: =IF(AND($D68="Via Cavour",$G68<>""),ROW(),"") | Y68: =IF(AND($D68="Miramare",$G68<>""),ROW(),"") | Z68: =IF(AND($D68="Agantonio",$G68<>""),ROW(),"") | AA68: =IF(AND($D68="Casa Bella Gialla",$G68<>""),ROW(),"") | AB68: =IF(AND($D68="Casa Verde Oliva",$G68<>""),ROW(),"") | AC68: =IF(AND($D68="Casa Nicola",$G68<>""),ROW(),"") | AD68: =IF(AND($D68="White Cottage",$G68<>""),ROW(),"") | AE68: =IF(AND($D68="Villa Nella",$G68<>""),ROW(),"") | AF68: =IF(AND($D68="Villa Elena",$G68<>""),ROW(),"") | AG68: =IF(AND($D68="Sotto la Quercia",$G68=""),ROW(),"") | AH68: =IF(AND($D68="Villa Elena",$G68=""),ROW(),"") | AI68: =IF(AND($D68="Casa Letizia",$G68=""),ROW(),"") | AJ68: =IF(AND($D68="Casa nel Borgo",$G68=""),ROW(),"") | AK68: =IF(AND($D68="Via San Rocco",$G68=""),ROW(),"") | AL68: =IF(AND($D68="Via Cavour",$G68=""),ROW(),"") | AM68: =IF(AND($D68="Miramare",$G68=""),ROW(),"") | AN68: =IF(AND($D68="Agantonio",$G68=""),ROW(),"") | AO68: =IF(AND($D68="Casa Bella Gialla",$G68=""),ROW(),"") | AP68: =IF(AND($D68="Casa Verde Oliva",$G68=""),ROW(),"") | AQ68: =IF(AND($D68="Casa Nicola",$G68=""),ROW(),"") | AR68: =IF(AND($D68="White Cottage",$G68=""),ROW(),"") | AS68: =IF(AND($D68="Villa Nella",$G68=""),ROW(),"") | AT68: =IF(AND($D68="Nel Cuore di Lanciano",$G68<>""),ROW(),"") | AU68: =IF(AND($D68="Nel Cuore di Lanciano",$G68=""),ROW(),"")
A69: 46237 | B69: 46244 | C69: =IF(A69<>"",B69-A69,"") -> 7 | D69: Villa Nella | E69: Annamaria Cantadori | F69: 8 | G69: diretta | H69: 3400 | I69: =IF(AND(H69<>"",C69<>"",C69<>0),H69/C69,"") -> 485.71429 | J69: 0 | K69: cash, master e bonifico | M69: =IF(H69<>"",H69*0.25,"") -> 850 | N69: 60 | O69: MARILENA | P69: 43 | S69: =IF(AND($D69="Sotto la Quercia",$G69<>""),ROW(),"") | T69: =IF($D69="Villa Elena",COUNTIF($D$3:$D69,"Villa Elena"),"") | U69: =IF(AND($D69="Casa Letizia",$G69<>""),ROW(),"") | V69: =IF(AND($D69="Casa nel Borgo",$G69<>""),ROW(),"") | W69: =IF(AND($D69="Via San Rocco",$G69<>""),ROW(),"") | X69: =IF(AND($D69="Via Cavour",$G69<>""),ROW(),"") | Y69: =IF(AND($D69="Miramare",$G69<>""),ROW(),"") | Z69: =IF(AND($D69="Agantonio",$G69<>""),ROW(),"") | AA69: =IF(AND($D69="Casa Bella Gialla",$G69<>""),ROW(),"") | AB69: =IF(AND($D69="Casa Verde Oliva",$G69<>""),ROW(),"") | AC69: =IF(AND($D69="Casa Nicola",$G69<>""),ROW(),"") | AD69: =IF(AND($D69="White Cottage",$G69<>""),ROW(),"") | AE69: =IF(AND($D69="Villa Nella",$G69<>""),ROW(),"") -> 69 | AF69: =IF(AND($D69="Villa Elena",$G69<>""),ROW(),"") | AG69: =IF(AND($D69="Sotto la Quercia",$G69=""),ROW(),"") | AH69: =IF(AND($D69="Villa Elena",$G69=""),ROW(),"") | AI69: =IF(AND($D69="Casa Letizia",$G69=""),ROW(),"") | AJ69: =IF(AND($D69="Casa nel Borgo",$G69=""),ROW(),"") | AK69: =IF(AND($D69="Via San Rocco",$G69=""),ROW(),"") | AL69: =IF(AND($D69="Via Cavour",$G69=""),ROW(),"") | AM69: =IF(AND($D69="Miramare",$G69=""),ROW(),"") | AN69: =IF(AND($D69="Agantonio",$G69=""),ROW(),"") | AO69: =IF(AND($D69="Casa Bella Gialla",$G69=""),ROW(),"") | AP69: =IF(AND($D69="Casa Verde Oliva",$G69=""),ROW(),"") | AQ69: =IF(AND($D69="Casa Nicola",$G69=""),ROW(),"") | AR69: =IF(AND($D69="White Cottage",$G69=""),ROW(),"") | AS69: =IF(AND($D69="Villa Nella",$G69=""),ROW(),"") | AT69: =IF(AND($D69="Nel Cuore di Lanciano",$G69<>""),ROW(),"") | AU69: =IF(AND($D69="Nel Cuore di Lanciano",$G69=""),ROW(),"")
A70: 46237 | B70: 46245 | C70: =IF(A70<>"",B70-A70,"") -> 8 | D70: Nel Cuore di Lanciano | E70: Giulio Querzoli | F70: 2 ad | G70: booking.com | H70: 657 | I70: =IF(AND(H70<>"",C70<>"",C70<>0),H70/C70,"") -> 82.125 | J70: =IF(AND(ISNUMBER(SEARCH("booking",G70)),OR(D70="Via San Rocco",D70="Via Cavour")),H70*0.165,IF(ISNUMBER(SEARCH("airbnb",G70)),H70*0.155,IF(ISNUMBER(SEARCH("booking",G70)),H70*0.15,""))) -> 98.55 | K70: MASTER | L70: 4 | M70: =IF(H70<>"",H70*0.25,"") -> 164.25 | N70: 30 | O70: MARILENA | P70: 10.38 | S70: =IF(AND($D70="Sotto la Quercia",$G70<>""),ROW(),"") | T70: =IF($D70="Villa Elena",COUNTIF($D$3:$D70,"Villa Elena"),"") | U70: =IF(AND($D70="Casa Letizia",$G70<>""),ROW(),"") | V70: =IF(AND($D70="Casa nel Borgo",$G70<>""),ROW(),"") | W70: =IF(AND($D70="Via San Rocco",$G70<>""),ROW(),"") | X70: =IF(AND($D70="Via Cavour",$G70<>""),ROW(),"") | Y70: =IF(AND($D70="Miramare",$G70<>""),ROW(),"") | Z70: =IF(AND($D70="Agantonio",$G70<>""),ROW(),"") | AA70: =IF(AND($D70="Casa Bella Gialla",$G70<>""),ROW(),"") | AB70: =IF(AND($D70="Casa Verde Oliva",$G70<>""),ROW(),"") | AC70: =IF(AND($D70="Casa Nicola",$G70<>""),ROW(),"") | AD70: =IF(AND($D70="White Cottage",$G70<>""),ROW(),"") | AE70: =IF(AND($D70="Villa Nella",$G70<>""),ROW(),"") | AF70: =IF(AND($D70="Villa Elena",$G70<>""),ROW(),"") | AG70: =IF(AND($D70="Sotto la Quercia",$G70=""),ROW(),"") | AH70: =IF(AND($D70="Villa Elena",$G70=""),ROW(),"") | AI70: =IF(AND($D70="Casa Letizia",$G70=""),ROW(),"") | AJ70: =IF(AND($D70="Casa nel Borgo",$G70=""),ROW(),"") | AK70: =IF(AND($D70="Via San Rocco",$G70=""),ROW(),"") | AL70: =IF(AND($D70="Via Cavour",$G70=""),ROW(),"") | AM70: =IF(AND($D70="Miramare",$G70=""),ROW(),"") | AN70: =IF(AND($D70="Agantonio",$G70=""),ROW(),"") | AO70: =IF(AND($D70="Casa Bella Gialla",$G70=""),ROW(),"") | AP70: =IF(AND($D70="Casa Verde Oliva",$G70=""),ROW(),"") | AQ70: =IF(AND($D70="Casa Nicola",$G70=""),ROW(),"") | AR70: =IF(AND($D70="White Cottage",$G70=""),ROW(),"") | AS70: =IF(AND($D70="Villa Nella",$G70=""),ROW(),"") | AT70: =IF(AND($D70="Nel Cuore di Lanciano",$G70<>""),ROW(),"") -> 70 | AU70: =IF(AND($D70="Nel Cuore di Lanciano",$G70=""),ROW(),"")
A71: 46237 | B71: 46241 | C71: =IF(A71<>"",B71-A71,"") -> 4 | D71: Casa nel Borgo | E71: Antonio Salzano | F71: 2 ad | G71: booking.com | H71: 345.34 | I71: =IF(AND(H71<>"",C71<>"",C71<>0),H71/C71,"") -> 86.335 | J71: =IF(AND(ISNUMBER(SEARCH("booking",G71)),OR(D71="Via San Rocco",D71="Via Cavour")),H71*0.165,IF(ISNUMBER(SEARCH("airbnb",G71)),H71*0.155,IF(ISNUMBER(SEARCH("booking",G71)),H71*0.15,""))) -> 51.801 | K71: MASTER | L71: 4 | M71: =IF(H71<>"",H71*0.25,"") -> 86.335 | N71: 20 | O71: MARILENA | P71: 10.38 | S71: =IF(AND($D71="Sotto la Quercia",$G71<>""),ROW(),"") | T71: =IF($D71="Villa Elena",COUNTIF($D$3:$D71,"Villa Elena"),"") | U71: =IF(AND($D71="Casa Letizia",$G71<>""),ROW(),"") | V71: =IF(AND($D71="Casa nel Borgo",$G71<>""),ROW(),"") -> 71 | W71: =IF(AND($D71="Via San Rocco",$G71<>""),ROW(),"") | X71: =IF(AND($D71="Via Cavour",$G71<>""),ROW(),"") | Y71: =IF(AND($D71="Miramare",$G71<>""),ROW(),"") | Z71: =IF(AND($D71="Agantonio",$G71<>""),ROW(),"") | AA71: =IF(AND($D71="Casa Bella Gialla",$G71<>""),ROW(),"") | AB71: =IF(AND($D71="Casa Verde Oliva",$G71<>""),ROW(),"") | AC71: =IF(AND($D71="Casa Nicola",$G71<>""),ROW(),"") | AD71: =IF(AND($D71="White Cottage",$G71<>""),ROW(),"") | AE71: =IF(AND($D71="Villa Nella",$G71<>""),ROW(),"") | AF71: =IF(AND($D71="Villa Elena",$G71<>""),ROW(),"") | AG71: =IF(AND($D71="Sotto la Quercia",$G71=""),ROW(),"") | AH71: =IF(AND($D71="Villa Elena",$G71=""),ROW(),"") | AI71: =IF(AND($D71="Casa Letizia",$G71=""),ROW(),"") | AJ71: =IF(AND($D71="Casa nel Borgo",$G71=""),ROW(),"") | AK71: =IF(AND($D71="Via San Rocco",$G71=""),ROW(),"") | AL71: =IF(AND($D71="Via Cavour",$G71=""),ROW(),"") | AM71: =IF(AND($D71="Miramare",$G71=""),ROW(),"") | AN71: =IF(AND($D71="Agantonio",$G71=""),ROW(),"") | AO71: =IF(AND($D71="Casa Bella Gialla",$G71=""),ROW(),"") | AP71: =IF(AND($D71="Casa Verde Oliva",$G71=""),ROW(),"") | AQ71: =IF(AND($D71="Casa Nicola",$G71=""),ROW(),"") | AR71: =IF(AND($D71="White Cottage",$G71=""),ROW(),"") | AS71: =IF(AND($D71="Villa Nella",$G71=""),ROW(),"") | AT71: =IF(AND($D71="Nel Cuore di Lanciano",$G71<>""),ROW(),"") | AU71: =IF(AND($D71="Nel Cuore di Lanciano",$G71=""),ROW(),"")
A72: 46241 | B72: 46251 | C72: =IF(A72<>"",B72-A72,"") -> 10 | D72: Sotto la Quercia | E72: Anna Pandolfi | F72: 2 ad | G72: booking.com | H72: 1694.07 | I72: =IF(AND(H72<>"",C72<>"",C72<>0),H72/C72,"") -> 169.407 | J72: =IF(AND(ISNUMBER(SEARCH("booking",G72)),OR(D72="Via San Rocco",D72="Via Cavour")),H72*0.165,IF(ISNUMBER(SEARCH("airbnb",G72)),H72*0.155,IF(ISNUMBER(SEARCH("booking",G72)),H72*0.15,""))) -> 254.1105 | K72: contanti | L72: 4 | M72: =IF(H72<>"",H72*0.25,"") -> 423.5175 | N72: 40 | O72: MARILENA | S72: =IF(AND($D72="Sotto la Quercia",$G72<>""),ROW(),"") -> 72 | T72: =IF($D72="Villa Elena",COUNTIF($D$3:$D72,"Villa Elena"),"") | U72: =IF(AND($D72="Casa Letizia",$G72<>""),ROW(),"") | V72: =IF(AND($D72="Casa nel Borgo",$G72<>""),ROW(),"") | W72: =IF(AND($D72="Via San Rocco",$G72<>""),ROW(),"") | X72: =IF(AND($D72="Via Cavour",$G72<>""),ROW(),"") | Y72: =IF(AND($D72="Miramare",$G72<>""),ROW(),"") | Z72: =IF(AND($D72="Agantonio",$G72<>""),ROW(),"") | AA72: =IF(AND($D72="Casa Bella Gialla",$G72<>""),ROW(),"") | AB72: =IF(AND($D72="Casa Verde Oliva",$G72<>""),ROW(),"") | AC72: =IF(AND($D72="Casa Nicola",$G72<>""),ROW(),"") | AD72: =IF(AND($D72="White Cottage",$G72<>""),ROW(),"") | AE72: =IF(AND($D72="Villa Nella",$G72<>""),ROW(),"") | AF72: =IF(AND($D72="Villa Elena",$G72<>""),ROW(),"") | AG72: =IF(AND($D72="Sotto la Quercia",$G72=""),ROW(),"") | AH72: =IF(AND($D72="Villa Elena",$G72=""),ROW(),"") | AI72: =IF(AND($D72="Casa Letizia",$G72=""),ROW(),"") | AJ72: =IF(AND($D72="Casa nel Borgo",$G72=""),ROW(),"") | AK72: =IF(AND($D72="Via San Rocco",$G72=""),ROW(),"") | AL72: =IF(AND($D72="Via Cavour",$G72=""),ROW(),"") | AM72: =IF(AND($D72="Miramare",$G72=""),ROW(),"") | AN72: =IF(AND($D72="Agantonio",$G72=""),ROW(),"") | AO72: =IF(AND($D72="Casa Bella Gialla",$G72=""),ROW(),"") | AP72: =IF(AND($D72="Casa Verde Oliva",$G72=""),ROW(),"") | AQ72: =IF(AND($D72="Casa Nicola",$G72=""),ROW(),"") | AR72: =IF(AND($D72="White Cottage",$G72=""),ROW(),"") | AS72: =IF(AND($D72="Villa Nella",$G72=""),ROW(),"") | AT72: =IF(AND($D72="Nel Cuore di Lanciano",$G72<>""),ROW(),"") | AU72: =IF(AND($D72="Nel Cuore di Lanciano",$G72=""),ROW(),"")
A73: 46242 | B73: 46252 | C73: =IF(A73<>"",B73-A73,"") -> 10 | D73: Miramare | E73: Andrea Tarozzi | F73: 2 ad | G73: diretta | H73: 1000 | I73: =IF(AND(H73<>"",C73<>"",C73<>0),H73/C73,"") -> 100 | J73: 0 | K73: contanti | L73: 20 | M73: =IF(H73<>"",H73*0.25,"") -> 250 | N73: 20 | O73: MARILENA | S73: =IF(AND($D73="Sotto la Quercia",$G73<>""),ROW(),"") | T73: =IF($D73="Villa Elena",COUNTIF($D$3:$D73,"Villa Elena"),"") | U73: =IF(AND($D73="Casa Letizia",$G73<>""),ROW(),"") | V73: =IF(AND($D73="Casa nel Borgo",$G73<>""),ROW(),"") | W73: =IF(AND($D73="Via San Rocco",$G73<>""),ROW(),"") | X73: =IF(AND($D73="Via Cavour",$G73<>""),ROW(),"") | Y73: =IF(AND($D73="Miramare",$G73<>""),ROW(),"") -> 73 | Z73: =IF(AND($D73="Agantonio",$G73<>""),ROW(),"") | AA73: =IF(AND($D73="Casa Bella Gialla",$G73<>""),ROW(),"") | AB73: =IF(AND($D73="Casa Verde Oliva",$G73<>""),ROW(),"") | AC73: =IF(AND($D73="Casa Nicola",$G73<>""),ROW(),"") | AD73: =IF(AND($D73="White Cottage",$G73<>""),ROW(),"") | AE73: =IF(AND($D73="Villa Nella",$G73<>""),ROW(),"") | AF73: =IF(AND($D73="Villa Elena",$G73<>""),ROW(),"") | AG73: =IF(AND($D73="Sotto la Quercia",$G73=""),ROW(),"") | AH73: =IF(AND($D73="Villa Elena",$G73=""),ROW(),"") | AI73: =IF(AND($D73="Casa Letizia",$G73=""),ROW(),"") | AJ73: =IF(AND($D73="Casa nel Borgo",$G73=""),ROW(),"") | AK73: =IF(AND($D73="Via San Rocco",$G73=""),ROW(),"") | AL73: =IF(AND($D73="Via Cavour",$G73=""),ROW(),"") | AM73: =IF(AND($D73="Miramare",$G73=""),ROW(),"") | AN73: =IF(AND($D73="Agantonio",$G73=""),ROW(),"") | AO73: =IF(AND($D73="Casa Bella Gialla",$G73=""),ROW(),"") | AP73: =IF(AND($D73="Casa Verde Oliva",$G73=""),ROW(),"") | AQ73: =IF(AND($D73="Casa Nicola",$G73=""),ROW(),"") | AR73: =IF(AND($D73="White Cottage",$G73=""),ROW(),"") | AS73: =IF(AND($D73="Villa Nella",$G73=""),ROW(),"") | AT73: =IF(AND($D73="Nel Cuore di Lanciano",$G73<>""),ROW(),"") | AU73: =IF(AND($D73="Nel Cuore di Lanciano",$G73=""),ROW(),"")
A74: 46242 | B74: 46250 | C74: =IF(A74<>"",B74-A74,"") -> 8 | D74: Casa nel Borgo | E74: Pascal Nucara | F74: 2 ad 1 b | G74: booking.com | H74: 1029.02 | I74: =IF(AND(H74<>"",C74<>"",C74<>0),H74/C74,"") -> 128.6275 | J74: =IF(AND(ISNUMBER(SEARCH("booking",G74)),OR(D74="Via San Rocco",D74="Via Cavour")),H74*0.165,IF(ISNUMBER(SEARCH("airbnb",G74)),H74*0.155,IF(ISNUMBER(SEARCH("booking",G74)),H74*0.15,""))) -> 154.353 | K74: contanti e master | L74: 6 | M74: =IF(H74<>"",H74*0.25,"") -> 257.255 | N74: 20 | O74: MARILENA | S74: =IF(AND($D74="Sotto la Quercia",$G74<>""),ROW(),"") | T74: =IF($D74="Villa Elena",COUNTIF($D$3:$D74,"Villa Elena"),"") | U74: =IF(AND($D74="Casa Letizia",$G74<>""),ROW(),"") | V74: =IF(AND($D74="Casa nel Borgo",$G74<>""),ROW(),"") -> 74 | W74: =IF(AND($D74="Via San Rocco",$G74<>""),ROW(),"") | X74: =IF(AND($D74="Via Cavour",$G74<>""),ROW(),"") | Y74: =IF(AND($D74="Miramare",$G74<>""),ROW(),"") | Z74: =IF(AND($D74="Agantonio",$G74<>""),ROW(),"") | AA74: =IF(AND($D74="Casa Bella Gialla",$G74<>""),ROW(),"") | AB74: =IF(AND($D74="Casa Verde Oliva",$G74<>""),ROW(),"") | AC74: =IF(AND($D74="Casa Nicola",$G74<>""),ROW(),"") | AD74: =IF(AND($D74="White Cottage",$G74<>""),ROW(),"") | AE74: =IF(AND($D74="Villa Nella",$G74<>""),ROW(),"") | AF74: =IF(AND($D74="Villa Elena",$G74<>""),ROW(),"") | AG74: =IF(AND($D74="Sotto la Quercia",$G74=""),ROW(),"") | AH74: =IF(AND($D74="Villa Elena",$G74=""),ROW(),"") | AI74: =IF(AND($D74="Casa Letizia",$G74=""),ROW(),"") | AJ74: =IF(AND($D74="Casa nel Borgo",$G74=""),ROW(),"") | AK74: =IF(AND($D74="Via San Rocco",$G74=""),ROW(),"") | AL74: =IF(AND($D74="Via Cavour",$G74=""),ROW(),"") | AM74: =IF(AND($D74="Miramare",$G74=""),ROW(),"") | AN74: =IF(AND($D74="Agantonio",$G74=""),ROW(),"") | AO74: =IF(AND($D74="Casa Bella Gialla",$G74=""),ROW(),"") | AP74: =IF(AND($D74="Casa Verde Oliva",$G74=""),ROW(),"") | AQ74: =IF(AND($D74="Casa Nicola",$G74=""),ROW(),"") | AR74: =IF(AND($D74="White Cottage",$G74=""),ROW(),"") | AS74: =IF(AND($D74="Villa Nella",$G74=""),ROW(),"") | AT74: =IF(AND($D74="Nel Cuore di Lanciano",$G74<>""),ROW(),"") | AU74: =IF(AND($D74="Nel Cuore di Lanciano",$G74=""),ROW(),"")
A75: 46243 | B75: 46250 | C75: =IF(A75<>"",B75-A75,"") -> 7 | D75: Via San Rocco | E75: Loredana Benassi | F75: 2 ad | G75: diretta | H75: 700 | I75: =IF(AND(H75<>"",C75<>"",C75<>0),H75/C75,"") -> 100 | J75: 0 | M75: =IF(H75<>"",H75*0.1,"") -> 70 | S75: =IF(AND($D75="Sotto la Quercia",$G75<>""),ROW(),"") | T75: =IF($D75="Villa Elena",COUNTIF($D$3:$D75,"Villa Elena"),"") | U75: =IF(AND($D75="Casa Letizia",$G75<>""),ROW(),"") | V75: =IF(AND($D75="Casa nel Borgo",$G75<>""),ROW(),"") | W75: =IF(AND($D75="Via San Rocco",$G75<>""),ROW(),"") -> 75 | X75: =IF(AND($D75="Via Cavour",$G75<>""),ROW(),"") | Y75: =IF(AND($D75="Miramare",$G75<>""),ROW(),"") | Z75: =IF(AND($D75="Agantonio",$G75<>""),ROW(),"") | AA75: =IF(AND($D75="Casa Bella Gialla",$G75<>""),ROW(),"") | AB75: =IF(AND($D75="Casa Verde Oliva",$G75<>""),ROW(),"") | AC75: =IF(AND($D75="Casa Nicola",$G75<>""),ROW(),"") | AD75: =IF(AND($D75="White Cottage",$G75<>""),ROW(),"") | AE75: =IF(AND($D75="Villa Nella",$G75<>""),ROW(),"") | AF75: =IF(AND($D75="Villa Elena",$G75<>""),ROW(),"") | AG75: =IF(AND($D75="Sotto la Quercia",$G75=""),ROW(),"") | AH75: =IF(AND($D75="Villa Elena",$G75=""),ROW(),"") | AI75: =IF(AND($D75="Casa Letizia",$G75=""),ROW(),"") | AJ75: =IF(AND($D75="Casa nel Borgo",$G75=""),ROW(),"") | AK75: =IF(AND($D75="Via San Rocco",$G75=""),ROW(),"") | AL75: =IF(AND($D75="Via Cavour",$G75=""),ROW(),"") | AM75: =IF(AND($D75="Miramare",$G75=""),ROW(),"") | AN75: =IF(AND($D75="Agantonio",$G75=""),ROW(),"") | AO75: =IF(AND($D75="Casa Bella Gialla",$G75=""),ROW(),"") | AP75: =IF(AND($D75="Casa Verde Oliva",$G75=""),ROW(),"") | AQ75: =IF(AND($D75="Casa Nicola",$G75=""),ROW(),"") | AR75: =IF(AND($D75="White Cottage",$G75=""),ROW(),"") | AS75: =IF(AND($D75="Villa Nella",$G75=""),ROW(),"") | AT75: =IF(AND($D75="Nel Cuore di Lanciano",$G75<>""),ROW(),"") | AU75: =IF(AND($D75="Nel Cuore di Lanciano",$G75=""),ROW(),"")
A76: 46243 | B76: 46253 | C76: =IF(A76<>"",B76-A76,"") -> 10 | D76: Agantonio | E76: Martelli Sara | F76: 2 ad | G76: booking.com | H76: 1285.92 | I76: =IF(AND(H76<>"",C76<>"",C76<>0),H76/C76,"") -> 128.592 | J76: =IF(AND(ISNUMBER(SEARCH("booking",G76)),OR(D76="Via San Rocco",D76="Via Cavour")),H76*0.165,IF(ISNUMBER(SEARCH("airbnb",G76)),H76*0.155,IF(ISNUMBER(SEARCH("booking",G76)),H76*0.15,""))) -> 192.888 | L76: 10 | M76: =IF(H76<>"",H76*0.25,"") -> 321.48 | N76: 20 | O76: MARILENA | R76: CANE | S76: =IF(AND($D76="Sotto la Quercia",$G76<>""),ROW(),"") | T76: =IF($D76="Villa Elena",COUNTIF($D$3:$D76,"Villa Elena"),"") | U76: =IF(AND($D76="Casa Letizia",$G76<>""),ROW(),"") | V76: =IF(AND($D76="Casa nel Borgo",$G76<>""),ROW(),"") | W76: =IF(AND($D76="Via San Rocco",$G76<>""),ROW(),"") | X76: =IF(AND($D76="Via Cavour",$G76<>""),ROW(),"") | Y76: =IF(AND($D76="Miramare",$G76<>""),ROW(),"") | Z76: =IF(AND($D76="Agantonio",$G76<>""),ROW(),"") -> 76 | AA76: =IF(AND($D76="Casa Bella Gialla",$G76<>""),ROW(),"") | AB76: =IF(AND($D76="Casa Verde Oliva",$G76<>""),ROW(),"") | AC76: =IF(AND($D76="Casa Nicola",$G76<>""),ROW(),"") | AD76: =IF(AND($D76="White Cottage",$G76<>""),ROW(),"") | AE76: =IF(AND($D76="Villa Nella",$G76<>""),ROW(),"") | AF76: =IF(AND($D76="Villa Elena",$G76<>""),ROW(),"") | AG76: =IF(AND($D76="Sotto la Quercia",$G76=""),ROW(),"") | AH76: =IF(AND($D76="Villa Elena",$G76=""),ROW(),"") | AI76: =IF(AND($D76="Casa Letizia",$G76=""),ROW(),"") | AJ76: =IF(AND($D76="Casa nel Borgo",$G76=""),ROW(),"") | AK76: =IF(AND($D76="Via San Rocco",$G76=""),ROW(),"") | AL76: =IF(AND($D76="Via Cavour",$G76=""),ROW(),"") | AM76: =IF(AND($D76="Miramare",$G76=""),ROW(),"") | AN76: =IF(AND($D76="Agantonio",$G76=""),ROW(),"") | AO76: =IF(AND($D76="Casa Bella Gialla",$G76=""),ROW(),"") | AP76: =IF(AND($D76="Casa Verde Oliva",$G76=""),ROW(),"") | AQ76: =IF(AND($D76="Casa Nicola",$G76=""),ROW(),"") | AR76: =IF(AND($D76="White Cottage",$G76=""),ROW(),"") | AS76: =IF(AND($D76="Villa Nella",$G76=""),ROW(),"") | AT76: =IF(AND($D76="Nel Cuore di Lanciano",$G76<>""),ROW(),"") | AU76: =IF(AND($D76="Nel Cuore di Lanciano",$G76=""),ROW(),"")
A77: 46243 | B77: 46256 | C77: =IF(A77<>"",B77-A77,"") -> 13 | D77: Casa Bella Gialla | E77: Giovanna Di Matteo | F77: 2 ad 1 b | G77: diretta | H77: 1365 | I77: =IF(AND(H77<>"",C77<>"",C77<>0),H77/C77,"") -> 105 | J77: 0 | K77: contanti | L77: 4 | M77: =IF(H77<>"",H77*0.25,"") -> 341.25 | N77: 60 | O77: MARILENA | R77: per conto di amici | S77: =IF(AND($D77="Sotto la Quercia",$G77<>""),ROW(),"") | T77: =IF($D77="Villa Elena",COUNTIF($D$3:$D77,"Villa Elena"),"") | U77: =IF(AND($D77="Casa Letizia",$G77<>""),ROW(),"") | V77: =IF(AND($D77="Casa nel Borgo",$G77<>""),ROW(),"") | W77: =IF(AND($D77="Via San Rocco",$G77<>""),ROW(),"") | X77: =IF(AND($D77="Via Cavour",$G77<>""),ROW(),"") | Y77: =IF(AND($D77="Miramare",$G77<>""),ROW(),"") | Z77: =IF(AND($D77="Agantonio",$G77<>""),ROW(),"") | AA77: =IF(AND($D77="Casa Bella Gialla",$G77<>""),ROW(),"") -> 77 | AB77: =IF(AND($D77="Casa Verde Oliva",$G77<>""),ROW(),"") | AC77: =IF(AND($D77="Casa Nicola",$G77<>""),ROW(),"") | AD77: =IF(AND($D77="White Cottage",$G77<>""),ROW(),"") | AE77: =IF(AND($D77="Villa Nella",$G77<>""),ROW(),"") | AF77: =IF(AND($D77="Villa Elena",$G77<>""),ROW(),"") | AG77: =IF(AND($D77="Sotto la Quercia",$G77=""),ROW(),"") | AH77: =IF(AND($D77="Villa Elena",$G77=""),ROW(),"") | AI77: =IF(AND($D77="Casa Letizia",$G77=""),ROW(),"") | AJ77: =IF(AND($D77="Casa nel Borgo",$G77=""),ROW(),"") | AK77: =IF(AND($D77="Via San Rocco",$G77=""),ROW(),"") | AL77: =IF(AND($D77="Via Cavour",$G77=""),ROW(),"") | AM77: =IF(AND($D77="Miramare",$G77=""),ROW(),"") | AN77: =IF(AND($D77="Agantonio",$G77=""),ROW(),"") | AO77: =IF(AND($D77="Casa Bella Gialla",$G77=""),ROW(),"") | AP77: =IF(AND($D77="Casa Verde Oliva",$G77=""),ROW(),"") | AQ77: =IF(AND($D77="Casa Nicola",$G77=""),ROW(),"") | AR77: =IF(AND($D77="White Cottage",$G77=""),ROW(),"") | AS77: =IF(AND($D77="Villa Nella",$G77=""),ROW(),"") | AT77: =IF(AND($D77="Nel Cuore di Lanciano",$G77<>""),ROW(),"") | AU77: =IF(AND($D77="Nel Cuore di Lanciano",$G77=""),ROW(),"")
A78: 46243 | B78: 46250 | C78: =IF(A78<>"",B78-A78,"") -> 7 | D78: Via Cavour | E78: David Mesa | F78: 1 ad 1 b | G78: booking.com | H78: 1004.85 | I78: =IF(AND(H78<>"",C78<>"",C78<>0),H78/C78,"") -> 143.55 | J78: =IF(AND(ISNUMBER(SEARCH("booking",G78)),OR(D78="Via San Rocco",D78="Via Cavour")),H78*0.165,IF(ISNUMBER(SEARCH("airbnb",G78)),H78*0.155,IF(ISNUMBER(SEARCH("booking",G78)),H78*0.15,""))) -> 165.80025 | M78: =IF(H78<>"",H78*0.1,"") -> 100.485 | S78: =IF(AND($D78="Sotto la Quercia",$G78<>""),ROW(),"") | T78: =IF($D78="Villa Elena",COUNTIF($D$3:$D78,"Villa Elena"),"") | U78: =IF(AND($D78="Casa Letizia",$G78<>""),ROW(),"") | V78: =IF(AND($D78="Casa nel Borgo",$G78<>""),ROW(),"") | W78: =IF(AND($D78="Via San Rocco",$G78<>""),ROW(),"") | X78: =IF(AND($D78="Via Cavour",$G78<>""),ROW(),"") -> 78 | Y78: =IF(AND($D78="Miramare",$G78<>""),ROW(),"") | Z78: =IF(AND($D78="Agantonio",$G78<>""),ROW(),"") | AA78: =IF(AND($D78="Casa Bella Gialla",$G78<>""),ROW(),"") | AB78: =IF(AND($D78="Casa Verde Oliva",$G78<>""),ROW(),"") | AC78: =IF(AND($D78="Casa Nicola",$G78<>""),ROW(),"") | AD78: =IF(AND($D78="White Cottage",$G78<>""),ROW(),"") | AE78: =IF(AND($D78="Villa Nella",$G78<>""),ROW(),"") | AF78: =IF(AND($D78="Villa Elena",$G78<>""),ROW(),"") | AG78: =IF(AND($D78="Sotto la Quercia",$G78=""),ROW(),"") | AH78: =IF(AND($D78="Villa Elena",$G78=""),ROW(),"") | AI78: =IF(AND($D78="Casa Letizia",$G78=""),ROW(),"") | AJ78: =IF(AND($D78="Casa nel Borgo",$G78=""),ROW(),"") | AK78: =IF(AND($D78="Via San Rocco",$G78=""),ROW(),"") | AL78: =IF(AND($D78="Via Cavour",$G78=""),ROW(),"") | AM78: =IF(AND($D78="Miramare",$G78=""),ROW(),"") | AN78: =IF(AND($D78="Agantonio",$G78=""),ROW(),"") | AO78: =IF(AND($D78="Casa Bella Gialla",$G78=""),ROW(),"") | AP78: =IF(AND($D78="Casa Verde Oliva",$G78=""),ROW(),"") | AQ78: =IF(AND($D78="Casa Nicola",$G78=""),ROW(),"") | AR78: =IF(AND($D78="White Cottage",$G78=""),ROW(),"") | AS78: =IF(AND($D78="Villa Nella",$G78=""),ROW(),"") | AT78: =IF(AND($D78="Nel Cuore di Lanciano",$G78<>""),ROW(),"") | AU78: =IF(AND($D78="Nel Cuore di Lanciano",$G78=""),ROW(),"")
A79: 46244 | B79: 46255 | C79: =IF(A79<>"",B79-A79,"") -> 11 | D79: casa nicola | E79: Michele Deponti | F79: 2 ad | G79: booking.com | H79: 1222.2 | I79: =IF(AND(H79<>"",C79<>"",C79<>0),H79/C79,"") -> 111.10909 | J79: =IF(AND(ISNUMBER(SEARCH("booking",G79)),OR(D79="Via San Rocco",D79="Via Cavour")),H79*0.165,IF(ISNUMBER(SEARCH("airbnb",G79)),H79*0.155,IF(ISNUMBER(SEARCH("booking",G79)),H79*0.15,""))) -> 183.33 | M79: =IF(H79<>"",H79*0.25,"") -> 305.55 | S79: =IF(AND($D79="Sotto la Quercia",$G79<>""),ROW(),"") | T79: =IF($D79="Villa Elena",COUNTIF($D$3:$D79,"Villa Elena"),"") | U79: =IF(AND($D79="Casa Letizia",$G79<>""),ROW(),"") | V79: =IF(AND($D79="Casa nel Borgo",$G79<>""),ROW(),"") | W79: =IF(AND($D79="Via San Rocco",$G79<>""),ROW(),"") | X79: =IF(AND($D79="Via Cavour",$G79<>""),ROW(),"") | Y79: =IF(AND($D79="Miramare",$G79<>""),ROW(),"") | Z79: =IF(AND($D79="Agantonio",$G79<>""),ROW(),"") | AA79: =IF(AND($D79="Casa Bella Gialla",$G79<>""),ROW(),"") | AB79: =IF(AND($D79="Casa Verde Oliva",$G79<>""),ROW(),"") | AC79: =IF(AND($D79="Casa Nicola",$G79<>""),ROW(),"") -> 79 | AD79: =IF(AND($D79="White Cottage",$G79<>""),ROW(),"") | AE79: =IF(AND($D79="Villa Nella",$G79<>""),ROW(),"") | AF79: =IF(AND($D79="Villa Elena",$G79<>""),ROW(),"") | AG79: =IF(AND($D79="Sotto la Quercia",$G79=""),ROW(),"") | AH79: =IF(AND($D79="Villa Elena",$G79=""),ROW(),"") | AI79: =IF(AND($D79="Casa Letizia",$G79=""),ROW(),"") | AJ79: =IF(AND($D79="Casa nel Borgo",$G79=""),ROW(),"") | AK79: =IF(AND($D79="Via San Rocco",$G79=""),ROW(),"") | AL79: =IF(AND($D79="Via Cavour",$G79=""),ROW(),"") | AM79: =IF(AND($D79="Miramare",$G79=""),ROW(),"") | AN79: =IF(AND($D79="Agantonio",$G79=""),ROW(),"") | AO79: =IF(AND($D79="Casa Bella Gialla",$G79=""),ROW(),"") | AP79: =IF(AND($D79="Casa Verde Oliva",$G79=""),ROW(),"") | AQ79: =IF(AND($D79="Casa Nicola",$G79=""),ROW(),"") | AR79: =IF(AND($D79="White Cottage",$G79=""),ROW(),"") | AS79: =IF(AND($D79="Villa Nella",$G79=""),ROW(),"") | AT79: =IF(AND($D79="Nel Cuore di Lanciano",$G79<>""),ROW(),"") | AU79: =IF(AND($D79="Nel Cuore di Lanciano",$G79=""),ROW(),"")
A80: 46244 | B80: 46256 | C80: =IF(A80<>"",B80-A80,"") -> 12 | D80: Casa Letizia | E80: Eugenio Romor | F80: 2 ad 1 b | G80: booking.com | H80: 1814.69 | I80: =IF(AND(H80<>"",C80<>"",C80<>0),H80/C80,"") -> 151.22417 | J80: =IF(AND(ISNUMBER(SEARCH("booking",G80)),OR(D80="Via San Rocco",D80="Via Cavour")),H80*0.165,IF(ISNUMBER(SEARCH("airbnb",G80)),H80*0.155,IF(ISNUMBER(SEARCH("booking",G80)),H80*0.15,""))) -> 272.2035 | M80: =IF(H80<>"",H80*0.25,"") -> 453.6725 | S80: =IF(AND($D80="Sotto la Quercia",$G80<>""),ROW(),"") | T80: =IF($D80="Villa Elena",COUNTIF($D$3:$D80,"Villa Elena"),"") | U80: =IF(AND($D80="Casa Letizia",$G80<>""),ROW(),"") -> 80 | V80: =IF(AND($D80="Casa nel Borgo",$G80<>""),ROW(),"") | W80: =IF(AND($D80="Via San Rocco",$G80<>""),ROW(),"") | X80: =IF(AND($D80="Via Cavour",$G80<>""),ROW(),"") | Y80: =IF(AND($D80="Miramare",$G80<>""),ROW(),"") | Z80: =IF(AND($D80="Agantonio",$G80<>""),ROW(),"") | AA80: =IF(AND($D80="Casa Bella Gialla",$G80<>""),ROW(),"") | AB80: =IF(AND($D80="Casa Verde Oliva",$G80<>""),ROW(),"") | AC80: =IF(AND($D80="Casa Nicola",$G80<>""),ROW(),"") | AD80: =IF(AND($D80="White Cottage",$G80<>""),ROW(),"") | AE80: =IF(AND($D80="Villa Nella",$G80<>""),ROW(),"") | AF80: =IF(AND($D80="Villa Elena",$G80<>""),ROW(),"") | AG80: =IF(AND($D80="Sotto la Quercia",$G80=""),ROW(),"") | AH80: =IF(AND($D80="Villa Elena",$G80=""),ROW(),"") | AI80: =IF(AND($D80="Casa Letizia",$G80=""),ROW(),"") | AJ80: =IF(AND($D80="Casa nel Borgo",$G80=""),ROW(),"") | AK80: =IF(AND($D80="Via San Rocco",$G80=""),ROW(),"") | AL80: =IF(AND($D80="Via Cavour",$G80=""),ROW(),"") | AM80: =IF(AND($D80="Miramare",$G80=""),ROW(),"") | AN80: =IF(AND($D80="Agantonio",$G80=""),ROW(),"") | AO80: =IF(AND($D80="Casa Bella Gialla",$G80=""),ROW(),"") | AP80: =IF(AND($D80="Casa Verde Oliva",$G80=""),ROW(),"") | AQ80: =IF(AND($D80="Casa Nicola",$G80=""),ROW(),"") | AR80: =IF(AND($D80="White Cottage",$G80=""),ROW(),"") | AS80: =IF(AND($D80="Villa Nella",$G80=""),ROW(),"") | AT80: =IF(AND($D80="Nel Cuore di Lanciano",$G80<>""),ROW(),"") | AU80: =IF(AND($D80="Nel Cuore di Lanciano",$G80=""),ROW(),"")
A81: 46244 | B81: 46251 | C81: =IF(A81<>"",B81-A81,"") -> 7 | D81: Villa Elena | E81: Paola Roana | F81: 2 ad | G81: booking.com | H81: 853.94 | I81: =IF(AND(H81<>"",C81<>"",C81<>0),H81/C81,"") -> 121.99143 | J81: =IF(AND(ISNUMBER(SEARCH("booking",G81)),OR(D81="Via San Rocco",D81="Via Cavour")),H81*0.165,IF(ISNUMBER(SEARCH("airbnb",G81)),H81*0.155,IF(ISNUMBER(SEARCH("booking",G81)),H81*0.15,""))) -> 128.091 | M81: =IF(H81<>"",H81*0.25,"") -> 213.485 | S81: =IF(AND($D81="Sotto la Quercia",$G81<>""),ROW(),"") | T81: =IF($D81="Villa Elena",COUNTIF($D$3:$D81,"Villa Elena"),"") -> 7 | U81: =IF(AND($D81="Casa Letizia",$G81<>""),ROW(),"") | V81: =IF(AND($D81="Casa nel Borgo",$G81<>""),ROW(),"") | W81: =IF(AND($D81="Via San Rocco",$G81<>""),ROW(),"") | X81: =IF(AND($D81="Via Cavour",$G81<>""),ROW(),"") | Y81: =IF(AND($D81="Miramare",$G81<>""),ROW(),"") | Z81: =IF(AND($D81="Agantonio",$G81<>""),ROW(),"") | AA81: =IF(AND($D81="Casa Bella Gialla",$G81<>""),ROW(),"") | AB81: =IF(AND($D81="Casa Verde Oliva",$G81<>""),ROW(),"") | AC81: =IF(AND($D81="Casa Nicola",$G81<>""),ROW(),"") | AD81: =IF(AND($D81="White Cottage",$G81<>""),ROW(),"") | AE81: =IF(AND($D81="Villa Nella",$G81<>""),ROW(),"") | AF81: =IF(AND($D81="Villa Elena",$G81<>""),ROW(),"") -> 81 | AG81: =IF(AND($D81="Sotto la Quercia",$G81=""),ROW(),"") | AH81: =IF(AND($D81="Villa Elena",$G81=""),ROW(),"") | AI81: =IF(AND($D81="Casa Letizia",$G81=""),ROW(),"") | AJ81: =IF(AND($D81="Casa nel Borgo",$G81=""),ROW(),"") | AK81: =IF(AND($D81="Via San Rocco",$G81=""),ROW(),"") | AL81: =IF(AND($D81="Via Cavour",$G81=""),ROW(),"") | AM81: =IF(AND($D81="Miramare",$G81=""),ROW(),"") | AN81: =IF(AND($D81="Agantonio",$G81=""),ROW(),"") | AO81: =IF(AND($D81="Casa Bella Gialla",$G81=""),ROW(),"") | AP81: =IF(AND($D81="Casa Verde Oliva",$G81=""),ROW(),"") | AQ81: =IF(AND($D81="Casa Nicola",$G81=""),ROW(),"") | AR81: =IF(AND($D81="White Cottage",$G81=""),ROW(),"") | AS81: =IF(AND($D81="Villa Nella",$G81=""),ROW(),"") | AT81: =IF(AND($D81="Nel Cuore di Lanciano",$G81<>""),ROW(),"") | AU81: =IF(AND($D81="Nel Cuore di Lanciano",$G81=""),ROW(),"")
A82: 46245 | B82: 46251 | C82: =IF(A82<>"",B82-A82,"") -> 6 | D82: Nel Cuore di Lanciano | E82: Juanna Rosa | F82: 2 ad 1 b | G82: booking.com | H82: 675 | I82: =IF(AND(H82<>"",C82<>"",C82<>0),H82/C82,"") -> 112.5 | J82: =IF(AND(ISNUMBER(SEARCH("booking",G82)),OR(D82="Via San Rocco",D82="Via Cavour")),H82*0.165,IF(ISNUMBER(SEARCH("airbnb",G82)),H82*0.155,IF(ISNUMBER(SEARCH("booking",G82)),H82*0.15,""))) -> 101.25 | K82: contanti | M82: =IF(H82<>"",H82*0.25,"") -> 168.75 | S82: =IF(AND($D82="Sotto la Quercia",$G82<>""),ROW(),"") | T82: =IF($D82="Villa Elena",COUNTIF($D$3:$D82,"Villa Elena"),"") | U82: =IF(AND($D82="Casa Letizia",$G82<>""),ROW(),"") | V82: =IF(AND($D82="Casa nel Borgo",$G82<>""),ROW(),"") | W82: =IF(AND($D82="Via San Rocco",$G82<>""),ROW(),"") | X82: =IF(AND($D82="Via Cavour",$G82<>""),ROW(),"") | Y82: =IF(AND($D82="Miramare",$G82<>""),ROW(),"") | Z82: =IF(AND($D82="Agantonio",$G82<>""),ROW(),"") | AA82: =IF(AND($D82="Casa Bella Gialla",$G82<>""),ROW(),"") | AB82: =IF(AND($D82="Casa Verde Oliva",$G82<>""),ROW(),"") | AC82: =IF(AND($D82="Casa Nicola",$G82<>""),ROW(),"") | AD82: =IF(AND($D82="White Cottage",$G82<>""),ROW(),"") | AE82: =IF(AND($D82="Villa Nella",$G82<>""),ROW(),"") | AF82: =IF(AND($D82="Villa Elena",$G82<>""),ROW(),"") | AG82: =IF(AND($D82="Sotto la Quercia",$G82=""),ROW(),"") | AH82: =IF(AND($D82="Villa Elena",$G82=""),ROW(),"") | AI82: =IF(AND($D82="Casa Letizia",$G82=""),ROW(),"") | AJ82: =IF(AND($D82="Casa nel Borgo",$G82=""),ROW(),"") | AK82: =IF(AND($D82="Via San Rocco",$G82=""),ROW(),"") | AL82: =IF(AND($D82="Via Cavour",$G82=""),ROW(),"") | AM82: =IF(AND($D82="Miramare",$G82=""),ROW(),"") | AN82: =IF(AND($D82="Agantonio",$G82=""),ROW(),"") | AO82: =IF(AND($D82="Casa Bella Gialla",$G82=""),ROW(),"") | AP82: =IF(AND($D82="Casa Verde Oliva",$G82=""),ROW(),"") | AQ82: =IF(AND($D82="Casa Nicola",$G82=""),ROW(),"") | AR82: =IF(AND($D82="White Cottage",$G82=""),ROW(),"") | AS82: =IF(AND($D82="Villa Nella",$G82=""),ROW(),"") | AT82: =IF(AND($D82="Nel Cuore di Lanciano",$G82<>""),ROW(),"") -> 82 | AU82: =IF(AND($D82="Nel Cuore di Lanciano",$G82=""),ROW(),"")
A83: 46246 | B83: 46251 | C83: =IF(A83<>"",B83-A83,"") -> 5 | D83: Casa Verde Oliva | E83: Luca. Maccarelli | F83: 2 ad | G83: booking.com | H83: 775.02 | I83: =IF(AND(H83<>"",C83<>"",C83<>0),H83/C83,"") -> 155.004 | J83: =IF(AND(ISNUMBER(SEARCH("booking",G83)),OR(D83="Via San Rocco",D83="Via Cavour")),H83*0.165,IF(ISNUMBER(SEARCH("airbnb",G83)),H83*0.155,IF(ISNUMBER(SEARCH("booking",G83)),H83*0.15,""))) -> 116.253 | M83: =IF(H83<>"",H83*0.25,"") -> 193.755 | S83: =IF(AND($D83="Sotto la Quercia",$G83<>""),ROW(),"") | T83: =IF($D83="Villa Elena",COUNTIF($D$3:$D83,"Villa Elena"),"") | U83: =IF(AND($D83="Casa Letizia",$G83<>""),ROW(),"") | V83: =IF(AND($D83="Casa nel Borgo",$G83<>""),ROW(),"") | W83: =IF(AND($D83="Via San Rocco",$G83<>""),ROW(),"") | X83: =IF(AND($D83="Via Cavour",$G83<>""),ROW(),"") | Y83: =IF(AND($D83="Miramare",$G83<>""),ROW(),"") | Z83: =IF(AND($D83="Agantonio",$G83<>""),ROW(),"") | AA83: =IF(AND($D83="Casa Bella Gialla",$G83<>""),ROW(),"") | AB83: =IF(AND($D83="Casa Verde Oliva",$G83<>""),ROW(),"") -> 83 | AC83: =IF(AND($D83="Casa Nicola",$G83<>""),ROW(),"") | AD83: =IF(AND($D83="White Cottage",$G83<>""),ROW(),"") | AE83: =IF(AND($D83="Villa Nella",$G83<>""),ROW(),"") | AF83: =IF(AND($D83="Villa Elena",$G83<>""),ROW(),"") | AG83: =IF(AND($D83="Sotto la Quercia",$G83=""),ROW(),"") | AH83: =IF(AND($D83="Villa Elena",$G83=""),ROW(),"") | AI83: =IF(AND($D83="Casa Letizia",$G83=""),ROW(),"") | AJ83: =IF(AND($D83="Casa nel Borgo",$G83=""),ROW(),"") | AK83: =IF(AND($D83="Via San Rocco",$G83=""),ROW(),"") | AL83: =IF(AND($D83="Via Cavour",$G83=""),ROW(),"") | AM83: =IF(AND($D83="Miramare",$G83=""),ROW(),"") | AN83: =IF(AND($D83="Agantonio",$G83=""),ROW(),"") | AO83: =IF(AND($D83="Casa Bella Gialla",$G83=""),ROW(),"") | AP83: =IF(AND($D83="Casa Verde Oliva",$G83=""),ROW(),"") | AQ83: =IF(AND($D83="Casa Nicola",$G83=""),ROW(),"") | AR83: =IF(AND($D83="White Cottage",$G83=""),ROW(),"") | AS83: =IF(AND($D83="Villa Nella",$G83=""),ROW(),"") | AT83: =IF(AND($D83="Nel Cuore di Lanciano",$G83<>""),ROW(),"") | AU83: =IF(AND($D83="Nel Cuore di Lanciano",$G83=""),ROW(),"")
A84: 46248 | B84: 46255 | C84: =IF(A84<>"",B84-A84,"") -> 7 | D84: Villa Nella | E84: Gianni Barbetta | F84: 5 ad + 1 n | G84: booking.com | H84: 2730.2 | I84: =IF(AND(H84<>"",C84<>"",C84<>0),H84/C84,"") -> 390.02857 | J84: =IF(AND(ISNUMBER(SEARCH("booking",G84)),OR(D84="Via San Rocco",D84="Via Cavour")),H84*0.165,IF(ISNUMBER(SEARCH("airbnb",G84)),H84*0.155,IF(ISNUMBER(SEARCH("booking",G84)),H84*0.15,""))) -> 409.53 | K84: da prendere | M84: =IF(H84<>"",H84*0.25,"") -> 682.55 | R84: NON RIMBORSABILE | S84: =IF(AND($D84="Sotto la Quercia",$G84<>""),ROW(),"") | T84: =IF($D84="Villa Elena",COUNTIF($D$3:$D84,"Villa Elena"),"") | U84: =IF(AND($D84="Casa Letizia",$G84<>""),ROW(),"") | V84: =IF(AND($D84="Casa nel Borgo",$G84<>""),ROW(),"") | W84: =IF(AND($D84="Via San Rocco",$G84<>""),ROW(),"") | X84: =IF(AND($D84="Via Cavour",$G84<>""),ROW(),"") | Y84: =IF(AND($D84="Miramare",$G84<>""),ROW(),"") | Z84: =IF(AND($D84="Agantonio",$G84<>""),ROW(),"") | AA84: =IF(AND($D84="Casa Bella Gialla",$G84<>""),ROW(),"") | AB84: =IF(AND($D84="Casa Verde Oliva",$G84<>""),ROW(),"") | AC84: =IF(AND($D84="Casa Nicola",$G84<>""),ROW(),"") | AD84: =IF(AND($D84="White Cottage",$G84<>""),ROW(),"") | AE84: =IF(AND($D84="Villa Nella",$G84<>""),ROW(),"") -> 84 | AF84: =IF(AND($D84="Villa Elena",$G84<>""),ROW(),"") | AG84: =IF(AND($D84="Sotto la Quercia",$G84=""),ROW(),"") | AH84: =IF(AND($D84="Villa Elena",$G84=""),ROW(),"") | AI84: =IF(AND($D84="Casa Letizia",$G84=""),ROW(),"") | AJ84: =IF(AND($D84="Casa nel Borgo",$G84=""),ROW(),"") | AK84: =IF(AND($D84="Via San Rocco",$G84=""),ROW(),"") | AL84: =IF(AND($D84="Via Cavour",$G84=""),ROW(),"") | AM84: =IF(AND($D84="Miramare",$G84=""),ROW(),"") | AN84: =IF(AND($D84="Agantonio",$G84=""),ROW(),"") | AO84: =IF(AND($D84="Casa Bella Gialla",$G84=""),ROW(),"") | AP84: =IF(AND($D84="Casa Verde Oliva",$G84=""),ROW(),"") | AQ84: =IF(AND($D84="Casa Nicola",$G84=""),ROW(),"") | AR84: =IF(AND($D84="White Cottage",$G84=""),ROW(),"") | AS84: =IF(AND($D84="Villa Nella",$G84=""),ROW(),"") | AT84: =IF(AND($D84="Nel Cuore di Lanciano",$G84<>""),ROW(),"") | AU84: =IF(AND($D84="Nel Cuore di Lanciano",$G84=""),ROW(),"")
A85: 46250 | B85: 46255 | C85: =IF(A85<>"",B85-A85,"") -> 5 | D85: Via Cavour | E85: Vincenzo Patti | F85: 2 ad | G85: diretta | H85: 500 | I85: =IF(AND(H85<>"",C85<>"",C85<>0),H85/C85,"") -> 100 | J85: =IF(AND(ISNUMBER(SEARCH("booking",G85)),OR(D85="Via San Rocco",D85="Via Cavour")),H85*0.165,IF(ISNUMBER(SEARCH("airbnb",G85)),H85*0.155,IF(ISNUMBER(SEARCH("booking",G85)),H85*0.15,""))) | M85: =IF(H85<>"",H85*0.1,"") -> 50 | S85: =IF(AND($D85="Sotto la Quercia",$G85<>""),ROW(),"") | T85: =IF($D85="Villa Elena",COUNTIF($D$3:$D85,"Villa Elena"),"") | U85: =IF(AND($D85="Casa Letizia",$G85<>""),ROW(),"") | V85: =IF(AND($D85="Casa nel Borgo",$G85<>""),ROW(),"") | W85: =IF(AND($D85="Via San Rocco",$G85<>""),ROW(),"") | X85: =IF(AND($D85="Via Cavour",$G85<>""),ROW(),"") -> 85 | Y85: =IF(AND($D85="Miramare",$G85<>""),ROW(),"") | Z85: =IF(AND($D85="Agantonio",$G85<>""),ROW(),"") | AA85: =IF(AND($D85="Casa Bella Gialla",$G85<>""),ROW(),"") | AB85: =IF(AND($D85="Casa Verde Oliva",$G85<>""),ROW(),"") | AC85: =IF(AND($D85="Casa Nicola",$G85<>""),ROW(),"") | AD85: =IF(AND($D85="White Cottage",$G85<>""),ROW(),"") | AE85: =IF(AND($D85="Villa Nella",$G85<>""),ROW(),"") | AF85: =IF(AND($D85="Villa Elena",$G85<>""),ROW(),"") | AG85: =IF(AND($D85="Sotto la Quercia",$G85=""),ROW(),"") | AH85: =IF(AND($D85="Villa Elena",$G85=""),ROW(),"") | AI85: =IF(AND($D85="Casa Letizia",$G85=""),ROW(),"") | AJ85: =IF(AND($D85="Casa nel Borgo",$G85=""),ROW(),"") | AK85: =IF(AND($D85="Via San Rocco",$G85=""),ROW(),"") | AL85: =IF(AND($D85="Via Cavour",$G85=""),ROW(),"") | AM85: =IF(AND($D85="Miramare",$G85=""),ROW(),"") | AN85: =IF(AND($D85="Agantonio",$G85=""),ROW(),"") | AO85: =IF(AND($D85="Casa Bella Gialla",$G85=""),ROW(),"") | AP85: =IF(AND($D85="Casa Verde Oliva",$G85=""),ROW(),"") | AQ85: =IF(AND($D85="Casa Nicola",$G85=""),ROW(),"") | AR85: =IF(AND($D85="White Cottage",$G85=""),ROW(),"") | AS85: =IF(AND($D85="Villa Nella",$G85=""),ROW(),"") | AT85: =IF(AND($D85="Nel Cuore di Lanciano",$G85<>""),ROW(),"") | AU85: =IF(AND($D85="Nel Cuore di Lanciano",$G85=""),ROW(),"")
A86: 46250 | B86: 46253 | C86: =IF(A86<>"",B86-A86,"") -> 3 | D86: Casa nel Borgo | E86: Carolin Prusseit | F86: 2 ad | G86: booking.com | H86: 379.62 | I86: =IF(AND(H86<>"",C86<>"",C86<>0),H86/C86,"") -> 126.54 | J86: =IF(AND(ISNUMBER(SEARCH("booking",G86)),OR(D86="Via San Rocco",D86="Via Cavour")),H86*0.165,IF(ISNUMBER(SEARCH("airbnb",G86)),H86*0.155,IF(ISNUMBER(SEARCH("booking",G86)),H86*0.15,""))) -> 56.943 | M86: =IF(H86<>"",H86*0.25,"") -> 94.905 | S86: =IF(AND($D86="Sotto la Quercia",$G86<>""),ROW(),"") | T86: =IF($D86="Villa Elena",COUNTIF($D$3:$D86,"Villa Elena"),"") | U86: =IF(AND($D86="Casa Letizia",$G86<>""),ROW(),"") | V86: =IF(AND($D86="Casa nel Borgo",$G86<>""),ROW(),"") -> 86 | W86: =IF(AND($D86="Via San Rocco",$G86<>""),ROW(),"") | X86: =IF(AND($D86="Via Cavour",$G86<>""),ROW(),"") | Y86: =IF(AND($D86="Miramare",$G86<>""),ROW(),"") | Z86: =IF(AND($D86="Agantonio",$G86<>""),ROW(),"") | AA86: =IF(AND($D86="Casa Bella Gialla",$G86<>""),ROW(),"") | AB86: =IF(AND($D86="Casa Verde Oliva",$G86<>""),ROW(),"") | AC86: =IF(AND($D86="Casa Nicola",$G86<>""),ROW(),"") | AD86: =IF(AND($D86="White Cottage",$G86<>""),ROW(),"") | AE86: =IF(AND($D86="Villa Nella",$G86<>""),ROW(),"") | AF86: =IF(AND($D86="Villa Elena",$G86<>""),ROW(),"") | AG86: =IF(AND($D86="Sotto la Quercia",$G86=""),ROW(),"") | AH86: =IF(AND($D86="Villa Elena",$G86=""),ROW(),"") | AI86: =IF(AND($D86="Casa Letizia",$G86=""),ROW(),"") | AJ86: =IF(AND($D86="Casa nel Borgo",$G86=""),ROW(),"") | AK86: =IF(AND($D86="Via San Rocco",$G86=""),ROW(),"") | AL86: =IF(AND($D86="Via Cavour",$G86=""),ROW(),"") | AM86: =IF(AND($D86="Miramare",$G86=""),ROW(),"") | AN86: =IF(AND($D86="Agantonio",$G86=""),ROW(),"") | AO86: =IF(AND($D86="Casa Bella Gialla",$G86=""),ROW(),"") | AP86: =IF(AND($D86="Casa Verde Oliva",$G86=""),ROW(),"") | AQ86: =IF(AND($D86="Casa Nicola",$G86=""),ROW(),"") | AR86: =IF(AND($D86="White Cottage",$G86=""),ROW(),"") | AS86: =IF(AND($D86="Villa Nella",$G86=""),ROW(),"") | AT86: =IF(AND($D86="Nel Cuore di Lanciano",$G86<>""),ROW(),"") | AU86: =IF(AND($D86="Nel Cuore di Lanciano",$G86=""),ROW(),"")
A87: 46251 | B87: 46257 | C87: =IF(A87<>"",B87-A87,"") -> 6 | D87: Nel Cuore di Lanciano | E87: Alessandro Brunetti | F87: 2 ad | G87: booking.com | H87: 576 | I87: =IF(AND(H87<>"",C87<>"",C87<>0),H87/C87,"") -> 96 | J87: =IF(AND(ISNUMBER(SEARCH("booking",G87)),OR(D87="Via San Rocco",D87="Via Cavour")),H87*0.165,IF(ISNUMBER(SEARCH("airbnb",G87)),H87*0.155,IF(ISNUMBER(SEARCH("booking",G87)),H87*0.15,""))) -> 86.4 | M87: =IF(H87<>"",H87*0.25,"") -> 144 | S87: =IF(AND($D87="Sotto la Quercia",$G87<>""),ROW(),"") | T87: =IF($D87="Villa Elena",COUNTIF($D$3:$D87,"Villa Elena"),"") | U87: =IF(AND($D87="Casa Letizia",$G87<>""),ROW(),"") | V87: =IF(AND($D87="Casa nel Borgo",$G87<>""),ROW(),"") | W87: =IF(AND($D87="Via San Rocco",$G87<>""),ROW(),"") | X87: =IF(AND($D87="Via Cavour",$G87<>""),ROW(),"") | Y87: =IF(AND($D87="Miramare",$G87<>""),ROW(),"") | Z87: =IF(AND($D87="Agantonio",$G87<>""),ROW(),"") | AA87: =IF(AND($D87="Casa Bella Gialla",$G87<>""),ROW(),"") | AB87: =IF(AND($D87="Casa Verde Oliva",$G87<>""),ROW(),"") | AC87: =IF(AND($D87="Casa Nicola",$G87<>""),ROW(),"") | AD87: =IF(AND($D87="White Cottage",$G87<>""),ROW(),"") | AE87: =IF(AND($D87="Villa Nella",$G87<>""),ROW(),"") | AF87: =IF(AND($D87="Villa Elena",$G87<>""),ROW(),"") | AG87: =IF(AND($D87="Sotto la Quercia",$G87=""),ROW(),"") | AH87: =IF(AND($D87="Villa Elena",$G87=""),ROW(),"") | AI87: =IF(AND($D87="Casa Letizia",$G87=""),ROW(),"") | AJ87: =IF(AND($D87="Casa nel Borgo",$G87=""),ROW(),"") | AK87: =IF(AND($D87="Via San Rocco",$G87=""),ROW(),"") | AL87: =IF(AND($D87="Via Cavour",$G87=""),ROW(),"") | AM87: =IF(AND($D87="Miramare",$G87=""),ROW(),"") | AN87: =IF(AND($D87="Agantonio",$G87=""),ROW(),"") | AO87: =IF(AND($D87="Casa Bella Gialla",$G87=""),ROW(),"") | AP87: =IF(AND($D87="Casa Verde Oliva",$G87=""),ROW(),"") | AQ87: =IF(AND($D87="Casa Nicola",$G87=""),ROW(),"") | AR87: =IF(AND($D87="White Cottage",$G87=""),ROW(),"") | AS87: =IF(AND($D87="Villa Nella",$G87=""),ROW(),"") | AT87: =IF(AND($D87="Nel Cuore di Lanciano",$G87<>""),ROW(),"") -> 87 | AU87: =IF(AND($D87="Nel Cuore di Lanciano",$G87=""),ROW(),"")
A88: 46251 | B88: 46258 | C88: =IF(A88<>"",B88-A88,"") -> 7 | D88: Sotto la Quercia | E88: Gennaro Pascale | F88: 4 ad | G88: booking.com | H88: 1648.43 | I88: =IF(AND(H88<>"",C88<>"",C88<>0),H88/C88,"") -> 235.49 | J88: =IF(AND(ISNUMBER(SEARCH("booking",G88)),OR(D88="Via San Rocco",D88="Via Cavour")),H88*0.165,IF(ISNUMBER(SEARCH("airbnb",G88)),H88*0.155,IF(ISNUMBER(SEARCH("booking",G88)),H88*0.15,""))) -> 247.2645 | M88: =IF(H88<>"",H88*0.25,"") -> 412.1075 | S88: =IF(AND($D88="Sotto la Quercia",$G88<>""),ROW(),"") -> 88 | T88: =IF($D88="Villa Elena",COUNTIF($D$3:$D88,"Villa Elena"),"") | U88: =IF(AND($D88="Casa Letizia",$G88<>""),ROW(),"") | V88: =IF(AND($D88="Casa nel Borgo",$G88<>""),ROW(),"") | W88: =IF(AND($D88="Via San Rocco",$G88<>""),ROW(),"") | X88: =IF(AND($D88="Via Cavour",$G88<>""),ROW(),"") | Y88: =IF(AND($D88="Miramare",$G88<>""),ROW(),"") | Z88: =IF(AND($D88="Agantonio",$G88<>""),ROW(),"") | AA88: =IF(AND($D88="Casa Bella Gialla",$G88<>""),ROW(),"") | AB88: =IF(AND($D88="Casa Verde Oliva",$G88<>""),ROW(),"") | AC88: =IF(AND($D88="Casa Nicola",$G88<>""),ROW(),"") | AD88: =IF(AND($D88="White Cottage",$G88<>""),ROW(),"") | AE88: =IF(AND($D88="Villa Nella",$G88<>""),ROW(),"") | AF88: =IF(AND($D88="Villa Elena",$G88<>""),ROW(),"") | AG88: =IF(AND($D88="Sotto la Quercia",$G88=""),ROW(),"") | AH88: =IF(AND($D88="Villa Elena",$G88=""),ROW(),"") | AI88: =IF(AND($D88="Casa Letizia",$G88=""),ROW(),"") | AJ88: =IF(AND($D88="Casa nel Borgo",$G88=""),ROW(),"") | AK88: =IF(AND($D88="Via San Rocco",$G88=""),ROW(),"") | AL88: =IF(AND($D88="Via Cavour",$G88=""),ROW(),"") | AM88: =IF(AND($D88="Miramare",$G88=""),ROW(),"") | AN88: =IF(AND($D88="Agantonio",$G88=""),ROW(),"") | AO88: =IF(AND($D88="Casa Bella Gialla",$G88=""),ROW(),"") | AP88: =IF(AND($D88="Casa Verde Oliva",$G88=""),ROW(),"") | AQ88: =IF(AND($D88="Casa Nicola",$G88=""),ROW(),"") | AR88: =IF(AND($D88="White Cottage",$G88=""),ROW(),"") | AS88: =IF(AND($D88="Villa Nella",$G88=""),ROW(),"") | AT88: =IF(AND($D88="Nel Cuore di Lanciano",$G88<>""),ROW(),"") | AU88: =IF(AND($D88="Nel Cuore di Lanciano",$G88=""),ROW(),"")
A89: 46252 | B89: 46259 | C89: =IF(A89<>"",B89-A89,"") -> 7 | D89: Via San Rocco | E89: Giulia Attenasio | F89: 2 ad | G89: booking.com | H89: 936.99 | I89: =IF(AND(H89<>"",C89<>"",C89<>0),H89/C89,"") -> 133.85571 | J89: =IF(AND(ISNUMBER(SEARCH("booking",G89)),OR(D89="Via San Rocco",D89="Via Cavour")),H89*0.165,IF(ISNUMBER(SEARCH("airbnb",G89)),H89*0.155,IF(ISNUMBER(SEARCH("booking",G89)),H89*0.15,""))) -> 154.60335 | M89: =IF(H89<>"",H89*0.1,"") -> 93.699 | S89: =IF(AND($D89="Sotto la Quercia",$G89<>""),ROW(),"") | T89: =IF($D89="Villa Elena",COUNTIF($D$3:$D89,"Villa Elena"),"") | U89: =IF(AND($D89="Casa Letizia",$G89<>""),ROW(),"") | V89: =IF(AND($D89="Casa nel Borgo",$G89<>""),ROW(),"") | W89: =IF(AND($D89="Via San Rocco",$G89<>""),ROW(),"") -> 89 | X89: =IF(AND($D89="Via Cavour",$G89<>""),ROW(),"") | Y89: =IF(AND($D89="Miramare",$G89<>""),ROW(),"") | Z89: =IF(AND($D89="Agantonio",$G89<>""),ROW(),"") | AA89: =IF(AND($D89="Casa Bella Gialla",$G89<>""),ROW(),"") | AB89: =IF(AND($D89="Casa Verde Oliva",$G89<>""),ROW(),"") | AC89: =IF(AND($D89="Casa Nicola",$G89<>""),ROW(),"") | AD89: =IF(AND($D89="White Cottage",$G89<>""),ROW(),"") | AE89: =IF(AND($D89="Villa Nella",$G89<>""),ROW(),"") | AF89: =IF(AND($D89="Villa Elena",$G89<>""),ROW(),"") | AG89: =IF(AND($D89="Sotto la Quercia",$G89=""),ROW(),"") | AH89: =IF(AND($D89="Villa Elena",$G89=""),ROW(),"") | AI89: =IF(AND($D89="Casa Letizia",$G89=""),ROW(),"") | AJ89: =IF(AND($D89="Casa nel Borgo",$G89=""),ROW(),"") | AK89: =IF(AND($D89="Via San Rocco",$G89=""),ROW(),"") | AL89: =IF(AND($D89="Via Cavour",$G89=""),ROW(),"") | AM89: =IF(AND($D89="Miramare",$G89=""),ROW(),"") | AN89: =IF(AND($D89="Agantonio",$G89=""),ROW(),"") | AO89: =IF(AND($D89="Casa Bella Gialla",$G89=""),ROW(),"") | AP89: =IF(AND($D89="Casa Verde Oliva",$G89=""),ROW(),"") | AQ89: =IF(AND($D89="Casa Nicola",$G89=""),ROW(),"") | AR89: =IF(AND($D89="White Cottage",$G89=""),ROW(),"") | AS89: =IF(AND($D89="Villa Nella",$G89=""),ROW(),"") | AT89: =IF(AND($D89="Nel Cuore di Lanciano",$G89<>""),ROW(),"") | AU89: =IF(AND($D89="Nel Cuore di Lanciano",$G89=""),ROW(),"")
A90: 46253 | B90: 46260 | C90: =IF(A90<>"",B90-A90,"") -> 7 | D90: Miramare | E90: Lara Olivieri | F90: 2 ad + 2 b | G90: booking.com | H90: 1003.6 | I90: =IF(AND(H90<>"",C90<>"",C90<>0),H90/C90,"") -> 143.37143 | J90: =IF(AND(ISNUMBER(SEARCH("booking",G90)),OR(D90="Via San Rocco",D90="Via Cavour")),H90*0.165,IF(ISNUMBER(SEARCH("airbnb",G90)),H90*0.155,IF(ISNUMBER(SEARCH("booking",G90)),H90*0.15,""))) -> 150.54 | M90: =IF(H90<>"",H90*0.25,"") -> 250.9 | S90: =IF(AND($D90="Sotto la Quercia",$G90<>""),ROW(),"") | T90: =IF($D90="Villa Elena",COUNTIF($D$3:$D90,"Villa Elena"),"") | U90: =IF(AND($D90="Casa Letizia",$G90<>""),ROW(),"") | V90: =IF(AND($D90="Casa nel Borgo",$G90<>""),ROW(),"") | W90: =IF(AND($D90="Via San Rocco",$G90<>""),ROW(),"") | X90: =IF(AND($D90="Via Cavour",$G90<>""),ROW(),"") | Y90: =IF(AND($D90="Miramare",$G90<>""),ROW(),"") -> 90 | Z90: =IF(AND($D90="Agantonio",$G90<>""),ROW(),"") | AA90: =IF(AND($D90="Casa Bella Gialla",$G90<>""),ROW(),"") | AB90: =IF(AND($D90="Casa Verde Oliva",$G90<>""),ROW(),"") | AC90: =IF(AND($D90="Casa Nicola",$G90<>""),ROW(),"") | AD90: =IF(AND($D90="White Cottage",$G90<>""),ROW(),"") | AE90: =IF(AND($D90="Villa Nella",$G90<>""),ROW(),"") | AF90: =IF(AND($D90="Villa Elena",$G90<>""),ROW(),"") | AG90: =IF(AND($D90="Sotto la Quercia",$G90=""),ROW(),"") | AH90: =IF(AND($D90="Villa Elena",$G90=""),ROW(),"") | AI90: =IF(AND($D90="Casa Letizia",$G90=""),ROW(),"") | AJ90: =IF(AND($D90="Casa nel Borgo",$G90=""),ROW(),"") | AK90: =IF(AND($D90="Via San Rocco",$G90=""),ROW(),"") | AL90: =IF(AND($D90="Via Cavour",$G90=""),ROW(),"") | AM90: =IF(AND($D90="Miramare",$G90=""),ROW(),"") | AN90: =IF(AND($D90="Agantonio",$G90=""),ROW(),"") | AO90: =IF(AND($D90="Casa Bella Gialla",$G90=""),ROW(),"") | AP90: =IF(AND($D90="Casa Verde Oliva",$G90=""),ROW(),"") | AQ90: =IF(AND($D90="Casa Nicola",$G90=""),ROW(),"") | AR90: =IF(AND($D90="White Cottage",$G90=""),ROW(),"") | AS90: =IF(AND($D90="Villa Nella",$G90=""),ROW(),"") | AT90: =IF(AND($D90="Nel Cuore di Lanciano",$G90<>""),ROW(),"") | AU90: =IF(AND($D90="Nel Cuore di Lanciano",$G90=""),ROW(),"")
A91: 46253 | B91: 46257 | C91: =IF(A91<>"",B91-A91,"") -> 4 | D91: Villa Elena | E91: Silvia Marinelli | F91: 2 ad | G91: booking.com | H91: 521.64 | I91: =IF(AND(H91<>"",C91<>"",C91<>0),H91/C91,"") -> 130.41 | J91: =IF(AND(ISNUMBER(SEARCH("booking",G91)),OR(D91="Via San Rocco",D91="Via Cavour")),H91*0.165,IF(ISNUMBER(SEARCH("airbnb",G91)),H91*0.155,IF(ISNUMBER(SEARCH("booking",G91)),H91*0.15,""))) -> 78.246 | M91: =IF(H91<>"",H91*0.25,"") -> 130.41 | S91: =IF(AND($D91="Sotto la Quercia",$G91<>""),ROW(),"") | T91: =IF($D91="Villa Elena",COUNTIF($D$3:$D91,"Villa Elena"),"") -> 8 | U91: =IF(AND($D91="Casa Letizia",$G91<>""),ROW(),"") | V91: =IF(AND($D91="Casa nel Borgo",$G91<>""),ROW(),"") | W91: =IF(AND($D91="Via San Rocco",$G91<>""),ROW(),"") | X91: =IF(AND($D91="Via Cavour",$G91<>""),ROW(),"") | Y91: =IF(AND($D91="Miramare",$G91<>""),ROW(),"") | Z91: =IF(AND($D91="Agantonio",$G91<>""),ROW(),"") | AA91: =IF(AND($D91="Casa Bella Gialla",$G91<>""),ROW(),"") | AB91: =IF(AND($D91="Casa Verde Oliva",$G91<>""),ROW(),"") | AC91: =IF(AND($D91="Casa Nicola",$G91<>""),ROW(),"") | AD91: =IF(AND($D91="White Cottage",$G91<>""),ROW(),"") | AE91: =IF(AND($D91="Villa Nella",$G91<>""),ROW(),"") | AF91: =IF(AND($D91="Villa Elena",$G91<>""),ROW(),"") -> 91 | AG91: =IF(AND($D91="Sotto la Quercia",$G91=""),ROW(),"") | AH91: =IF(AND($D91="Villa Elena",$G91=""),ROW(),"") | AI91: =IF(AND($D91="Casa Letizia",$G91=""),ROW(),"") | AJ91: =IF(AND($D91="Casa nel Borgo",$G91=""),ROW(),"") | AK91: =IF(AND($D91="Via San Rocco",$G91=""),ROW(),"") | AL91: =IF(AND($D91="Via Cavour",$G91=""),ROW(),"") | AM91: =IF(AND($D91="Miramare",$G91=""),ROW(),"") | AN91: =IF(AND($D91="Agantonio",$G91=""),ROW(),"") | AO91: =IF(AND($D91="Casa Bella Gialla",$G91=""),ROW(),"") | AP91: =IF(AND($D91="Casa Verde Oliva",$G91=""),ROW(),"") | AQ91: =IF(AND($D91="Casa Nicola",$G91=""),ROW(),"") | AR91: =IF(AND($D91="White Cottage",$G91=""),ROW(),"") | AS91: =IF(AND($D91="Villa Nella",$G91=""),ROW(),"") | AT91: =IF(AND($D91="Nel Cuore di Lanciano",$G91<>""),ROW(),"") | AU91: =IF(AND($D91="Nel Cuore di Lanciano",$G91=""),ROW(),"")
A92: 46254 | B92: 46259 | C92: =IF(A92<>"",B92-A92,"") -> 5 | D92: Casa nel Borgo | E92: Margaret Aitken | F92: 2 ad | G92: booking.com | H92: 451.97 | I92: =IF(AND(H92<>"",C92<>"",C92<>0),H92/C92,"") -> 90.394 | J92: =IF(AND(ISNUMBER(SEARCH("booking",G92)),OR(D92="Via San Rocco",D92="Via Cavour")),H92*0.165,IF(ISNUMBER(SEARCH("airbnb",G92)),H92*0.155,IF(ISNUMBER(SEARCH("booking",G92)),H92*0.15,""))) -> 67.7955 | K92: da prendere | M92: =IF(H92<>"",H92*0.25,"") -> 112.9925 | R92: NON RIMBORSABILE | S92: =IF(AND($D92="Sotto la Quercia",$G92<>""),ROW(),"") | T92: =IF($D92="Villa Elena",COUNTIF($D$3:$D92,"Villa Elena"),"") | U92: =IF(AND($D92="Casa Letizia",$G92<>""),ROW(),"") | V92: =IF(AND($D92="Casa nel Borgo",$G92<>""),ROW(),"") -> 92 | W92: =IF(AND($D92="Via San Rocco",$G92<>""),ROW(),"") | X92: =IF(AND($D92="Via Cavour",$G92<>""),ROW(),"") | Y92: =IF(AND($D92="Miramare",$G92<>""),ROW(),"") | Z92: =IF(AND($D92="Agantonio",$G92<>""),ROW(),"") | AA92: =IF(AND($D92="Casa Bella Gialla",$G92<>""),ROW(),"") | AB92: =IF(AND($D92="Casa Verde Oliva",$G92<>""),ROW(),"") | AC92: =IF(AND($D92="Casa Nicola",$G92<>""),ROW(),"") | AD92: =IF(AND($D92="White Cottage",$G92<>""),ROW(),"") | AE92: =IF(AND($D92="Villa Nella",$G92<>""),ROW(),"") | AF92: =IF(AND($D92="Villa Elena",$G92<>""),ROW(),"") | AG92: =IF(AND($D92="Sotto la Quercia",$G92=""),ROW(),"") | AH92: =IF(AND($D92="Villa Elena",$G92=""),ROW(),"") | AI92: =IF(AND($D92="Casa Letizia",$G92=""),ROW(),"") | AJ92: =IF(AND($D92="Casa nel Borgo",$G92=""),ROW(),"") | AK92: =IF(AND($D92="Via San Rocco",$G92=""),ROW(),"") | AL92: =IF(AND($D92="Via Cavour",$G92=""),ROW(),"") | AM92: =IF(AND($D92="Miramare",$G92=""),ROW(),"") | AN92: =IF(AND($D92="Agantonio",$G92=""),ROW(),"") | AO92: =IF(AND($D92="Casa Bella Gialla",$G92=""),ROW(),"") | AP92: =IF(AND($D92="Casa Verde Oliva",$G92=""),ROW(),"") | AQ92: =IF(AND($D92="Casa Nicola",$G92=""),ROW(),"") | AR92: =IF(AND($D92="White Cottage",$G92=""),ROW(),"") | AS92: =IF(AND($D92="Villa Nella",$G92=""),ROW(),"") | AT92: =IF(AND($D92="Nel Cuore di Lanciano",$G92<>""),ROW(),"") | AU92: =IF(AND($D92="Nel Cuore di Lanciano",$G92=""),ROW(),"")
A93: 46254 | B93: 46263 | C93: =IF(A93<>"",B93-A93,"") -> 9 | D93: Agantonio | E93: Alessandra Galli | F93: 1 ad 2 b | G93: booking.com | H93: 1084.23 | I93: =IF(AND(H93<>"",C93<>"",C93<>0),H93/C93,"") -> 120.47 | J93: =IF(AND(ISNUMBER(SEARCH("booking",G93)),OR(D93="Via San Rocco",D93="Via Cavour")),H93*0.165,IF(ISNUMBER(SEARCH("airbnb",G93)),H93*0.155,IF(ISNUMBER(SEARCH("booking",G93)),H93*0.15,""))) -> 162.6345 | M93: =IF(H93<>"",H93*0.25,"") -> 271.0575 | S93: =IF(AND($D93="Sotto la Quercia",$G93<>""),ROW(),"") | T93: =IF($D93="Villa Elena",COUNTIF($D$3:$D93,"Villa Elena"),"") | U93: =IF(AND($D93="Casa Letizia",$G93<>""),ROW(),"") | V93: =IF(AND($D93="Casa nel Borgo",$G93<>""),ROW(),"") | W93: =IF(AND($D93="Via San Rocco",$G93<>""),ROW(),"") | X93: =IF(AND($D93="Via Cavour",$G93<>""),ROW(),"") | Y93: =IF(AND($D93="Miramare",$G93<>""),ROW(),"") | Z93: =IF(AND($D93="Agantonio",$G93<>""),ROW(),"") -> 93 | AA93: =IF(AND($D93="Casa Bella Gialla",$G93<>""),ROW(),"") | AB93: =IF(AND($D93="Casa Verde Oliva",$G93<>""),ROW(),"") | AC93: =IF(AND($D93="Casa Nicola",$G93<>""),ROW(),"") | AD93: =IF(AND($D93="White Cottage",$G93<>""),ROW(),"") | AE93: =IF(AND($D93="Villa Nella",$G93<>""),ROW(),"") | AF93: =IF(AND($D93="Villa Elena",$G93<>""),ROW(),"") | AG93: =IF(AND($D93="Sotto la Quercia",$G93=""),ROW(),"") | AH93: =IF(AND($D93="Villa Elena",$G93=""),ROW(),"") | AI93: =IF(AND($D93="Casa Letizia",$G93=""),ROW(),"") | AJ93: =IF(AND($D93="Casa nel Borgo",$G93=""),ROW(),"") | AK93: =IF(AND($D93="Via San Rocco",$G93=""),ROW(),"") | AL93: =IF(AND($D93="Via Cavour",$G93=""),ROW(),"") | AM93: =IF(AND($D93="Miramare",$G93=""),ROW(),"") | AN93: =IF(AND($D93="Agantonio",$G93=""),ROW(),"") | AO93: =IF(AND($D93="Casa Bella Gialla",$G93=""),ROW(),"") | AP93: =IF(AND($D93="Casa Verde Oliva",$G93=""),ROW(),"") | AQ93: =IF(AND($D93="Casa Nicola",$G93=""),ROW(),"") | AR93: =IF(AND($D93="White Cottage",$G93=""),ROW(),"") | AS93: =IF(AND($D93="Villa Nella",$G93=""),ROW(),"") | AT93: =IF(AND($D93="Nel Cuore di Lanciano",$G93<>""),ROW(),"") | AU93: =IF(AND($D93="Nel Cuore di Lanciano",$G93=""),ROW(),"")
A94: 46255 | B94: 46257 | C94: =IF(A94<>"",B94-A94,"") -> 2 | D94: Via Cavour | E94: Sonia Bartolomeo | F94: 2 ad | G94: booking.com | H94: 257.72 | I94: =IF(AND(H94<>"",C94<>"",C94<>0),H94/C94,"") -> 128.86 | J94: =IF(AND(ISNUMBER(SEARCH("booking",G94)),OR(D94="Via San Rocco",D94="Via Cavour")),H94*0.165,IF(ISNUMBER(SEARCH("airbnb",G94)),H94*0.155,IF(ISNUMBER(SEARCH("booking",G94)),H94*0.15,""))) -> 42.5238 | M94: =IF(H94<>"",H94*0.1,"") -> 25.772 | S94: =IF(AND($D94="Sotto la Quercia",$G94<>""),ROW(),"") | T94: =IF($D94="Villa Elena",COUNTIF($D$3:$D94,"Villa Elena"),"") | U94: =IF(AND($D94="Casa Letizia",$G94<>""),ROW(),"") | V94: =IF(AND($D94="Casa nel Borgo",$G94<>""),ROW(),"") | W94: =IF(AND($D94="Via San Rocco",$G94<>""),ROW(),"") | X94: =IF(AND($D94="Via Cavour",$G94<>""),ROW(),"") -> 94 | Y94: =IF(AND($D94="Miramare",$G94<>""),ROW(),"") | Z94: =IF(AND($D94="Agantonio",$G94<>""),ROW(),"") | AA94: =IF(AND($D94="Casa Bella Gialla",$G94<>""),ROW(),"") | AB94: =IF(AND($D94="Casa Verde Oliva",$G94<>""),ROW(),"") | AC94: =IF(AND($D94="Casa Nicola",$G94<>""),ROW(),"") | AD94: =IF(AND($D94="White Cottage",$G94<>""),ROW(),"") | AE94: =IF(AND($D94="Villa Nella",$G94<>""),ROW(),"") | AF94: =IF(AND($D94="Villa Elena",$G94<>""),ROW(),"") | AG94: =IF(AND($D94="Sotto la Quercia",$G94=""),ROW(),"") | AH94: =IF(AND($D94="Villa Elena",$G94=""),ROW(),"") | AI94: =IF(AND($D94="Casa Letizia",$G94=""),ROW(),"") | AJ94: =IF(AND($D94="Casa nel Borgo",$G94=""),ROW(),"") | AK94: =IF(AND($D94="Via San Rocco",$G94=""),ROW(),"") | AL94: =IF(AND($D94="Via Cavour",$G94=""),ROW(),"") | AM94: =IF(AND($D94="Miramare",$G94=""),ROW(),"") | AN94: =IF(AND($D94="Agantonio",$G94=""),ROW(),"") | AO94: =IF(AND($D94="Casa Bella Gialla",$G94=""),ROW(),"") | AP94: =IF(AND($D94="Casa Verde Oliva",$G94=""),ROW(),"") | AQ94: =IF(AND($D94="Casa Nicola",$G94=""),ROW(),"") | AR94: =IF(AND($D94="White Cottage",$G94=""),ROW(),"") | AS94: =IF(AND($D94="Villa Nella",$G94=""),ROW(),"") | AT94: =IF(AND($D94="Nel Cuore di Lanciano",$G94<>""),ROW(),"") | AU94: =IF(AND($D94="Nel Cuore di Lanciano",$G94=""),ROW(),"")
A95: 46256 | B95: 46265 | C95: =IF(A95<>"",B95-A95,"") -> 9 | D95: Casa Letizia | E95: Valeria Rossi | F95: 4 ad | G95: booking.com | H95: 1301.67 | I95: =IF(AND(H95<>"",C95<>"",C95<>0),H95/C95,"") -> 144.63 | J95: =IF(AND(ISNUMBER(SEARCH("booking",G95)),OR(D95="Via San Rocco",D95="Via Cavour")),H95*0.165,IF(ISNUMBER(SEARCH("airbnb",G95)),H95*0.155,IF(ISNUMBER(SEARCH("booking",G95)),H95*0.15,""))) -> 195.2505 | M95: =IF(H95<>"",H95*0.25,"") -> 325.4175 | S95: =IF(AND($D95="Sotto la Quercia",$G95<>""),ROW(),"") | T95: =IF($D95="Villa Elena",COUNTIF($D$3:$D95,"Villa Elena"),"") | U95: =IF(AND($D95="Casa Letizia",$G95<>""),ROW(),"") -> 95 | V95: =IF(AND($D95="Casa nel Borgo",$G95<>""),ROW(),"") | W95: =IF(AND($D95="Via San Rocco",$G95<>""),ROW(),"") | X95: =IF(AND($D95="Via Cavour",$G95<>""),ROW(),"") | Y95: =IF(AND($D95="Miramare",$G95<>""),ROW(),"") | Z95: =IF(AND($D95="Agantonio",$G95<>""),ROW(),"") | AA95: =IF(AND($D95="Casa Bella Gialla",$G95<>""),ROW(),"") | AB95: =IF(AND($D95="Casa Verde Oliva",$G95<>""),ROW(),"") | AC95: =IF(AND($D95="Casa Nicola",$G95<>""),ROW(),"") | AD95: =IF(AND($D95="White Cottage",$G95<>""),ROW(),"") | AE95: =IF(AND($D95="Villa Nella",$G95<>""),ROW(),"") | AF95: =IF(AND($D95="Villa Elena",$G95<>""),ROW(),"") | AG95: =IF(AND($D95="Sotto la Quercia",$G95=""),ROW(),"") | AH95: =IF(AND($D95="Villa Elena",$G95=""),ROW(),"") | AI95: =IF(AND($D95="Casa Letizia",$G95=""),ROW(),"") | AJ95: =IF(AND($D95="Casa nel Borgo",$G95=""),ROW(),"") | AK95: =IF(AND($D95="Via San Rocco",$G95=""),ROW(),"") | AL95: =IF(AND($D95="Via Cavour",$G95=""),ROW(),"") | AM95: =IF(AND($D95="Miramare",$G95=""),ROW(),"") | AN95: =IF(AND($D95="Agantonio",$G95=""),ROW(),"") | AO95: =IF(AND($D95="Casa Bella Gialla",$G95=""),ROW(),"") | AP95: =IF(AND($D95="Casa Verde Oliva",$G95=""),ROW(),"") | AQ95: =IF(AND($D95="Casa Nicola",$G95=""),ROW(),"") | AR95: =IF(AND($D95="White Cottage",$G95=""),ROW(),"") | AS95: =IF(AND($D95="Villa Nella",$G95=""),ROW(),"") | AT95: =IF(AND($D95="Nel Cuore di Lanciano",$G95<>""),ROW(),"") | AU95: =IF(AND($D95="Nel Cuore di Lanciano",$G95=""),ROW(),"")
A96: 46257 | B96: 46262 | C96: =IF(A96<>"",B96-A96,"") -> 5 | D96: Casa Verde Oliva | E96: Bruno Chiosi | F96: 2 ad | G96: booking.com | H96: 590.94 | I96: =IF(AND(H96<>"",C96<>"",C96<>0),H96/C96,"") -> 118.188 | J96: =IF(AND(ISNUMBER(SEARCH("booking",G96)),OR(D96="Via San Rocco",D96="Via Cavour")),H96*0.165,IF(ISNUMBER(SEARCH("airbnb",G96)),H96*0.155,IF(ISNUMBER(SEARCH("booking",G96)),H96*0.15,""))) -> 88.641 | M96: =IF(H96<>"",H96*0.25,"") -> 147.735 | S96: =IF(AND($D96="Sotto la Quercia",$G96<>""),ROW(),"") | T96: =IF($D96="Villa Elena",COUNTIF($D$3:$D96,"Villa Elena"),"") | U96: =IF(AND($D96="Casa Letizia",$G96<>""),ROW(),"") | V96: =IF(AND($D96="Casa nel Borgo",$G96<>""),ROW(),"") | W96: =IF(AND($D96="Via San Rocco",$G96<>""),ROW(),"") | X96: =IF(AND($D96="Via Cavour",$G96<>""),ROW(),"") | Y96: =IF(AND($D96="Miramare",$G96<>""),ROW(),"") | Z96: =IF(AND($D96="Agantonio",$G96<>""),ROW(),"") | AA96: =IF(AND($D96="Casa Bella Gialla",$G96<>""),ROW(),"") | AB96: =IF(AND($D96="Casa Verde Oliva",$G96<>""),ROW(),"") -> 96 | AC96: =IF(AND($D96="Casa Nicola",$G96<>""),ROW(),"") | AD96: =IF(AND($D96="White Cottage",$G96<>""),ROW(),"") | AE96: =IF(AND($D96="Villa Nella",$G96<>""),ROW(),"") | AF96: =IF(AND($D96="Villa Elena",$G96<>""),ROW(),"") | AG96: =IF(AND($D96="Sotto la Quercia",$G96=""),ROW(),"") | AH96: =IF(AND($D96="Villa Elena",$G96=""),ROW(),"") | AI96: =IF(AND($D96="Casa Letizia",$G96=""),ROW(),"") | AJ96: =IF(AND($D96="Casa nel Borgo",$G96=""),ROW(),"") | AK96: =IF(AND($D96="Via San Rocco",$G96=""),ROW(),"") | AL96: =IF(AND($D96="Via Cavour",$G96=""),ROW(),"") | AM96: =IF(AND($D96="Miramare",$G96=""),ROW(),"") | AN96: =IF(AND($D96="Agantonio",$G96=""),ROW(),"") | AO96: =IF(AND($D96="Casa Bella Gialla",$G96=""),ROW(),"") | AP96: =IF(AND($D96="Casa Verde Oliva",$G96=""),ROW(),"") | AQ96: =IF(AND($D96="Casa Nicola",$G96=""),ROW(),"") | AR96: =IF(AND($D96="White Cottage",$G96=""),ROW(),"") | AS96: =IF(AND($D96="Villa Nella",$G96=""),ROW(),"") | AT96: =IF(AND($D96="Nel Cuore di Lanciano",$G96<>""),ROW(),"") | AU96: =IF(AND($D96="Nel Cuore di Lanciano",$G96=""),ROW(),"")
A97: 46258 | B97: 46264 | C97: =IF(A97<>"",B97-A97,"") -> 6 | D97: casa nicola | E97: Alessandro De Ascaniis | F97: 3 ad | G97: booking.com | H97: 730.8 | I97: =IF(AND(H97<>"",C97<>"",C97<>0),H97/C97,"") -> 121.8 | J97: =IF(AND(ISNUMBER(SEARCH("booking",G97)),OR(D97="Via San Rocco",D97="Via Cavour")),H97*0.165,IF(ISNUMBER(SEARCH("airbnb",G97)),H97*0.155,IF(ISNUMBER(SEARCH("booking",G97)),H97*0.15,""))) -> 109.62 | M97: =IF(H97<>"",H97*0.25,"") -> 182.7 | S97: =IF(AND($D97="Sotto la Quercia",$G97<>""),ROW(),"") | T97: =IF($D97="Villa Elena",COUNTIF($D$3:$D97,"Villa Elena"),"") | U97: =IF(AND($D97="Casa Letizia",$G97<>""),ROW(),"") | V97: =IF(AND($D97="Casa nel Borgo",$G97<>""),ROW(),"") | W97: =IF(AND($D97="Via San Rocco",$G97<>""),ROW(),"") | X97: =IF(AND($D97="Via Cavour",$G97<>""),ROW(),"") | Y97: =IF(AND($D97="Miramare",$G97<>""),ROW(),"") | Z97: =IF(AND($D97="Agantonio",$G97<>""),ROW(),"") | AA97: =IF(AND($D97="Casa Bella Gialla",$G97<>""),ROW(),"") | AB97: =IF(AND($D97="Casa Verde Oliva",$G97<>""),ROW(),"") | AC97: =IF(AND($D97="Casa Nicola",$G97<>""),ROW(),"") -> 97 | AD97: =IF(AND($D97="White Cottage",$G97<>""),ROW(),"") | AE97: =IF(AND($D97="Villa Nella",$G97<>""),ROW(),"") | AF97: =IF(AND($D97="Villa Elena",$G97<>""),ROW(),"") | AG97: =IF(AND($D97="Sotto la Quercia",$G97=""),ROW(),"") | AH97: =IF(AND($D97="Villa Elena",$G97=""),ROW(),"") | AI97: =IF(AND($D97="Casa Letizia",$G97=""),ROW(),"") | AJ97: =IF(AND($D97="Casa nel Borgo",$G97=""),ROW(),"") | AK97: =IF(AND($D97="Via San Rocco",$G97=""),ROW(),"") | AL97: =IF(AND($D97="Via Cavour",$G97=""),ROW(),"") | AM97: =IF(AND($D97="Miramare",$G97=""),ROW(),"") | AN97: =IF(AND($D97="Agantonio",$G97=""),ROW(),"") | AO97: =IF(AND($D97="Casa Bella Gialla",$G97=""),ROW(),"") | AP97: =IF(AND($D97="Casa Verde Oliva",$G97=""),ROW(),"") | AQ97: =IF(AND($D97="Casa Nicola",$G97=""),ROW(),"") | AR97: =IF(AND($D97="White Cottage",$G97=""),ROW(),"") | AS97: =IF(AND($D97="Villa Nella",$G97=""),ROW(),"") | AT97: =IF(AND($D97="Nel Cuore di Lanciano",$G97<>""),ROW(),"") | AU97: =IF(AND($D97="Nel Cuore di Lanciano",$G97=""),ROW(),"")
